{"code":0,"msg":"ok","data":{"id":"cm412c3s9002z8ha4zmzb12ei","title":"橙色浅色现代电商运营人力教师简历","width":595,"height":842,"priceStrategy":"free","snapshot":"https://cdn.aitubiao.com/resource/templates/cm2opn33c004dm6pjboet1jzl.png","createdAt":"2024-11-28T08:38:49.639Z","updatedAt":"2025-06-11T09:05:51.122Z","dimension":"简历","tags":[{"id":"cmbrq5yya0029cj3ea0trfyno","name":"市场","dimensionId":18,"dimension":{"scopes":["resume"]}},{"id":"cmbrq5yy90021cj3eaifp2k60","name":"产品经理","dimensionId":18,"dimension":{"scopes":["resume"]}},{"id":"cmbrq5yy90022cj3e44zefv2z","name":"行政/人力","dimensionId":18,"dimension":{"scopes":["resume"]}},{"id":"cmbrq5yy90023cj3ebuldadpn","name":"运营/销售","dimensionId":18,"dimension":{"scopes":["resume"]}},{"id":"cmbrq5yya0026cj3e7ejm01bd","name":"财务","dimensionId":18,"dimension":{"scopes":["resume"]}},{"id":"cmbrq5yya0027cj3ea65b80ad","name":"教师","dimensionId":18,"dimension":{"scopes":["resume"]}},{"id":"cmbrq5yya0028cj3e8w0w003c","name":"咨询","dimensionId":18,"dimension":{"scopes":["resume"]}}],"author":{"id":"clzb5ewqk0003j5yc55w8zbuk","name":"coveabc","avatar":null,"tier":{"id":"ckxtg2o0j00019zue6g8t68kc","name":"会员用户"}},"data":{"pages":{"66d2cabb8G6BQz8gZ8wYgSK1aJvGaM":{"id":"66d2cabb8G6BQz8gZ8wYgSK1aJvGaM","name":"Productivity Tools","size":{"width":595,"height":842},"theme":{"colors":[]},"locked":false,"orders":["67204a00x5mLjC4iCibF3AhojUpkgx","672049a2fvmvMmoDdiSM39QSSsRBvH","66d2d0e44xeosGaZnwX4MjiC2HnA6U","66d2d525qx1eY7UwTcje1o5MP7xHsx","66d2d66b74Tt2byzHG5qdwwma6PpRX","66d2d68168Ntn1fVjUaqhUkpg5Rdt5","66d2d857dM2VK7e9rntBzjUF8hdkAe","66d2d858uXJ75tD8N5aX8YEYhSUBU2","66d2d874n2BLopDtVA5cjbT47ssUvw","66d2d889vWmNAhQfMkP24Df4CGNjJK","66d2dba2rNMFS2RBDA1ZM7SqcoBoRM","66d2dc8cp3p5BDzSLJFirnLr3QphDN","66d2dce5rGxtV63teoaJecszgV4X4y","66d2dceack4Cp16tAn5hM4y3uVv9od","672053cafpj29vRLrnoXj3wXHcskXa","672053cewJeUVsAvSmZvhfc1GeGTti","66d2e246vq1JxiwTSpHsbSCx4S289Q","66d2deec6aPVZg85fkvojQzWbeDb3z","66d2df177KbU1XkMvZtN2fzPvapY9j","66d2e76ewGoGuuim3VL3bqeikVfJMQ","67204a4baY6Aave9hexgKVSAo2BKQr","67204acdohtuuH7aQfriLs9c6WPoNE","67204e80soszkLuzGbXWgjwwWcpcBE","67204ed24Phnx8YQHdKjH9A19W7Ten","67204ee6mXdpwoaJ2PdMMGQL5dy9yC"],"visible":true,"elements":{"66d2d0e44xeosGaZnwX4MjiC2HnA6U":{"id":"66d2d0e44xeosGaZnwX4MjiC2HnA6U","size":{"width":602.11,"height":105.32},"scale":1,"locked":false,"pageId":"66d2cabb8G6BQz8gZ8wYgSK1aJvGaM","parent":null,"setting":{"alt":"image.png","fit":"fill","src":"https://cdn.core.editorup.com/image/clzc0sxkd0000vb55bza2s5iw/cm0huc62g005ejuo6fydb7g6p/1725092066338_image.png","flip":"none","size":{"width":703.205761316872,"height":107},"scale":1.0936166546595587,"stroke":{"show":false,"color":{"color":"#000000","opacity":1},"style":"solid","width":1,"radius":0},"opacity":1,"version":1730169244772,"transform":{"scale":1,"translate":{"x":-54.1028806584361,"y":-10.7}},"adjustment":{"src":"https://cdn.core.editorup.com/image/clzb5ewqk0003j5yc55w8zbuk/cm2opn33c004dm6pjboet1jzl/66d2d0e44xeosGaZnwX4MjiC2HnA6U_1730169243107_zi2zal4xx1.png","color":{"hue":0,"blur":0,"noise":0,"enable":false,"contrast":0,"pixelate":1,"vibrance":0,"brightness":0,"saturation":0},"filter":{"sepia":false,"emboss":false,"enable":true,"invert":false,"brownie":true,"sharpen":false,"vintage":false,"polaroid":false,"grayscale":false,"blackwhite":false,"kodachrome":false,"technicolor":false},"shadow":{"blur":10,"show":false,"angle":45,"color":{"color":"#000000","opacity":0.5},"offset":10},"version":"7a0adfbf182e3428b8befda1c1a01612df1ea46367092b0adf8b556a482737d5"}},"visible":true,"category":"image","position":{"x":-0.74,"y":-3.72},"rotation":0},"66d2d525qx1eY7UwTcje1o5MP7xHsx":{"id":"66d2d525qx1eY7UwTcje1o5MP7xHsx","size":{"width":88.91,"height":41.49},"scale":1,"locked":false,"pageId":"66d2cabb8G6BQz8gZ8wYgSK1aJvGaM","parent":null,"setting":{"scale":0.823204202678362,"version":1730170877133,"autoSize":true,"direction":"horizontal-tb","paragraphs":[{"chars":[{"text":"王小镝","color":{"color":"#2a2a2a","opacity":1},"fontSize":36,"fontStyle":"normal","fontFamily":"Misans 加粗","fontWeight":"normal","textStroke":false,"letterSpacing":0,"textDecoration":[],"textStrokeColor":{"color":"#44e296","opacity":1},"textStrokeWidth":10}],"textAlign":"center","lineHeight":1.4}],"textShadow":false,"textShadowBlur":10,"textShadowAngle":45,"textShadowColor":{"color":"#000000","opacity":0.4},"textShadowOffset":10},"visible":true,"category":"text","position":{"x":35.31,"y":137.7},"rotation":0},"66d2d5e26vBpwaQNFaMDj4RQRitVGa":{"id":"66d2d5e26vBpwaQNFaMDj4RQRitVGa","size":{"width":3.79,"height":18.01},"scale":1,"locked":true,"pageId":"66d2cabb8G6BQz8gZ8wYgSK1aJvGaM","parent":"66d2d66b74Tt2byzHG5qdwwma6PpRX","setting":{"blur":0,"fill":{"color":"#ffffff","opacity":1},"path":"M0,0 L256,0 L256,256 L0,256 Z","scale":0.26625,"shadow":{"blur":4,"show":false,"type":"outer","angle":90,"color":{"color":"#000000","opacity":0.25},"behind":true,"offset":4},"stroke":{"color":{"color":"#000","opacity":1},"style":"solid","width":0,"radius":0},"version":1725093368025},"visible":true,"category":"shape","position":{"x":0,"y":2.195},"rotation":0},"66d2d617bMnU1wSuMcGXae8d42ySpK":{"id":"66d2d617bMnU1wSuMcGXae8d42ySpK","size":{"width":144,"height":22.39},"scale":1,"locked":true,"pageId":"66d2cabb8G6BQz8gZ8wYgSK1aJvGaM","parent":"66d2d66b74Tt2byzHG5qdwwma6PpRX","setting":{"scale":1,"version":1725093454729,"autoSize":true,"direction":"horizontal-tb","paragraphs":[{"chars":[{"text":"求职意向：电商运营","color":{"color":"#ffffff","opacity":1},"fontSize":16,"fontStyle":"normal","fontFamily":"Misans 中等","fontWeight":"normal","textStroke":false,"letterSpacing":0,"textDecoration":[],"textStrokeColor":{"color":"#44e296","opacity":1},"textStrokeWidth":10}],"textAlign":"center","lineHeight":1.4}],"textShadow":false,"textShadowBlur":10,"textShadowAngle":45,"textShadowColor":{"color":"#000000","opacity":0.4},"textShadowOffset":10},"visible":true,"category":"text","position":{"x":13.67,"y":0},"rotation":0},"66d2d66b74Tt2byzHG5qdwwma6PpRX":{"id":"66d2d66b74Tt2byzHG5qdwwma6PpRX","size":{"width":194.02,"height":27.56},"scale":1,"locked":false,"pageId":"66d2cabb8G6BQz8gZ8wYgSK1aJvGaM","parent":null,"setting":{"scale":1.2305172231801407,"version":1725093483756,"children":["66d2d5e26vBpwaQNFaMDj4RQRitVGa","66d2d617bMnU1wSuMcGXae8d42ySpK"]},"visible":true,"category":"group","position":{"x":351.07,"y":44},"rotation":0},"66d2d68168Ntn1fVjUaqhUkpg5Rdt5":{"id":"66d2d68168Ntn1fVjUaqhUkpg5Rdt5","size":{"width":465.38,"height":55.2},"scale":1,"locked":false,"pageId":"66d2cabb8G6BQz8gZ8wYgSK1aJvGaM","parent":null,"setting":{"scale":2.464003687924778,"version":1730169623857,"autoSize":true,"direction":"horizontal-tb","paragraphs":[{"chars":[{"text":"MY RESUME","color":{"color":"#ffffff","opacity":0.1},"fontSize":16,"fontStyle":"normal","fontFamily":"Misans 中等","fontWeight":"normal","textStroke":false,"letterSpacing":0,"textDecoration":[],"textStrokeColor":{"color":"#44e296","opacity":1},"textStrokeWidth":10}],"textAlign":"center","lineHeight":1.4}],"textShadow":false,"textShadowBlur":10,"textShadowAngle":45,"textShadowColor":{"color":"#000000","opacity":0.4},"textShadowOffset":10},"visible":true,"category":"text","position":{"x":248.17,"y":60.88},"rotation":0},"66d2d73dccvF7gD4cd4PxmnXMuQggz":{"id":"66d2d73dccvF7gD4cd4PxmnXMuQggz","size":{"width":56,"height":19.59},"scale":1,"locked":false,"pageId":"66d2cabb8G6BQz8gZ8wYgSK1aJvGaM","parent":"66d2d857dM2VK7e9rntBzjUF8hdkAe","setting":{"scale":1,"version":1725093990052,"autoSize":true,"direction":"horizontal-tb","paragraphs":[{"chars":[{"text":"基本信息","color":{"color":"#4f5765","opacity":1},"fontSize":14,"fontStyle":"normal","fontFamily":"Misans 中等","fontWeight":"normal","textStroke":false,"letterSpacing":0,"textDecoration":[],"textStrokeColor":{"color":"#44e296","opacity":1},"textStrokeWidth":10}],"textAlign":"start","lineHeight":1.4}],"textShadow":false,"textShadowBlur":10,"textShadowAngle":45,"textShadowColor":{"color":"#000000","opacity":0.4},"textShadowOffset":10},"visible":true,"category":"text","position":{"x":22.28,"y":0.22},"rotation":0},"66d2d766k5X1PvdesGQQnymKVWsogb":{"id":"66d2d766k5X1PvdesGQQnymKVWsogb","size":{"width":11.6,"height":18.4},"scale":1,"locked":false,"pageId":"66d2cabb8G6BQz8gZ8wYgSK1aJvGaM","parent":"66d2d857dM2VK7e9rntBzjUF8hdkAe","setting":{"blur":0,"fill":{"color":"#f7941e","opacity":1},"path":"M0,0 L256,0 L256,256 L0,256 Z","scale":0.1318,"shadow":{"blur":4,"show":false,"type":"outer","angle":90,"color":{"color":"#000000","opacity":0.25},"behind":true,"offset":4},"stroke":{"color":{"color":"#f7941e","opacity":1},"style":"solid","width":0,"radius":2},"version":1725093802127},"visible":true,"category":"shape","position":{"x":0,"y":0.0900000000000034},"rotation":0},"66d2d7afgQiURbJ4CVkRGFVZKPdgC1":{"id":"66d2d7afgQiURbJ4CVkRGFVZKPdgC1","size":{"width":11.6,"height":12.01},"scale":1,"locked":false,"pageId":"66d2cabb8G6BQz8gZ8wYgSK1aJvGaM","parent":"66d2d857dM2VK7e9rntBzjUF8hdkAe","setting":{"blur":0,"fill":{"color":"#4f5765","opacity":1},"path":"M0,0 L256,0 L256,256 L0,256 Z","scale":0.1318,"shadow":{"blur":4,"show":false,"type":"outer","angle":90,"color":{"color":"#000000","opacity":0.25},"behind":true,"offset":4},"stroke":{"color":{"color":"#f7941e","opacity":1},"style":"solid","width":0,"radius":2},"version":1725093826305},"visible":true,"category":"shape","position":{"x":3.98999999999999,"y":0},"rotation":0},"66d2d857dM2VK7e9rntBzjUF8hdkAe":{"id":"66d2d857dM2VK7e9rntBzjUF8hdkAe","size":{"width":78.28,"height":19.81},"scale":1,"locked":false,"pageId":"66d2cabb8G6BQz8gZ8wYgSK1aJvGaM","parent":null,"setting":{"scale":1,"version":1725093975283,"children":["66d2d73dccvF7gD4cd4PxmnXMuQggz","66d2d766k5X1PvdesGQQnymKVWsogb","66d2d7afgQiURbJ4CVkRGFVZKPdgC1"]},"visible":true,"category":"group","position":{"x":27.25,"y":203.15},"rotation":0},"66d2d858uXJ75tD8N5aX8YEYhSUBU2":{"id":"66d2d858uXJ75tD8N5aX8YEYhSUBU2","size":{"width":78.28,"height":19.81},"scale":1,"locked":false,"pageId":"66d2cabb8G6BQz8gZ8wYgSK1aJvGaM","parent":null,"setting":{"scale":1,"version":1725093975283,"children":["66d2d858v1XnE4iB3szjeN8EHj8LdQ","66d2d858xaEczYaGiFbyc4wqV5XktK","66d2d858uj39KK6CET9r1uUzBfLnkK"]},"visible":true,"category":"group","position":{"x":282.89,"y":158.3},"rotation":0},"66d2d858uj39KK6CET9r1uUzBfLnkK":{"id":"66d2d858uj39KK6CET9r1uUzBfLnkK","size":{"width":11.6,"height":12.01},"scale":1,"locked":false,"pageId":"66d2cabb8G6BQz8gZ8wYgSK1aJvGaM","parent":"66d2d858uXJ75tD8N5aX8YEYhSUBU2","setting":{"blur":0,"fill":{"color":"#4f5765","opacity":1},"path":"M0,0 L256,0 L256,256 L0,256 Z","scale":0.1318,"shadow":{"blur":4,"show":false,"type":"outer","angle":90,"color":{"color":"#000000","opacity":0.25},"behind":true,"offset":4},"stroke":{"color":{"color":"#f7941e","opacity":1},"style":"solid","width":0,"radius":2},"version":1725093826305},"visible":true,"category":"shape","position":{"x":3.98999999999999,"y":0},"rotation":0},"66d2d858v1XnE4iB3szjeN8EHj8LdQ":{"id":"66d2d858v1XnE4iB3szjeN8EHj8LdQ","size":{"width":56,"height":19.59},"scale":1,"locked":false,"pageId":"66d2cabb8G6BQz8gZ8wYgSK1aJvGaM","parent":"66d2d858uXJ75tD8N5aX8YEYhSUBU2","setting":{"scale":1,"version":1725093999024,"autoSize":true,"direction":"horizontal-tb","paragraphs":[{"chars":[{"text":"教育背景","color":{"color":"#4f5765","opacity":1},"fontSize":14,"fontStyle":"normal","fontFamily":"Misans 中等","fontWeight":"normal","textStroke":false,"letterSpacing":0,"textDecoration":[],"textStrokeColor":{"color":"#44e296","opacity":1},"textStrokeWidth":10}],"textAlign":"start","lineHeight":1.4}],"textShadow":false,"textShadowBlur":10,"textShadowAngle":45,"textShadowColor":{"color":"#000000","opacity":0.4},"textShadowOffset":10},"visible":true,"category":"text","position":{"x":22.28,"y":0.22},"rotation":0},"66d2d858xaEczYaGiFbyc4wqV5XktK":{"id":"66d2d858xaEczYaGiFbyc4wqV5XktK","size":{"width":11.6,"height":18.4},"scale":1,"locked":false,"pageId":"66d2cabb8G6BQz8gZ8wYgSK1aJvGaM","parent":"66d2d858uXJ75tD8N5aX8YEYhSUBU2","setting":{"blur":0,"fill":{"color":"#f7941e","opacity":1},"path":"M0,0 L256,0 L256,256 L0,256 Z","scale":0.1318,"shadow":{"blur":4,"show":false,"type":"outer","angle":90,"color":{"color":"#000000","opacity":0.25},"behind":true,"offset":4},"stroke":{"color":{"color":"#f7941e","opacity":1},"style":"solid","width":0,"radius":2},"version":1725093802127},"visible":true,"category":"shape","position":{"x":0,"y":0.0900000000000034},"rotation":0},"66d2d874cdHQoQmYx2Z3d4Bh43oF9o":{"id":"66d2d874cdHQoQmYx2Z3d4Bh43oF9o","size":{"width":11.6,"height":12.01},"scale":1,"locked":false,"pageId":"66d2cabb8G6BQz8gZ8wYgSK1aJvGaM","parent":"66d2d874n2BLopDtVA5cjbT47ssUvw","setting":{"blur":0,"fill":{"color":"#4f5765","opacity":1},"path":"M0,0 L256,0 L256,256 L0,256 Z","scale":0.1318,"shadow":{"blur":4,"show":false,"type":"outer","angle":90,"color":{"color":"#000000","opacity":0.25},"behind":true,"offset":4},"stroke":{"color":{"color":"#f7941e","opacity":1},"style":"solid","width":0,"radius":2},"version":1725093826305},"visible":true,"category":"shape","position":{"x":3.98999999999999,"y":0},"rotation":0},"66d2d874hccmKUk7jS2Kyb15dFGHhp":{"id":"66d2d874hccmKUk7jS2Kyb15dFGHhp","size":{"width":56,"height":19.59},"scale":1,"locked":false,"pageId":"66d2cabb8G6BQz8gZ8wYgSK1aJvGaM","parent":"66d2d874n2BLopDtVA5cjbT47ssUvw","setting":{"scale":1,"version":1725094023195,"autoSize":true,"direction":"horizontal-tb","paragraphs":[{"chars":[{"text":"从业经历","color":{"color":"#4f5765","opacity":1},"fontSize":14,"fontStyle":"normal","fontFamily":"Misans 中等","fontWeight":"normal","textStroke":false,"letterSpacing":0,"textDecoration":[],"textStrokeColor":{"color":"#44e296","opacity":1},"textStrokeWidth":10}],"textAlign":"start","lineHeight":1.4}],"textShadow":false,"textShadowBlur":10,"textShadowAngle":45,"textShadowColor":{"color":"#000000","opacity":0.4},"textShadowOffset":10},"visible":true,"category":"text","position":{"x":22.28,"y":0.22},"rotation":0},"66d2d874n2BLopDtVA5cjbT47ssUvw":{"id":"66d2d874n2BLopDtVA5cjbT47ssUvw","size":{"width":78.28,"height":19.81},"scale":1,"locked":false,"pageId":"66d2cabb8G6BQz8gZ8wYgSK1aJvGaM","parent":null,"setting":{"scale":1,"version":1725093975283,"children":["66d2d874hccmKUk7jS2Kyb15dFGHhp","66d2d874rFw6gkMKCqN92iqVwD6ob3","66d2d874cdHQoQmYx2Z3d4Bh43oF9o"]},"visible":true,"category":"group","position":{"x":283.2,"y":284.96},"rotation":0},"66d2d874rFw6gkMKCqN92iqVwD6ob3":{"id":"66d2d874rFw6gkMKCqN92iqVwD6ob3","size":{"width":11.6,"height":18.4},"scale":1,"locked":false,"pageId":"66d2cabb8G6BQz8gZ8wYgSK1aJvGaM","parent":"66d2d874n2BLopDtVA5cjbT47ssUvw","setting":{"blur":0,"fill":{"color":"#f7941e","opacity":1},"path":"M0,0 L256,0 L256,256 L0,256 Z","scale":0.1318,"shadow":{"blur":4,"show":false,"type":"outer","angle":90,"color":{"color":"#000000","opacity":0.25},"behind":true,"offset":4},"stroke":{"color":{"color":"#f7941e","opacity":1},"style":"solid","width":0,"radius":2},"version":1725093802127},"visible":true,"category":"shape","position":{"x":0,"y":0.0900000000000034},"rotation":0},"66d2d8897PcdqPwWbtogGtyw2modLU":{"id":"66d2d8897PcdqPwWbtogGtyw2modLU","size":{"width":11.6,"height":18.4},"scale":1,"locked":false,"pageId":"66d2cabb8G6BQz8gZ8wYgSK1aJvGaM","parent":"66d2d889vWmNAhQfMkP24Df4CGNjJK","setting":{"blur":0,"fill":{"color":"#f7941e","opacity":1},"path":"M0,0 L256,0 L256,256 L0,256 Z","scale":0.1318,"shadow":{"blur":4,"show":false,"type":"outer","angle":90,"color":{"color":"#000000","opacity":0.25},"behind":true,"offset":4},"stroke":{"color":{"color":"#f7941e","opacity":1},"style":"solid","width":0,"radius":2},"version":1725093802127},"visible":true,"category":"shape","position":{"x":0,"y":0.0900000000000034},"rotation":0},"66d2d889d4BE211MACwpjBtqdG5Aoc":{"id":"66d2d889d4BE211MACwpjBtqdG5Aoc","size":{"width":56,"height":19.59},"scale":1,"locked":false,"pageId":"66d2cabb8G6BQz8gZ8wYgSK1aJvGaM","parent":"66d2d889vWmNAhQfMkP24Df4CGNjJK","setting":{"scale":1,"version":1725095136306,"autoSize":true,"direction":"horizontal-tb","paragraphs":[{"chars":[{"text":"自我评价","color":{"color":"#4f5765","opacity":1},"fontSize":14,"fontStyle":"normal","fontFamily":"Misans 中等","fontWeight":"normal","textStroke":false,"letterSpacing":0,"textDecoration":[],"textStrokeColor":{"color":"#44e296","opacity":1},"textStrokeWidth":10}],"textAlign":"start","lineHeight":1.4}],"textShadow":false,"textShadowBlur":10,"textShadowAngle":45,"textShadowColor":{"color":"#000000","opacity":0.4},"textShadowOffset":10},"visible":true,"category":"text","position":{"x":22.28,"y":0.22},"rotation":0},"66d2d889fUHqfqgTzjkbPEAeSiR5EX":{"id":"66d2d889fUHqfqgTzjkbPEAeSiR5EX","size":{"width":11.6,"height":12.01},"scale":1,"locked":false,"pageId":"66d2cabb8G6BQz8gZ8wYgSK1aJvGaM","parent":"66d2d889vWmNAhQfMkP24Df4CGNjJK","setting":{"blur":0,"fill":{"color":"#4f5765","opacity":1},"path":"M0,0 L256,0 L256,256 L0,256 Z","scale":0.1318,"shadow":{"blur":4,"show":false,"type":"outer","angle":90,"color":{"color":"#000000","opacity":0.25},"behind":true,"offset":4},"stroke":{"color":{"color":"#f7941e","opacity":1},"style":"solid","width":0,"radius":2},"version":1725093826305},"visible":true,"category":"shape","position":{"x":3.98999999999999,"y":0},"rotation":0},"66d2d889vWmNAhQfMkP24Df4CGNjJK":{"id":"66d2d889vWmNAhQfMkP24Df4CGNjJK","size":{"width":78.28,"height":19.81},"scale":1,"locked":false,"pageId":"66d2cabb8G6BQz8gZ8wYgSK1aJvGaM","parent":null,"setting":{"scale":1,"version":1725093975283,"children":["66d2d889d4BE211MACwpjBtqdG5Aoc","66d2d8897PcdqPwWbtogGtyw2modLU","66d2d889fUHqfqgTzjkbPEAeSiR5EX"]},"visible":true,"category":"group","position":{"x":283.75,"y":661.09},"rotation":0},"66d2daa8uxE8YazkGFyA8oF4aezedc":{"id":"66d2daa8uxE8YazkGFyA8oF4aezedc","size":{"width":225.3,"height":16.8},"scale":1,"locked":false,"pageId":"66d2cabb8G6BQz8gZ8wYgSK1aJvGaM","parent":"66d2dba2rNMFS2RBDA1ZM7SqcoBoRM","setting":{"scale":1,"version":1725098091984,"autoSize":true,"direction":"horizontal-tb","paragraphs":[{"chars":[{"text":"20xx.x-20xx.x    镝数大学    新闻学专业","color":{"color":"#f7941e","opacity":1},"fontSize":12,"fontStyle":"normal","fontFamily":"Misans 加粗","fontWeight":"normal","textStroke":false,"letterSpacing":0,"textDecoration":[],"textStrokeColor":{"color":"#44e296","opacity":1},"textStrokeWidth":10}],"textAlign":"start","lineHeight":1.4}],"textShadow":false,"textShadowBlur":10,"textShadowAngle":45,"textShadowColor":{"color":"#000000","opacity":0.4},"textShadowOffset":10},"visible":true,"category":"text","position":{"x":0.59,"y":0},"rotation":0},"66d2db48ijs4ocb8zwhLXT1GvA9ASU":{"id":"66d2db48ijs4ocb8zwhLXT1GvA9ASU","size":{"width":256.69,"height":50.39},"scale":1,"locked":false,"pageId":"66d2cabb8G6BQz8gZ8wYgSK1aJvGaM","parent":"66d2dba2rNMFS2RBDA1ZM7SqcoBoRM","setting":{"scale":1,"version":1725094750193,"autoSize":false,"direction":"horizontal-tb","paragraphs":[{"chars":[{"text":"主修课程:《传播学概论》《广告学》《摄影基础》《photoshop教程》《Premiere与视频非线性编辑》","color":{"color":"#666666","opacity":1},"fontSize":12,"fontStyle":"normal","fontFamily":"Misans 中等","fontWeight":"normal","textStroke":false,"letterSpacing":0,"textDecoration":[],"textStrokeColor":{"color":"#44e296","opacity":1},"textStrokeWidth":10}],"textAlign":"start","lineHeight":1.4}],"textShadow":false,"textShadowBlur":10,"textShadowAngle":45,"textShadowColor":{"color":"#000000","opacity":0.4},"textShadowOffset":10},"visible":true,"category":"text","position":{"x":0,"y":25.13},"rotation":0},"66d2db70fGoR57T7YwAEx36vgtGsQ5":{"id":"66d2db70fGoR57T7YwAEx36vgtGsQ5","size":{"width":256.69,"height":67.19},"scale":1,"locked":false,"pageId":"66d2cabb8G6BQz8gZ8wYgSK1aJvGaM","parent":"66d2dc8cp3p5BDzSLJFirnLr3QphDN","setting":{"scale":1,"version":1725094996457,"autoSize":false,"direction":"horizontal-tb","paragraphs":[{"chars":[{"text":"1.负责直通车、钻展、淘客、搜索、微信、老客户等推广方式在推广节奏里面的时间节点、花费、引流力度等的安排，确保推广方案执行效果。","color":{"color":"#666666","opacity":1},"fontSize":12,"fontStyle":"normal","fontFamily":"Misans 中等","fontWeight":"normal","textStroke":false,"letterSpacing":0,"textDecoration":[],"textStrokeColor":{"color":"#44e296","opacity":1},"textStrokeWidth":10}],"textAlign":"start","lineHeight":1.4}],"textShadow":false,"textShadowBlur":10,"textShadowAngle":45,"textShadowColor":{"color":"#000000","opacity":0.4},"textShadowOffset":10},"visible":true,"category":"text","position":{"x":0,"y":25.1300000000001},"rotation":0},"66d2db70rzY87N9Dyb8DWwsAHYnTAP":{"id":"66d2db70rzY87N9Dyb8DWwsAHYnTAP","size":{"width":264.48,"height":16.8},"scale":1,"locked":false,"pageId":"66d2cabb8G6BQz8gZ8wYgSK1aJvGaM","parent":"66d2dc8cp3p5BDzSLJFirnLr3QphDN","setting":{"scale":1,"version":1725098085327,"autoSize":true,"direction":"horizontal-tb","paragraphs":[{"chars":[{"text":"20xx.x-20xx.x    xx科技有限公司    店主兼运营","color":{"color":"#f7941e","opacity":1},"fontSize":12,"fontStyle":"normal","fontFamily":"Misans 加粗","fontWeight":"normal","textStroke":false,"letterSpacing":0,"textDecoration":[],"textStrokeColor":{"color":"#44e296","opacity":1},"textStrokeWidth":10}],"textAlign":"start","lineHeight":1.4}],"textShadow":false,"textShadowBlur":10,"textShadowAngle":45,"textShadowColor":{"color":"#000000","opacity":0.4},"textShadowOffset":10},"visible":true,"category":"text","position":{"x":0.59,"y":0},"rotation":0},"66d2dba2rNMFS2RBDA1ZM7SqcoBoRM":{"id":"66d2dba2rNMFS2RBDA1ZM7SqcoBoRM","size":{"width":256.69,"height":75.52},"scale":1,"locked":false,"pageId":"66d2cabb8G6BQz8gZ8wYgSK1aJvGaM","parent":null,"setting":{"scale":1,"version":1725094818992,"children":["66d2daa8uxE8YazkGFyA8oF4aezedc","66d2db48ijs4ocb8zwhLXT1GvA9ASU"]},"visible":true,"category":"group","position":{"x":282.83,"y":188},"rotation":0},"66d2dbeceQYcBBwB3rUypR6wrwwMHF":{"id":"66d2dbeceQYcBBwB3rUypR6wrwwMHF","size":{"width":256.69,"height":33.6},"scale":1,"locked":false,"pageId":"66d2cabb8G6BQz8gZ8wYgSK1aJvGaM","parent":"66d2dceack4Cp16tAn5hM4y3uVv9od","setting":{"scale":1,"version":1725095065185,"autoSize":false,"direction":"horizontal-tb","paragraphs":[{"chars":[{"text":"1.负责品牌方向视频策划，内容稿撰写，视频广告文案的创意构思，创意性视频广告方案策划。","color":{"color":"#666666","opacity":1},"fontSize":12,"fontStyle":"normal","fontFamily":"Misans 中等","fontWeight":"normal","textStroke":false,"letterSpacing":0,"textDecoration":[],"textStrokeColor":{"color":"#44e296","opacity":1},"textStrokeWidth":10}],"textAlign":"start","lineHeight":1.4}],"textShadow":false,"textShadowBlur":10,"textShadowAngle":45,"textShadowColor":{"color":"#000000","opacity":0.4},"textShadowOffset":10},"visible":true,"category":"text","position":{"x":0.140000000000043,"y":25.13},"rotation":0},"66d2dbecr8Cr63nEBNFg4gdAFRnatr":{"id":"66d2dbecr8Cr63nEBNFg4gdAFRnatr","size":{"width":264.48,"height":16.8},"scale":1,"locked":false,"pageId":"66d2cabb8G6BQz8gZ8wYgSK1aJvGaM","parent":"66d2dceack4Cp16tAn5hM4y3uVv9od","setting":{"scale":1,"version":1725098097746,"autoSize":true,"direction":"horizontal-tb","paragraphs":[{"chars":[{"text":"20xx.x-20xx.x    xx科技有限公司    短视频策划","color":{"color":"#f7941e","opacity":1},"fontSize":12,"fontStyle":"normal","fontFamily":"Misans 加粗","fontWeight":"normal","textStroke":false,"letterSpacing":0,"textDecoration":[],"textStrokeColor":{"color":"#44e296","opacity":1},"textStrokeWidth":10}],"textAlign":"start","lineHeight":1.4}],"textShadow":false,"textShadowBlur":10,"textShadowAngle":45,"textShadowColor":{"color":"#000000","opacity":0.4},"textShadowOffset":10},"visible":true,"category":"text","position":{"x":0.73,"y":0},"rotation":0},"66d2dc4e569cCyBbUq9B9yM4gNvFXB":{"id":"66d2dc4e569cCyBbUq9B9yM4gNvFXB","size":{"width":256.69,"height":33.6},"scale":1,"locked":false,"pageId":"66d2cabb8G6BQz8gZ8wYgSK1aJvGaM","parent":"66d2dc8cp3p5BDzSLJFirnLr3QphDN","setting":{"scale":1,"version":1725095021339,"autoSize":false,"direction":"horizontal-tb","paragraphs":[{"chars":[{"text":"3.负责月、季度店铺推广计划的花费、销量、产品线排名等的定位和规划。","color":{"color":"#666666","opacity":1},"fontSize":12,"fontStyle":"normal","fontFamily":"Misans 中等","fontWeight":"normal","textStroke":false,"letterSpacing":0,"textDecoration":[],"textStrokeColor":{"color":"#44e296","opacity":1},"textStrokeWidth":10}],"textAlign":"start","lineHeight":1.4}],"textShadow":false,"textShadowBlur":10,"textShadowAngle":45,"textShadowColor":{"color":"#000000","opacity":0.4},"textShadowOffset":10},"visible":true,"category":"text","position":{"x":0.129999999999995,"y":135.04},"rotation":0},"66d2dc4egwnr7GJpmGp6baxFnNKZwP":{"id":"66d2dc4egwnr7GJpmGp6baxFnNKZwP","size":{"width":256.69,"height":33.6},"scale":1,"locked":false,"pageId":"66d2cabb8G6BQz8gZ8wYgSK1aJvGaM","parent":"66d2dc8cp3p5BDzSLJFirnLr3QphDN","setting":{"scale":1,"version":1725095006501,"autoSize":false,"direction":"horizontal-tb","paragraphs":[{"chars":[{"text":"2.把控产品推广预算，并确保产品利润目标达成。","color":{"color":"#666666","opacity":1},"fontSize":12,"fontStyle":"normal","fontFamily":"Misans 中等","fontWeight":"normal","textStroke":false,"letterSpacing":0,"textDecoration":[],"textStrokeColor":{"color":"#44e296","opacity":1},"textStrokeWidth":10}],"textAlign":"start","lineHeight":1.4}],"textShadow":false,"textShadowBlur":10,"textShadowAngle":45,"textShadowColor":{"color":"#000000","opacity":0.4},"textShadowOffset":10},"visible":true,"category":"text","position":{"x":0.159999999999968,"y":96.5},"rotation":0},"66d2dc8cp3p5BDzSLJFirnLr3QphDN":{"id":"66d2dc8cp3p5BDzSLJFirnLr3QphDN","size":{"width":256.86,"height":168.63},"scale":1,"locked":false,"pageId":"66d2cabb8G6BQz8gZ8wYgSK1aJvGaM","parent":null,"setting":{"scale":1,"version":1725095052787,"children":["66d2db70fGoR57T7YwAEx36vgtGsQ5","66d2db70rzY87N9Dyb8DWwsAHYnTAP","66d2dc4egwnr7GJpmGp6baxFnNKZwP","66d2dc4e569cCyBbUq9B9yM4gNvFXB"]},"visible":true,"category":"group","position":{"x":283.04,"y":318.28},"rotation":0},"66d2dc941NUCBCbAyBwPSxJkW7pKDf":{"id":"66d2dc941NUCBCbAyBwPSxJkW7pKDf","size":{"width":256.69,"height":33.6},"scale":1,"locked":false,"pageId":"66d2cabb8G6BQz8gZ8wYgSK1aJvGaM","parent":"66d2dceack4Cp16tAn5hM4y3uVv9od","setting":{"scale":1,"version":1725095078769,"autoSize":false,"direction":"horizontal-tb","paragraphs":[{"chars":[{"text":"2.完成创意性视频广告的命题策划，撰写脚本和制定拍摄计划。","color":{"color":"#666666","opacity":1},"fontSize":12,"fontStyle":"normal","fontFamily":"Misans 中等","fontWeight":"normal","textStroke":false,"letterSpacing":0,"textDecoration":[],"textStrokeColor":{"color":"#44e296","opacity":1},"textStrokeWidth":10}],"textAlign":"start","lineHeight":1.4}],"textShadow":false,"textShadowBlur":10,"textShadowAngle":45,"textShadowColor":{"color":"#000000","opacity":0.4},"textShadowOffset":10},"visible":true,"category":"text","position":{"x":0,"y":65.54},"rotation":0},"66d2dc946Y3RGdSBLEMdR11LYFp3WW":{"id":"66d2dc946Y3RGdSBLEMdR11LYFp3WW","size":{"width":256.69,"height":33.6},"scale":1,"locked":false,"pageId":"66d2cabb8G6BQz8gZ8wYgSK1aJvGaM","parent":"66d2dceack4Cp16tAn5hM4y3uVv9od","setting":{"scale":1,"version":1725095084576,"autoSize":false,"direction":"horizontal-tb","paragraphs":[{"chars":[{"text":"3.对产品的卖点做出创意性的表达，运用符合美学观感的镜头表达。","color":{"color":"#666666","opacity":1},"fontSize":12,"fontStyle":"normal","fontFamily":"Misans 中等","fontWeight":"normal","textStroke":false,"letterSpacing":0,"textDecoration":[],"textStrokeColor":{"color":"#44e296","opacity":1},"textStrokeWidth":10}],"textAlign":"start","lineHeight":1.4}],"textShadow":false,"textShadowBlur":10,"textShadowAngle":45,"textShadowColor":{"color":"#000000","opacity":0.4},"textShadowOffset":10},"visible":true,"category":"text","position":{"x":0.200000000000045,"y":104.23},"rotation":0},"66d2dce5rGxtV63teoaJecszgV4X4y":{"id":"66d2dce5rGxtV63teoaJecszgV4X4y","size":{"width":256.69,"height":100.78},"scale":1,"locked":false,"pageId":"66d2cabb8G6BQz8gZ8wYgSK1aJvGaM","parent":null,"setting":{"scale":1,"version":1725095164477,"autoSize":false,"direction":"horizontal-tb","paragraphs":[{"chars":[{"text":"本人了解互联网社交产品的屈性，有意愿在电商行业长期发展。对于时尚产品有较为准确的审美把握能力，了解轻熟的用户网购的心理和习惯。有强烈的自我革新与学习意识，乐于面对变化，工作积极主动，善于沟通协调。抗压能力好，心态积极阳光，做事细心沉稳负责任。","color":{"color":"#666666","opacity":1},"fontSize":12,"fontStyle":"normal","fontFamily":"Misans 中等","fontWeight":"normal","textStroke":false,"letterSpacing":0,"textDecoration":[],"textStrokeColor":{"color":"#44e296","opacity":1},"textStrokeWidth":10}],"textAlign":"start","lineHeight":1.4}],"textShadow":false,"textShadowBlur":10,"textShadowAngle":45,"textShadowColor":{"color":"#000000","opacity":0.4},"textShadowOffset":10},"visible":true,"category":"text","position":{"x":283.6,"y":687.75},"rotation":0},"66d2dceack4Cp16tAn5hM4y3uVv9od":{"id":"66d2dceack4Cp16tAn5hM4y3uVv9od","size":{"width":256.89,"height":137.82},"scale":1,"locked":false,"pageId":"66d2cabb8G6BQz8gZ8wYgSK1aJvGaM","parent":null,"setting":{"scale":1,"version":1725095146572,"children":["66d2dbeceQYcBBwB3rUypR6wrwwMHF","66d2dbecr8Cr63nEBNFg4gdAFRnatr","66d2dc941NUCBCbAyBwPSxJkW7pKDf","66d2dc946Y3RGdSBLEMdR11LYFp3WW"]},"visible":true,"category":"group","position":{"x":284.37,"y":500.75},"rotation":0},"66d2dd52qy9oFW6pnYrCbyCpyfcdJY":{"id":"66d2dd52qy9oFW6pnYrCbyCpyfcdJY","size":{"width":155.24,"height":17.34},"scale":1,"locked":false,"pageId":"66d2cabb8G6BQz8gZ8wYgSK1aJvGaM","parent":"672053cafpj29vRLrnoXj3wXHcskXa","setting":{"blur":0,"fill":{"color":"#484a67","opacity":1},"path":"M0,0 L256,0 L256,256 L0,256 Z","scale":1,"shadow":{"blur":4,"show":false,"type":"outer","angle":90,"color":{"color":"#000000","opacity":0.25},"behind":true,"offset":4},"stroke":{"color":{"color":"#000","opacity":1},"style":"solid","width":0,"radius":12},"version":1730169023385},"version":2,"visible":true,"category":"shape","position":{"x":-7.105427357601002e-15,"y":0},"rotation":0,"updatedAt":1730171850890},"66d2deb9uvff55oYCZzaRt9De4bQbb":{"id":"66d2deb9uvff55oYCZzaRt9De4bQbb","size":{"width":72,"height":16.8},"scale":1,"locked":false,"pageId":"66d2cabb8G6BQz8gZ8wYgSK1aJvGaM","parent":"672053cafpj29vRLrnoXj3wXHcskXa","setting":{"scale":1,"version":1725095644081,"autoSize":true,"direction":"horizontal-tb","paragraphs":[{"chars":[{"text":"计算机二级证","color":{"color":"#ffffff","opacity":1},"fontSize":12,"fontStyle":"normal","fontFamily":"Misans 中等","fontWeight":"normal","textStroke":false,"letterSpacing":0,"textDecoration":[],"textStrokeColor":{"color":"#44e296","opacity":1},"textStrokeWidth":10}],"textAlign":"start","lineHeight":1.4}],"textShadow":false,"textShadowBlur":10,"textShadowAngle":45,"textShadowColor":{"color":"#000000","opacity":0.4},"textShadowOffset":10},"version":2,"visible":true,"category":"text","position":{"x":16.54,"y":0.22000000000002728},"rotation":0,"updatedAt":1730171850890},"66d2deec5UF38xhtvToAc7NbvV4nBt":{"id":"66d2deec5UF38xhtvToAc7NbvV4nBt","size":{"width":156.07,"height":17.34},"scale":1,"locked":false,"pageId":"66d2cabb8G6BQz8gZ8wYgSK1aJvGaM","parent":"672053cewJeUVsAvSmZvhfc1GeGTti","setting":{"blur":0,"fill":{"color":"#484a67","opacity":1},"path":"M0,0 L256,0 L256,256 L0,256 Z","scale":1,"shadow":{"blur":4,"show":false,"type":"outer","angle":90,"color":{"color":"#000000","opacity":0.25},"behind":true,"offset":4},"stroke":{"color":{"color":"#000","opacity":1},"style":"solid","width":0,"radius":12},"version":1730169032400},"version":2,"visible":true,"category":"shape","position":{"x":0,"y":0},"rotation":0,"updatedAt":1730171854893},"66d2deec6aPVZg85fkvojQzWbeDb3z":{"id":"66d2deec6aPVZg85fkvojQzWbeDb3z","size":{"width":3.16,"height":3.16},"scale":1,"locked":false,"pageId":"66d2cabb8G6BQz8gZ8wYgSK1aJvGaM","setting":{"blur":0,"fill":{"color":"#EEEEEE","opacity":1},"path":"M128,128 m-128,0 a128,128 0 1,0 256,0 a128,128 0 1,0 -256,0","scale":0.0157500000000001,"shadow":{"blur":4,"show":false,"type":"outer","angle":90,"color":{"color":"#000000","opacity":0.25},"behind":true,"offset":4},"stroke":{"color":{"color":"#000","opacity":1},"style":"solid","width":0,"radius":0},"version":1725095580056},"visible":true,"category":"shape","position":{"x":54.21000000000001,"y":442.31000000000006},"rotation":0},"66d2deecncmKuLGSbk1fomSGgecv91":{"id":"66d2deecncmKuLGSbk1fomSGgecv91","size":{"width":84,"height":16.8},"scale":1,"locked":false,"pageId":"66d2cabb8G6BQz8gZ8wYgSK1aJvGaM","parent":"672053cewJeUVsAvSmZvhfc1GeGTti","setting":{"scale":1,"version":1725095672200,"autoSize":true,"direction":"horizontal-tb","paragraphs":[{"chars":[{"text":"大学英语六级证","color":{"color":"#ffffff","opacity":1},"fontSize":12,"fontStyle":"normal","fontFamily":"Misans 中等","fontWeight":"normal","textStroke":false,"letterSpacing":0,"textDecoration":[],"textStrokeColor":{"color":"#44e296","opacity":1},"textStrokeWidth":10}],"textAlign":"start","lineHeight":1.4}],"textShadow":false,"textShadowBlur":10,"textShadowAngle":45,"textShadowColor":{"color":"#000000","opacity":0.4},"textShadowOffset":10},"version":2,"visible":true,"category":"text","position":{"x":15.579999999999998,"y":0.7300000000000182},"rotation":0,"updatedAt":1730171854893},"66d2df177KbU1XkMvZtN2fzPvapY9j":{"id":"66d2df177KbU1XkMvZtN2fzPvapY9j","size":{"width":3.16,"height":3.16},"scale":1,"locked":false,"pageId":"66d2cabb8G6BQz8gZ8wYgSK1aJvGaM","setting":{"blur":0,"fill":{"color":"#EEEEEE","opacity":1},"path":"M128,128 m-128,0 a128,128 0 1,0 256,0 a128,128 0 1,0 -256,0","scale":0.0157500000000001,"shadow":{"blur":4,"show":false,"type":"outer","angle":90,"color":{"color":"#000000","opacity":0.25},"behind":true,"offset":4},"stroke":{"color":{"color":"#000","opacity":1},"style":"solid","width":0,"radius":0},"version":1725095580056},"visible":true,"category":"shape","position":{"x":55.19,"y":473.17},"rotation":0},"66d2e246vq1JxiwTSpHsbSCx4S289Q":{"id":"66d2e246vq1JxiwTSpHsbSCx4S289Q","size":{"width":286.5,"height":214.25},"scale":1,"locked":false,"pageId":"66d2cabb8G6BQz8gZ8wYgSK1aJvGaM","parent":null,"setting":{"data":[[["技能","比例（%）"],["直通车使用","90"],["钻展使用","80"],["数据分析","70"],["PS","60"],["PR","55"],["AE","50"]]],"pipe":"key_value","props":{"map":[{"name":"名称","type":"","index":0,"function":"objCol","isLegend":true,"radiusIndex":0,"configurable":true},{"name":"值","type":"pie","index":1,"function":"vCol","isLegend":false,"angleIndex":0,"configurable":true}],"axis":{"show":true,"angleAxis":[{"grid":{"show":false,"type":"solid","color":{"color":"#D9D9D9","opacity":1},"width":1},"line":{"show":false,"color":{"color":"#4D4D4D","opacity":1},"width":1},"type":"value","label":{"show":false,"color":{"color":"#000000","opacity":1},"suffix":"","fontSize":12,"direction":"horizontal","fontFamily":"Misans 常规"},"range":[],"position":"outside","stepOfLabel":"auto"}],"radiusAxis":[{"grid":{"show":false,"type":"dotted","color":{"color":"#cccccc","opacity":0.6},"width":1},"line":{"show":false,"color":{"color":"#4D4D4D","opacity":1},"width":1},"type":"category","label":{"show":true,"angle":0,"color":{"color":"#2a2a2a","opacity":1},"fontSize":22.4786661794153,"fontFamily":"Misans 常规"},"position":"inside"}]},"fill":{"props":[{"color":{"color":"#ee5636","opacity":1},"border":{"type":"solid","color":{"color":"#ffffff","opacity":1},"width":0},"shadow":{"blur":1,"show":false,"type":"outer","angle":180,"color":{"color":"#0e26aa","opacity":0.5},"radius":3},"texture":{"url":""}},{"color":{"color":"#f89523","opacity":1},"border":{"type":"solid","color":{"color":"#ffffff","opacity":1},"width":0},"shadow":{"blur":1,"show":false,"type":"outer","angle":180,"color":{"color":"#0e26aa","opacity":0.5},"radius":3},"texture":{"url":""}}],"controlType":"gradient"},"type":"jade-jue","label":{"show":true,"overlap":false,"highlight":false,"numberLabel":{"show":false,"color":{"color":"#333333","opacity":1},"suffix":"","fontSize":12,"fontFamily":"Misans","positionChoice":"outside"}},"title":{"show":false,"subTitle":{"show":false,"text":"副标题","color":{"color":"#333333","opacity":1},"fontSize":16,"fontFamily":"Misans"},"mainTitle":{"show":true,"text":"基础柱状图","color":{"color":"#333333","opacity":1},"fontSize":24,"position":{"x":"center","y":"top"},"fontFamily":"Misans"}},"legend":{"show":false,"color":{"color":"#333333","opacity":1},"display":"horizontal","fontSize":12,"position":{"x":"right","y":"top"},"fontFamily":"Misans 常规"},"display":{"pie":{"border":{"type":"solid","color":null,"width":0,"radius":4},"drawAngle":270,"startAngle":0,"gapPercentage":55,"rotateDirection":"clockwise","innerRadiusRatio":0.2}},"padding":{"top":20,"left":24,"right":24,"bottom":23},"tooltip":true,"animation":{"loop":false,"show":false,"duration":2,"endPause":1,"moveStyle":null,"startDelay":0,"transition":false},"background":{"blur":0,"show":false,"color":{"color":"#ffffff","opacity":1},"border":{"radius":0},"texture":""},"numberFormat":{"decimalPlaces":null,"separatorType":"1000.00"}},"scale":0.40927856194308126,"version":1730169488868},"visible":true,"category":"chart","position":{"x":-43.7,"y":474.16},"rotation":0},"66d2e76ewGoGuuim3VL3bqeikVfJMQ":{"id":"66d2e76ewGoGuuim3VL3bqeikVfJMQ","size":{"width":105.63,"height":105.45},"scale":1,"locked":false,"pageId":"66d2cabb8G6BQz8gZ8wYgSK1aJvGaM","parent":null,"setting":{"alt":"img_v3_02e9_bd0bfd86-1b1c-42c0-af4f-0b5f1bb1c18g.jpg","fit":"fill","src":"https://cdn.core.editorup.com/image/clzc0sxkd0000vb55bza2s5iw/cm0huc62g005ejuo6fydb7g6p/1725097835617_img_v3_02e9_bd0bfd86-1b1c-42c0-af4f-0b5f1bb1c18g.jpg","flip":"none","size":{"width":476,"height":475.210613598673},"scale":0.22189865161684785,"stroke":{"show":true,"color":{"color":"#000000","opacity":1},"style":"solid","width":1,"radius":100},"opacity":1,"version":1725097867185,"transform":{"scale":1,"translate":{"x":0,"y":0}},"adjustment":{"src":"","color":{"hue":0,"blur":0,"noise":0,"enable":false,"contrast":0,"pixelate":1,"vibrance":0,"brightness":0,"saturation":0},"filter":{"sepia":false,"emboss":false,"enable":false,"invert":false,"brownie":false,"sharpen":false,"vintage":false,"polaroid":false,"grayscale":false,"blackwhite":false,"kodachrome":false,"technicolor":false},"shadow":{"blur":10,"show":false,"angle":45,"color":{"color":"#000000","opacity":0.5},"offset":10},"version":""}},"visible":true,"category":"image","position":{"x":28.44,"y":31.12},"rotation":0},"672049a2fvmvMmoDdiSM39QSSsRBvH":{"id":"672049a2fvmvMmoDdiSM39QSSsRBvH","size":{"width":324.95,"height":688.85},"scale":1,"locked":false,"pageId":"66d2cabb8G6BQz8gZ8wYgSK1aJvGaM","setting":{"blur":8,"fill":{"color":{"type":"linear","angle":90,"colorStops":[{"color":"#ffffff","offset":0.014563106796116505,"opacity":1},{"color":"#ffffff","offset":0.9854368932038835,"opacity":0.53}]},"opacity":1},"path":"M0,0 L256,0 L256,256 L0,256 Z","scale":1,"shadow":{"blur":4,"show":false,"type":"outer","angle":90,"color":{"color":"#000000","opacity":0.25},"behind":true,"offset":4},"stroke":{"color":{"color":"#000000","opacity":1},"style":"solid","width":0,"radius":8},"version":1730169334223},"visible":true,"category":"shape","position":{"x":259.87,"y":130.01},"rotation":0},"67204a00x5mLjC4iCibF3AhojUpkgx":{"id":"67204a00x5mLjC4iCibF3AhojUpkgx","size":{"width":324.95,"height":750.52},"scale":1,"locked":false,"pageId":"66d2cabb8G6BQz8gZ8wYgSK1aJvGaM","setting":{"blur":8,"fill":{"color":{"type":"linear","angle":90,"colorStops":[{"color":"#ffffff","offset":0.014563106796116505,"opacity":1},{"color":"#ffffff","offset":0.9854368932038835,"opacity":0.53}]},"opacity":1},"path":"M0,0 L256,0 L256,256 L0,256 Z","scale":1,"shadow":{"blur":4,"show":false,"type":"outer","angle":90,"color":{"color":"#000000","opacity":0.25},"behind":true,"offset":4},"stroke":{"color":{"color":"#000000","opacity":1},"style":"solid","width":0,"radius":24},"version":1730169366300},"visible":true,"category":"shape","position":{"x":-91.71,"y":67.94},"rotation":0},"67204a4baY6Aave9hexgKVSAo2BKQr":{"id":"67204a4baY6Aave9hexgKVSAo2BKQr","size":{"width":172.63,"height":83.98},"scale":1,"locked":false,"pageId":"66d2cabb8G6BQz8gZ8wYgSK1aJvGaM","setting":{"scale":1,"version":1730169426115,"autoSize":false,"direction":"horizontal-tb","paragraphs":[{"chars":[{"text":"性别：男\n年龄：22岁\n院校：镝数大学/本科\n电话：027-8888666\n邮箱：667788@dyclub.org\n","color":{"color":"#2a2a2a","opacity":1},"fontSize":12,"fontStyle":"normal","fontFamily":"Misans 中等","fontWeight":"normal","textStroke":false,"letterSpacing":0,"textDecoration":[],"textStrokeColor":{"color":"#44e296","opacity":1},"textStrokeWidth":10}],"textAlign":"start","lineHeight":1.4}],"textShadow":false,"defaultText":true,"textShadowBlur":10,"textShadowAngle":45,"textShadowColor":{"color":"#000000","opacity":0.4},"textShadowOffset":10},"visible":true,"category":"text","position":{"x":43.32,"y":234.23},"rotation":0},"67204acdohtuuH7aQfriLs9c6WPoNE":{"id":"67204acdohtuuH7aQfriLs9c6WPoNE","size":{"width":61.16,"height":61.16},"scale":1,"locked":false,"pageId":"66d2cabb8G6BQz8gZ8wYgSK1aJvGaM","setting":{"alt":"img_v3_02fu_e2ca913c-85de-477f-9ca1-cb48cbc219fg.jpg","fit":"fill","src":"https://cdn.core.editorup.com/image/clzb5ewqk0003j5yc55w8zbuk/cm2szq21e0003hekz1zd41qbm/1730106975342","flip":"none","size":{"width":430,"height":430},"scale":0.14222093023255816,"stroke":{"show":false,"color":{"color":"#000000","opacity":1},"style":"solid","width":1,"radius":0},"opacity":1,"version":1730168802133,"transform":{"scale":1,"translate":{"x":0,"y":0}},"adjustment":{"src":"","color":{"hue":0,"blur":0,"noise":0,"enable":false,"contrast":0,"pixelate":1,"vibrance":0,"brightness":0,"saturation":0,"temperature":0},"filter":{"sepia":false,"emboss":false,"enable":false,"invert":false,"brownie":false,"sharpen":false,"vintage":false,"polaroid":false,"grayscale":false,"blackwhite":false,"kodachrome":false,"technicolor":false},"shadow":{"blur":10,"show":false,"angle":45,"color":{"color":"#000000","opacity":0.5},"offset":10},"version":""}},"visible":true,"category":"image","position":{"x":27.72,"y":728.88},"rotation":0},"67204e80soszkLuzGbXWgjwwWcpcBE":{"id":"67204e80soszkLuzGbXWgjwwWcpcBE","size":{"width":83.05,"height":14.54},"scale":1,"locked":false,"pageId":"66d2cabb8G6BQz8gZ8wYgSK1aJvGaM","setting":{"scale":0.32438356809718744,"version":1730170512184,"autoSize":true,"direction":"horizontal-tb","paragraphs":[{"chars":[{"text":"扫描二维码联系我﻿","color":{"color":"#000000","opacity":1},"fontSize":32,"fontStyle":"normal","fontFamily":"Misans 中等","fontWeight":"normal","textStroke":false,"letterSpacing":0,"textDecoration":[],"textStrokeColor":{"color":"#44e296","opacity":1},"textStrokeWidth":10}],"textAlign":"start","lineHeight":1.4}],"textShadow":false,"defaultText":false,"textShadowBlur":10,"textShadowAngle":45,"textShadowColor":{"color":"#000000","opacity":0.4},"textShadowOffset":10},"visible":true,"category":"text","position":{"x":106.06,"y":752.54},"rotation":0},"67204ed24Phnx8YQHdKjH9A19W7Ten":{"id":"67204ed24Phnx8YQHdKjH9A19W7Ten","size":{"width":78.28,"height":19.81},"scale":1,"locked":false,"pageId":"66d2cabb8G6BQz8gZ8wYgSK1aJvGaM","parent":null,"setting":{"scale":1,"version":1725093975283,"children":["67204ed2eBBkrKqCaSS8jauozuuj7w","67204ed2d1PSf9H2qTnN2TWHpPbqg3","67204ed2sbgwFc5SuLJVykHHvvR6Nc"]},"visible":true,"category":"group","position":{"x":27.25,"y":345.6},"rotation":0},"67204ed2d1PSf9H2qTnN2TWHpPbqg3":{"id":"67204ed2d1PSf9H2qTnN2TWHpPbqg3","size":{"width":11.6,"height":18.4},"scale":1,"locked":false,"pageId":"66d2cabb8G6BQz8gZ8wYgSK1aJvGaM","parent":"67204ed24Phnx8YQHdKjH9A19W7Ten","setting":{"blur":0,"fill":{"color":"#f7941e","opacity":1},"path":"M0,0 L256,0 L256,256 L0,256 Z","scale":0.1318,"shadow":{"blur":4,"show":false,"type":"outer","angle":90,"color":{"color":"#000000","opacity":0.25},"behind":true,"offset":4},"stroke":{"color":{"color":"#f7941e","opacity":1},"style":"solid","width":0,"radius":2},"version":1725093802127},"visible":true,"category":"shape","position":{"x":0,"y":0.0900000000000034},"rotation":0},"67204ed2eBBkrKqCaSS8jauozuuj7w":{"id":"67204ed2eBBkrKqCaSS8jauozuuj7w","size":{"width":56,"height":19.59},"scale":1,"locked":false,"pageId":"66d2cabb8G6BQz8gZ8wYgSK1aJvGaM","parent":"67204ed24Phnx8YQHdKjH9A19W7Ten","setting":{"scale":1,"version":1730170595971,"autoSize":true,"direction":"horizontal-tb","paragraphs":[{"chars":[{"text":"学历奖项","color":{"color":"#4f5765","opacity":1},"fontSize":14,"fontStyle":"normal","fontFamily":"Misans 中等","fontWeight":"normal","textStroke":false,"letterSpacing":0,"textDecoration":[],"textStrokeColor":{"color":"#44e296","opacity":1},"textStrokeWidth":10}],"textAlign":"start","lineHeight":1.4}],"textShadow":false,"defaultText":false,"textShadowBlur":10,"textShadowAngle":45,"textShadowColor":{"color":"#000000","opacity":0.4},"textShadowOffset":10},"visible":true,"category":"text","position":{"x":22.28,"y":0.22},"rotation":0},"67204ed2sbgwFc5SuLJVykHHvvR6Nc":{"id":"67204ed2sbgwFc5SuLJVykHHvvR6Nc","size":{"width":11.6,"height":12.01},"scale":1,"locked":false,"pageId":"66d2cabb8G6BQz8gZ8wYgSK1aJvGaM","parent":"67204ed24Phnx8YQHdKjH9A19W7Ten","setting":{"blur":0,"fill":{"color":"#4f5765","opacity":1},"path":"M0,0 L256,0 L256,256 L0,256 Z","scale":0.1318,"shadow":{"blur":4,"show":false,"type":"outer","angle":90,"color":{"color":"#000000","opacity":0.25},"behind":true,"offset":4},"stroke":{"color":{"color":"#f7941e","opacity":1},"style":"solid","width":0,"radius":2},"version":1725093826305},"visible":true,"category":"shape","position":{"x":3.98999999999999,"y":0},"rotation":0},"67204ee61f21ATGDmT8gxe2HQve6bz":{"id":"67204ee61f21ATGDmT8gxe2HQve6bz","size":{"width":11.6,"height":18.4},"scale":1,"locked":false,"pageId":"66d2cabb8G6BQz8gZ8wYgSK1aJvGaM","parent":"67204ee6mXdpwoaJ2PdMMGQL5dy9yC","setting":{"blur":0,"fill":{"color":"#f7941e","opacity":1},"path":"M0,0 L256,0 L256,256 L0,256 Z","scale":0.1318,"shadow":{"blur":4,"show":false,"type":"outer","angle":90,"color":{"color":"#000000","opacity":0.25},"behind":true,"offset":4},"stroke":{"color":{"color":"#f7941e","opacity":1},"style":"solid","width":0,"radius":2},"version":1725093802127},"visible":true,"category":"shape","position":{"x":0,"y":0.0900000000000034},"rotation":0},"67204ee6bLUBP8DWiFCMGShFKVP8Bn":{"id":"67204ee6bLUBP8DWiFCMGShFKVP8Bn","size":{"width":28,"height":19.59},"scale":1,"locked":false,"pageId":"66d2cabb8G6BQz8gZ8wYgSK1aJvGaM","parent":"67204ee6mXdpwoaJ2PdMMGQL5dy9yC","setting":{"scale":1,"version":1730171833735,"autoSize":true,"direction":"horizontal-tb","paragraphs":[{"chars":[{"text":"技能﻿","color":{"color":"#4f5765","opacity":1},"fontSize":14,"fontStyle":"normal","fontFamily":"Misans 中等","fontWeight":"normal","textStroke":false,"letterSpacing":0,"textDecoration":[],"textStrokeColor":{"color":"#44e296","opacity":1},"textStrokeWidth":10}],"textAlign":"start","lineHeight":1.4}],"textShadow":false,"defaultText":false,"textShadowBlur":10,"textShadowAngle":45,"textShadowColor":{"color":"#000000","opacity":0.4},"textShadowOffset":10},"visible":true,"category":"text","position":{"x":22.28,"y":0.22},"rotation":0},"67204ee6mXdpwoaJ2PdMMGQL5dy9yC":{"id":"67204ee6mXdpwoaJ2PdMMGQL5dy9yC","size":{"width":78.28,"height":19.81},"scale":1,"locked":false,"pageId":"66d2cabb8G6BQz8gZ8wYgSK1aJvGaM","parent":null,"setting":{"scale":1,"version":1725093975283,"children":["67204ee6bLUBP8DWiFCMGShFKVP8Bn","67204ee61f21ATGDmT8gxe2HQve6bz","67204ee6ujGFrJFuJQV4d9wMZFc33n"]},"visible":true,"category":"group","position":{"x":27.25,"y":460.31},"rotation":0},"67204ee6ujGFrJFuJQV4d9wMZFc33n":{"id":"67204ee6ujGFrJFuJQV4d9wMZFc33n","size":{"width":11.6,"height":12.01},"scale":1,"locked":false,"pageId":"66d2cabb8G6BQz8gZ8wYgSK1aJvGaM","parent":"67204ee6mXdpwoaJ2PdMMGQL5dy9yC","setting":{"blur":0,"fill":{"color":"#4f5765","opacity":1},"path":"M0,0 L256,0 L256,256 L0,256 Z","scale":0.1318,"shadow":{"blur":4,"show":false,"type":"outer","angle":90,"color":{"color":"#000000","opacity":0.25},"behind":true,"offset":4},"stroke":{"color":{"color":"#f7941e","opacity":1},"style":"solid","width":0,"radius":2},"version":1725093826305},"visible":true,"category":"shape","position":{"x":3.98999999999999,"y":0},"rotation":0},"672053cafpj29vRLrnoXj3wXHcskXa":{"id":"672053cafpj29vRLrnoXj3wXHcskXa","size":{"width":155.24,"height":17.34},"scale":1,"locked":false,"pageId":"66d2cabb8G6BQz8gZ8wYgSK1aJvGaM","setting":{"scale":1,"version":1730171850890,"children":["66d2dd52qy9oFW6pnYrCbyCpyfcdJY","66d2deb9uvff55oYCZzaRt9De4bQbb"]},"visible":true,"category":"group","position":{"x":37.790000000000006,"y":390.75},"rotation":0},"672053cewJeUVsAvSmZvhfc1GeGTti":{"id":"672053cewJeUVsAvSmZvhfc1GeGTti","size":{"width":156.07,"height":17.53},"scale":1,"locked":false,"pageId":"66d2cabb8G6BQz8gZ8wYgSK1aJvGaM","setting":{"scale":1,"version":1730171854893,"children":["66d2deec5UF38xhtvToAc7NbvV4nBt","66d2deecncmKuLGSbk1fomSGgecv91"]},"visible":true,"category":"group","position":{"x":36.99000000000001,"y":416.19},"rotation":0}},"createdAt":1725090491326,"background":{"flip":"none","color":"#ffffff","image":"https://cdn.core.editorup.com/image/clzb5ewqk0003j5yc55w8zbuk/cm2opn33c004dm6pjboet1jzl/66d2cabb8G6BQz8gZ8wYgSK1aJvGaM_1730169175300_wn24x6b2bui.png","locked":false,"opacity":1,"rotation":0}}},"orders":["66d2cabb8G6BQz8gZ8wYgSK1aJvGaM"]}}}