{"code":0,"msg":"ok","data":{"id":"cmbqc5v5200403c3eb8ved1sn","title":"橙红现代工作总结研究报告单页","width":960,"height":540,"priceStrategy":"paid","snapshot":"https://cdn.aitubiao.com/cover/cmb5xiow1066mh0o65qvx7o71_1749433268600.png","createdAt":"2025-06-10T09:44:08.062Z","updatedAt":"2025-06-11T09:05:51.122Z","dimension":"PPT","tags":[{"id":"cmbrq5yxx000jcj3egz0z8cwd","name":"饼图","dimensionId":8,"dimension":{"scopes":["ppt"]}},{"id":"cmbrq5yxz000pcj3e5cvx26ud","name":"工作总结","dimensionId":9,"dimension":{"scopes":["ppt"]}},{"id":"cmbrq5yxz000qcj3eg2ked8a2","name":"市场营销","dimensionId":9,"dimension":{"scopes":["ppt"]}},{"id":"cmbrq5yxz000rcj3eaxcte4m4","name":"研究报告","dimensionId":9,"dimension":{"scopes":["ppt"]}},{"id":"cmbrq5yy0000vcj3eg5f2axr5","name":"单图表","dimensionId":10,"dimension":{"scopes":["ppt"]}}],"author":{"id":"clzb5ewqk0003j5yc55w8zbuk","name":"coveabc","avatar":null,"tier":{"id":"ckxtg2o0j00019zue6g8t68kc","name":"会员用户"}},"data":{"pages":{"68352ae3uBxHL5Uo3BfCJdAkDySQF6":{"id":"68352ae3uBxHL5Uo3BfCJdAkDySQF6","name":"","next":null,"prev":null,"size":{"width":960,"height":540},"theme":{"colors":[]},"locked":false,"orders":["68352ae3cVX4H1n2QQezASgrVoR9b7","68352ae3jTwxwhThkYJay37fZ4NSZ5","68352ae37KSttVqLH1CFNgiJ5tQPCa","68352ae394vfyZZmMVSNSeZnxvn1yW","68352ae31W2aDadDmXLg5FGxt8Sop4","68352ae3u4YAuN72RmCNWE521EoVER","68352ae3p5EpfjP2YbQidwUddjthci","68352ae3kYrMs6CCx6nLDeya8JMKUC","68352ae3qj9Nr7T4rzrANs8LYZ2C3t","68352ae3sDK8skJMUPqK36ZZ7bV4Uu","68352ae3cDfM34oxQC5ZsFzoFFmu1v","68352ae3rSQAWHEWtT2pxb1s9PbD4M","68352ae3vGVPAbkqmsCa511EPR6TbX","68352ae36mq6nSuW5Vg3ktj3Ht9wA6","68352ae3voCCvw2x2Lzz5nzzJ8LPRR","68352ae3t8fHqS1XdVVF5gZ27KBdV6","68352ae3ev2Jx7kJb5JkUfwyfG4dac","68352ae39xotQxXj33x55cv5Ki63yQ"],"visible":true,"elements":{"68352ae31W2aDadDmXLg5FGxt8Sop4":{"id":"68352ae31W2aDadDmXLg5FGxt8Sop4","size":{"width":463.65,"height":139.86},"scale":1,"locked":false,"pageId":"68352ae3uBxHL5Uo3BfCJdAkDySQF6","setting":{"blur":0,"fill":{"color":"#ff3f3f","opacity":0.1},"path":"M0,0 L256,0 L256,256 L0,256 Z","scale":1,"shadow":{"blur":4,"show":false,"type":"outer","angle":90,"color":{"color":"#000000","opacity":0.25},"behind":true,"offset":4},"stroke":{"color":{"color":"#000000","opacity":1},"style":"solid","width":0,"radius":0},"version":1746587804928},"visible":true,"category":"shape","position":{"x":455.45,"y":90.17000000000002},"rotation":0},"68352ae34joWBJAvx5XsMPsYsmdVSc":{"id":"68352ae34joWBJAvx5XsMPsYsmdVSc","size":{"width":24.1,"height":29.14},"scale":1,"locked":false,"pageId":"68352ae3uBxHL5Uo3BfCJdAkDySQF6","parent":"68352ae3cVX4H1n2QQezASgrVoR9b7","setting":{"blur":0,"fill":{"color":{"type":"linear","angle":294,"colorStops":[{"color":"#ff8a00","offset":0,"opacity":1},{"color":"#ff8a00","offset":1,"opacity":0.83}]},"opacity":1},"path":"M0,0 L256,0 L256,256 L0,256 Z","scale":1,"shadow":{"blur":4,"show":false,"type":"outer","angle":90,"color":{"color":"#000000","opacity":0.25},"behind":true,"offset":4},"stroke":{"color":{"color":"#000000","opacity":1},"style":"solid","width":0,"radius":0},"version":1746536786743},"visible":true,"category":"shape","position":{"x":0,"y":6.43},"rotation":0},"68352ae36mq6nSuW5Vg3ktj3Ht9wA6":{"id":"68352ae36mq6nSuW5Vg3ktj3Ht9wA6","size":{"width":217.7,"height":39.17},"scale":1,"locked":false,"pageId":"68352ae3uBxHL5Uo3BfCJdAkDySQF6","setting":{"scale":1,"version":1746604129249,"autoSize":false,"direction":"horizontal-tb","paragraphs":[{"chars":[{"text":"双击此处输入正文内容，内容要简单扼要说明，保证阅读清晰度。","color":{"color":"#616161","opacity":1},"fontSize":14,"fontStyle":"normal","fontFamily":"Misans 常规","fontWeight":"normal","textStroke":false,"letterSpacing":0,"textDecoration":[],"textStrokeColor":{"color":"#44e296","opacity":1},"textStrokeWidth":10}],"textAlign":"start","lineHeight":1.4}],"textShadow":false,"defaultText":false,"textShadowBlur":10,"textShadowAngle":45,"textShadowColor":{"color":"#000000","opacity":0.4},"textShadowOffset":10},"visible":true,"category":"text","position":{"x":57.879999999999995,"y":349.16},"rotation":0},"68352ae37KSttVqLH1CFNgiJ5tQPCa":{"id":"68352ae37KSttVqLH1CFNgiJ5tQPCa","size":{"width":463.65,"height":140.4},"scale":1,"locked":false,"pageId":"68352ae3uBxHL5Uo3BfCJdAkDySQF6","setting":{"blur":0,"fill":{"color":"#7ee4a9","opacity":0.16},"path":"M0,0 L256,0 L256,256 L0,256 Z","scale":1,"shadow":{"blur":4,"show":false,"type":"outer","angle":90,"color":{"color":"#000000","opacity":0.25},"behind":true,"offset":4},"stroke":{"color":{"color":"#000000","opacity":1},"style":"solid","width":0,"radius":0},"version":1746587024312},"visible":true,"category":"shape","position":{"x":38.620000000000005,"y":265.04},"rotation":0},"68352ae37eVDai369vtz923J6kM1dF":{"id":"68352ae37eVDai369vtz923J6kM1dF","size":{"width":777.34,"height":39.17},"scale":1,"locked":false,"pageId":"68352ae3uBxHL5Uo3BfCJdAkDySQF6","parent":"68352ae39xotQxXj33x55cv5Ki63yQ","setting":{"scale":1,"version":1746541647637,"autoSize":false,"direction":"horizontal-tb","paragraphs":[{"chars":[{"text":"﻿双击此处输入正文内容，内容要求简单明了扼要说明，不必过于繁琐，保证阅读清晰度。﻿双击此处输入正文内容，内容要求简单明了扼要说明，不必过于繁琐，保证阅读清晰度。","color":{"color":"#616161","opacity":1},"fontSize":14,"fontStyle":"normal","fontFamily":"Misans 中等","fontWeight":"normal","textStroke":false,"letterSpacing":0,"textDecoration":[],"textStrokeColor":{"color":"#44e296","opacity":1},"textStrokeWidth":10}],"textAlign":"start","lineHeight":1.4}],"textShadow":false,"defaultText":true,"textShadowBlur":10,"textShadowAngle":45,"textShadowColor":{"color":"#000000","opacity":0.4},"textShadowOffset":10},"visible":true,"category":"text","position":{"x":103.57,"y":0},"rotation":0},"68352ae394vfyZZmMVSNSeZnxvn1yW":{"id":"68352ae394vfyZZmMVSNSeZnxvn1yW","size":{"width":463.65,"height":140.4},"scale":1,"locked":false,"pageId":"68352ae3uBxHL5Uo3BfCJdAkDySQF6","setting":{"blur":0,"fill":{"color":"#4b50f6","opacity":0.1},"path":"M0,0 L256,0 L256,256 L0,256 Z","scale":1,"shadow":{"blur":4,"show":false,"type":"outer","angle":90,"color":{"color":"#000000","opacity":0.25},"behind":true,"offset":4},"stroke":{"color":{"color":"#000000","opacity":1},"style":"solid","width":0,"radius":0},"version":1746587799618},"visible":true,"category":"shape","position":{"x":455.45,"y":265.04},"rotation":0},"68352ae39xotQxXj33x55cv5Ki63yQ":{"id":"68352ae39xotQxXj33x55cv5Ki63yQ","size":{"width":880.91,"height":39.17},"scale":1,"locked":false,"pageId":"68352ae3uBxHL5Uo3BfCJdAkDySQF6","setting":{"scale":1,"version":1746699516830,"children":["68352ae37eVDai369vtz923J6kM1dF","68352ae3ts1SEUPNFG5aeeG8SQPbqx","68352ae3uyMG8a7jtRazJHF7EkTahK"]},"visible":true,"category":"group","position":{"x":38.62,"y":457.63},"rotation":0},"68352ae3bYAKoKrdTHvimRHryofaQB":{"id":"68352ae3bYAKoKrdTHvimRHryofaQB","size":{"width":5.94,"height":29.26},"scale":1,"locked":false,"pageId":"68352ae3uBxHL5Uo3BfCJdAkDySQF6","parent":"68352ae3cVX4H1n2QQezASgrVoR9b7","setting":{"blur":0,"fill":{"color":"#ff8a00","opacity":0.6},"path":"M0,0 L256,0 L256,256 L0,256 Z","scale":1,"shadow":{"blur":4,"show":false,"type":"outer","angle":90,"color":{"color":"#000000","opacity":0.25},"behind":true,"offset":4},"stroke":{"color":{"color":"#000000","opacity":1},"style":"solid","width":0,"radius":0},"version":1746536855182},"visible":true,"category":"shape","position":{"x":25.610000000000007,"y":6.310000000000002},"rotation":0},"68352ae3cDfM34oxQC5ZsFzoFFmu1v":{"id":"68352ae3cDfM34oxQC5ZsFzoFFmu1v","size":{"width":87.94,"height":28},"scale":1,"locked":false,"pageId":"68352ae3uBxHL5Uo3BfCJdAkDySQF6","setting":{"scale":1,"version":1746603416502,"autoSize":false,"direction":"horizontal-tb","paragraphs":[{"chars":[{"text":"产品四","color":{"color":"#000000","opacity":1},"fontSize":20,"fontStyle":"normal","fontFamily":"Misans 中等","fontWeight":"normal","textStroke":false,"letterSpacing":0,"textDecoration":[],"textStrokeColor":{"color":"#44e296","opacity":1},"textStrokeWidth":10}],"textAlign":"start","lineHeight":1.4}],"textShadow":false,"defaultText":false,"textShadowBlur":10,"textShadowAngle":45,"textShadowColor":{"color":"#000000","opacity":0.4},"textShadowOffset":10},"visible":true,"category":"text","position":{"x":848.68,"y":316.9800000000001},"rotation":0},"68352ae3cVX4H1n2QQezASgrVoR9b7":{"id":"68352ae3cVX4H1n2QQezASgrVoR9b7","size":{"width":236.97,"height":44.79},"scale":1,"locked":false,"pageId":"68352ae3uBxHL5Uo3BfCJdAkDySQF6","setting":{"scale":1,"version":1746544010165,"children":["68352ae3rwF6B2owzaa3d41dG4DvgT","68352ae34joWBJAvx5XsMPsYsmdVSc","68352ae3bYAKoKrdTHvimRHryofaQB","68352ae3wLwxRZ7su3BKsUitwc8539"]},"visible":true,"category":"group","position":{"x":38.62,"y":33.86},"rotation":0},"68352ae3ev2Jx7kJb5JkUfwyfG4dac":{"id":"68352ae3ev2Jx7kJb5JkUfwyfG4dac","size":{"width":102.66,"height":44.79},"scale":1,"locked":false,"pageId":"68352ae3uBxHL5Uo3BfCJdAkDySQF6","setting":{"scale":1,"version":1746611419073,"children":["68352ae3rSEhibLiuHYNpKAnM9SdoK","68352ae3qzQyemm9wmf5zCSQDTnppN"]},"visible":true,"category":"group","position":{"x":430.195,"y":246.44},"rotation":0},"68352ae3jTwxwhThkYJay37fZ4NSZ5":{"id":"68352ae3jTwxwhThkYJay37fZ4NSZ5","size":{"width":463.65,"height":139.86},"scale":1,"locked":false,"pageId":"68352ae3uBxHL5Uo3BfCJdAkDySQF6","setting":{"blur":0,"fill":{"color":"#ffc03f","opacity":0.16},"path":"M0,0 L256,0 L256,256 L0,256 Z","scale":1,"shadow":{"blur":4,"show":false,"type":"outer","angle":90,"color":{"color":"#000000","opacity":0.25},"behind":true,"offset":4},"stroke":{"color":{"color":"#000000","opacity":1},"style":"solid","width":0,"radius":0},"version":1746587030017},"visible":true,"category":"shape","position":{"x":38.620000000000005,"y":90.17000000000002},"rotation":0},"68352ae3kYrMs6CCx6nLDeya8JMKUC":{"id":"68352ae3kYrMs6CCx6nLDeya8JMKUC","size":{"width":210.04,"height":39.17},"scale":1,"locked":false,"pageId":"68352ae3uBxHL5Uo3BfCJdAkDySQF6","setting":{"scale":1,"version":1746604154855,"autoSize":false,"direction":"horizontal-tb","paragraphs":[{"chars":[{"text":"双击此处输入正文内容，内容要简单扼要说明，保证阅读清晰度。","color":{"color":"#616161","opacity":1},"fontSize":14,"fontStyle":"normal","fontFamily":"Misans 常规","fontWeight":"normal","textStroke":false,"letterSpacing":0,"textDecoration":[],"textStrokeColor":{"color":"#44e296","opacity":1},"textStrokeWidth":10}],"textAlign":"start","lineHeight":1.4}],"textShadow":false,"defaultText":false,"textShadowBlur":10,"textShadowAngle":45,"textShadowColor":{"color":"#000000","opacity":0.4},"textShadowOffset":10},"visible":true,"category":"text","position":{"x":698.65,"y":176.15000000000003},"rotation":0},"68352ae3p5EpfjP2YbQidwUddjthci":{"id":"68352ae3p5EpfjP2YbQidwUddjthci","size":{"width":453.43583088462714,"height":415.32946578219287},"scale":1,"locked":false,"pageId":"68352ae3uBxHL5Uo3BfCJdAkDySQF6","setting":{"data":[[["受教育水平","人数占比"],["大学专科","30"],["大学本科","25"],["硕士","25"],["博士","20"]]],"pipe":"key_value","props":{"map":[{"name":"名称","type":"","index":0,"function":"objCol","isLegend":true,"xAxisIndex":0,"configurable":true},{"name":"值","type":"pie","index":1,"function":"vCol","isLegend":false,"yAxisIndex":0,"configurable":true}],"fill":{"props":[{"color":{"color":"#F24242","opacity":1},"border":{"type":"solid","color":null,"width":0},"shadow":{"blur":10,"show":false,"type":"outer","angle":96,"color":{"color":"#F24242","opacity":0.5},"radius":18},"symbol":{"url":""},"texture":{"url":""}},{"color":{"color":"#2857FF","opacity":1},"border":{"type":"solid","color":null,"width":0},"shadow":{"blur":10,"show":false,"type":"outer","angle":96,"color":{"color":"#F24242","opacity":0.5},"radius":18},"symbol":{"url":""},"texture":{"url":""}},{"color":{"color":"#4fe7a4","opacity":1},"border":{"type":"solid","color":null,"width":0},"shadow":{"blur":0,"show":false,"type":"outer","angle":0,"color":{"color":"#000000","opacity":1},"radius":0},"symbol":{"url":""},"texture":{"url":""}},{"color":{"color":"#ffb100","opacity":1},"border":{"type":"solid","color":null,"width":0},"shadow":{"blur":0,"show":false,"type":"outer","angle":0,"color":{"color":"#000000","opacity":1},"radius":0},"symbol":{"url":""},"texture":{"url":""}}],"controlType":"multiple"},"type":"basic-pie","label":{"show":true,"overlap":true,"highlight":false,"textLabel":{"show":false,"color":{"color":"#333333","opacity":1},"fontSize":16,"fontFamily":"阿里妈妈方圆体 中等","positionChoice":"outside-ellipse"},"numberLabel":{"show":false,"color":{"color":"#161616","opacity":1},"suffix":"","fontSize":16,"fontFamily":"Misans","positionChoice":"inside-horizontal"},"percentLabel":{"show":true,"color":{"color":"#000000","opacity":1},"fontSize":19.34303563369341,"fontFamily":"Misans 中等","positionChoice":"outside-edge"}},"title":{"show":false,"subTitle":{"show":true,"text":"副标题","color":{"color":"#333333","opacity":1},"fontSize":16,"fontFamily":"Misans"},"mainTitle":{"show":true,"text":"饼图","color":{"color":"#333333","opacity":1},"fontSize":24,"position":{"x":"center","y":"top"},"fontFamily":"Misans"}},"legend":{"show":false,"color":{"color":"#333333","opacity":1},"display":"horizontal","fontSize":14,"position":{"x":"center","y":"bottom"},"fontFamily":"Misans 常规"},"display":{"pie":{"border":{"type":"solid","color":{"color":"#ffffff","opacity":1},"width":2,"radius":0},"gapPercentage":0,"innerRadiusRatio":0.57}},"padding":{"top":20,"left":24,"right":24,"bottom":23},"tooltip":false,"animation":{"loop":false,"show":false,"duration":2,"endPause":1,"moveStyle":null,"startDelay":0,"transition":false},"background":{"blur":0,"show":false,"color":{"color":"#ffffff","opacity":1},"border":{"radius":0},"texture":""},"numberFormat":{"decimalPlaces":null,"separatorType":"1000.00"}},"scale":1.042159389988077,"version":1746603323623},"visible":true,"category":"chart","position":{"x":254.8,"y":42.30000000000001},"rotation":0},"68352ae3qj9Nr7T4rzrANs8LYZ2C3t":{"id":"68352ae3qj9Nr7T4rzrANs8LYZ2C3t","size":{"width":74.17,"height":28},"scale":1,"locked":false,"pageId":"68352ae3uBxHL5Uo3BfCJdAkDySQF6","setting":{"scale":1,"version":1746603413514,"autoSize":false,"direction":"horizontal-tb","paragraphs":[{"chars":[{"text":"产品三","color":{"color":"#000000","opacity":1},"fontSize":20,"fontStyle":"normal","fontFamily":"Misans 中等","fontWeight":"normal","textStroke":false,"letterSpacing":0,"textDecoration":[],"textStrokeColor":{"color":"#44e296","opacity":1},"textStrokeWidth":10}],"textAlign":"start","lineHeight":1.4}],"textShadow":false,"defaultText":false,"textShadowBlur":10,"textShadowAngle":45,"textShadowColor":{"color":"#000000","opacity":0.4},"textShadowOffset":10},"visible":true,"category":"text","position":{"x":848.68,"y":143.97000000000003},"rotation":0},"68352ae3qzQyemm9wmf5zCSQDTnppN":{"id":"68352ae3qzQyemm9wmf5zCSQDTnppN","size":{"width":21.65,"height":19.58},"scale":1,"locked":false,"pageId":"68352ae3uBxHL5Uo3BfCJdAkDySQF6","parent":"68352ae3ev2Jx7kJb5JkUfwyfG4dac","setting":{"scale":1,"version":1746611390822,"autoSize":false,"direction":"horizontal-tb","paragraphs":[{"chars":[{"text":"件","color":{"color":"#616161","opacity":1},"fontSize":14,"fontStyle":"normal","fontFamily":"Misans 中等","fontWeight":"normal","textStroke":false,"letterSpacing":0,"textDecoration":[],"textStrokeColor":{"color":"#44e296","opacity":1},"textStrokeWidth":10}],"textAlign":"center","lineHeight":1.4}],"textShadow":false,"defaultText":false,"textShadowBlur":10,"textShadowAngle":45,"textShadowColor":{"color":"#000000","opacity":0.4},"textShadowOffset":10},"visible":true,"category":"text","position":{"x":81.00999999999999,"y":16.77000000000001},"rotation":0},"68352ae3rSEhibLiuHYNpKAnM9SdoK":{"id":"68352ae3rSEhibLiuHYNpKAnM9SdoK","size":{"width":80.54,"height":44.79},"scale":1,"locked":false,"pageId":"68352ae3uBxHL5Uo3BfCJdAkDySQF6","parent":"68352ae3ev2Jx7kJb5JkUfwyfG4dac","setting":{"scale":1,"version":1746611321689,"autoSize":false,"direction":"horizontal-tb","paragraphs":[{"chars":[{"text":"8765","color":{"color":"#000000","opacity":1},"fontSize":32,"fontStyle":"normal","fontFamily":"Misans 加粗","fontWeight":"normal","textStroke":false,"letterSpacing":0,"textDecoration":[],"textStrokeColor":{"color":"#44e296","opacity":1},"textStrokeWidth":10}],"textAlign":"center","lineHeight":1.4}],"textShadow":false,"defaultText":false,"textShadowBlur":10,"textShadowAngle":45,"textShadowColor":{"color":"#000000","opacity":0.4},"textShadowOffset":10},"visible":true,"category":"text","position":{"x":0,"y":0},"rotation":0},"68352ae3rSQAWHEWtT2pxb1s9PbD4M":{"id":"68352ae3rSQAWHEWtT2pxb1s9PbD4M","size":{"width":217.7,"height":39.17},"scale":1,"locked":false,"pageId":"68352ae3uBxHL5Uo3BfCJdAkDySQF6","setting":{"scale":1,"version":1746604118937,"autoSize":false,"direction":"horizontal-tb","paragraphs":[{"chars":[{"text":"双击此处输入正文内容，内容要简单扼要说明，保证阅读清晰度。","color":{"color":"#616161","opacity":1},"fontSize":14,"fontStyle":"normal","fontFamily":"Misans 常规","fontWeight":"normal","textStroke":false,"letterSpacing":0,"textDecoration":[],"textStrokeColor":{"color":"#44e296","opacity":1},"textStrokeWidth":10}],"textAlign":"start","lineHeight":1.4}],"textShadow":false,"defaultText":false,"textShadowBlur":10,"textShadowAngle":45,"textShadowColor":{"color":"#000000","opacity":0.4},"textShadowOffset":10},"visible":true,"category":"text","position":{"x":57.88000000000001,"y":176.15000000000003},"rotation":0},"68352ae3rwF6B2owzaa3d41dG4DvgT":{"id":"68352ae3rwF6B2owzaa3d41dG4DvgT","size":{"width":192,"height":44.79},"scale":1,"locked":false,"pageId":"68352ae3uBxHL5Uo3BfCJdAkDySQF6","parent":"68352ae3cVX4H1n2QQezASgrVoR9b7","setting":{"scale":1,"version":1746530158038,"autoSize":true,"direction":"horizontal-tb","paragraphs":[{"chars":[{"text":"请输入主标题","color":{"color":"#000000","opacity":1},"fontSize":32,"fontStyle":"normal","fontFamily":"Misans 加粗","fontWeight":"normal","textStroke":false,"letterSpacing":0,"textDecoration":[],"textStrokeColor":{"color":"#44e296","opacity":1},"textStrokeWidth":10}],"textAlign":"start","lineHeight":1.4}],"textShadow":false,"defaultText":true,"textShadowBlur":10,"textShadowAngle":45,"textShadowColor":{"color":"#000000","opacity":0.4},"textShadowOffset":10},"visible":true,"category":"text","position":{"x":44.970000000000006,"y":0},"rotation":0},"68352ae3sDK8skJMUPqK36ZZ7bV4Uu":{"id":"68352ae3sDK8skJMUPqK36ZZ7bV4Uu","size":{"width":211.37,"height":39.17},"scale":1,"locked":false,"pageId":"68352ae3uBxHL5Uo3BfCJdAkDySQF6","setting":{"scale":1,"version":1746604165143,"autoSize":false,"direction":"horizontal-tb","paragraphs":[{"chars":[{"text":"双击此处输入正文内容，内容要简单扼要说明，保证阅读清晰度。","color":{"color":"#616161","opacity":1},"fontSize":14,"fontStyle":"normal","fontFamily":"Misans 常规","fontWeight":"normal","textStroke":false,"letterSpacing":0,"textDecoration":[],"textStrokeColor":{"color":"#44e296","opacity":1},"textStrokeWidth":10}],"textAlign":"start","lineHeight":1.4}],"textShadow":false,"defaultText":false,"textShadowBlur":10,"textShadowAngle":45,"textShadowColor":{"color":"#000000","opacity":0.4},"textShadowOffset":10},"visible":true,"category":"text","position":{"x":697.31,"y":349.16},"rotation":0},"68352ae3t8fHqS1XdVVF5gZ27KBdV6":{"id":"68352ae3t8fHqS1XdVVF5gZ27KBdV6","size":{"width":133.77,"height":28},"scale":1,"locked":false,"pageId":"68352ae3uBxHL5Uo3BfCJdAkDySQF6","setting":{"scale":1,"version":1746611459454,"autoSize":false,"direction":"horizontal-tb","paragraphs":[{"chars":[{"text":"销售总量","color":{"color":"#616161","opacity":1},"fontSize":20,"fontStyle":"normal","fontFamily":"Misans 中等","fontWeight":"normal","textStroke":false,"letterSpacing":0,"textDecoration":[],"textStrokeColor":{"color":"#44e296","opacity":1},"textStrokeWidth":10}],"textAlign":"center","lineHeight":1.4}],"textShadow":false,"defaultText":false,"textShadowBlur":10,"textShadowAngle":45,"textShadowColor":{"color":"#000000","opacity":0.4},"textShadowOffset":10},"visible":true,"category":"text","position":{"x":414.64,"y":208.69},"rotation":0},"68352ae3ts1SEUPNFG5aeeG8SQPbqx":{"id":"68352ae3ts1SEUPNFG5aeeG8SQPbqx","size":{"width":40,"height":28},"scale":1,"locked":false,"pageId":"68352ae3uBxHL5Uo3BfCJdAkDySQF6","parent":"68352ae39xotQxXj33x55cv5Ki63yQ","setting":{"scale":1,"version":1746543435074,"autoSize":true,"direction":"horizontal-tb","paragraphs":[{"chars":[{"text":"总结","color":{"color":"#000000","opacity":1},"fontSize":20,"fontStyle":"normal","fontFamily":"Misans 中等","fontWeight":"normal","textStroke":false,"letterSpacing":0,"textDecoration":[],"textStrokeColor":{"color":"#44e296","opacity":1},"textStrokeWidth":10}],"textAlign":"start","lineHeight":1.4}],"textShadow":false,"defaultText":true,"textShadowBlur":10,"textShadowAngle":45,"textShadowColor":{"color":"#000000","opacity":0.4},"textShadowOffset":10},"visible":true,"category":"text","position":{"x":16.020000000000017,"y":5.579999999999984},"rotation":0},"68352ae3u4YAuN72RmCNWE521EoVER":{"id":"68352ae3u4YAuN72RmCNWE521EoVER","size":{"width":328.50500000000005,"height":328.50500000000005},"scale":1,"locked":false,"pageId":"68352ae3uBxHL5Uo3BfCJdAkDySQF6","setting":{"blur":0,"fill":{"color":"#fffefe","opacity":1},"path":"M128,0 A128,128 0 1,1 0,128 A128,128 0 0,1 128,0 Z","scale":2.027808641975309,"shadow":{"blur":4,"show":false,"type":"outer","angle":90,"color":{"color":"#000000","opacity":0.25},"behind":true,"offset":4},"stroke":{"color":{"color":"#000000","opacity":1},"style":"solid","width":0,"radius":0},"version":1746586648420},"visible":true,"category":"shape","position":{"x":317.265,"y":85.70500000000004},"rotation":0},"68352ae3uyMG8a7jtRazJHF7EkTahK":{"id":"68352ae3uyMG8a7jtRazJHF7EkTahK","size":{"width":4.38,"height":20.48},"scale":1,"locked":false,"pageId":"68352ae3uBxHL5Uo3BfCJdAkDySQF6","parent":"68352ae39xotQxXj33x55cv5Ki63yQ","setting":{"blur":0,"fill":{"color":"#ff8a00","opacity":1},"path":"M0,0 L256,0 L256,256 L0,256 Z","scale":0.8180921546465053,"shadow":{"blur":4,"show":false,"type":"outer","angle":90,"color":{"color":"#000000","opacity":0.25},"behind":true,"offset":4},"stroke":{"color":{"color":"#ff8a00","opacity":1},"style":"solid","width":0,"radius":24},"version":1746533713895},"visible":true,"category":"shape","position":{"x":1.4210854715202004e-14,"y":9.34499999999997},"rotation":0},"68352ae3vGVPAbkqmsCa511EPR6TbX":{"id":"68352ae3vGVPAbkqmsCa511EPR6TbX","size":{"width":84.31,"height":28},"scale":1,"locked":false,"pageId":"68352ae3uBxHL5Uo3BfCJdAkDySQF6","setting":{"scale":1,"version":1746603355775,"autoSize":false,"direction":"horizontal-tb","paragraphs":[{"chars":[{"text":"产品一","color":{"color":"#000000","opacity":1},"fontSize":20,"fontStyle":"normal","fontFamily":"Misans 中等","fontWeight":"normal","textStroke":false,"letterSpacing":0,"textDecoration":[],"textStrokeColor":{"color":"#44e296","opacity":1},"textStrokeWidth":10}],"textAlign":"start","lineHeight":1.4}],"textShadow":false,"defaultText":false,"textShadowBlur":10,"textShadowAngle":45,"textShadowColor":{"color":"#000000","opacity":0.4},"textShadowOffset":10},"visible":true,"category":"text","position":{"x":57.88000000000001,"y":143.97000000000003},"rotation":0},"68352ae3voCCvw2x2Lzz5nzzJ8LPRR":{"id":"68352ae3voCCvw2x2Lzz5nzzJ8LPRR","size":{"width":93.55,"height":28},"scale":1,"locked":false,"pageId":"68352ae3uBxHL5Uo3BfCJdAkDySQF6","setting":{"scale":1,"version":1746603347123,"autoSize":false,"direction":"horizontal-tb","paragraphs":[{"chars":[{"text":"产品二","color":{"color":"#000000","opacity":1},"fontSize":20,"fontStyle":"normal","fontFamily":"Misans 中等","fontWeight":"normal","textStroke":false,"letterSpacing":0,"textDecoration":[],"textStrokeColor":{"color":"#44e296","opacity":1},"textStrokeWidth":10}],"textAlign":"start","lineHeight":1.4}],"textShadow":false,"defaultText":false,"textShadowBlur":10,"textShadowAngle":45,"textShadowColor":{"color":"#000000","opacity":0.4},"textShadowOffset":10},"visible":true,"category":"text","position":{"x":57.88000000000001,"y":316.9800000000001},"rotation":0},"68352ae3wLwxRZ7su3BKsUitwc8539":{"id":"68352ae3wLwxRZ7su3BKsUitwc8539","size":{"width":5.94,"height":29.14},"scale":1,"locked":false,"pageId":"68352ae3uBxHL5Uo3BfCJdAkDySQF6","parent":"68352ae3cVX4H1n2QQezASgrVoR9b7","setting":{"blur":0,"fill":{"color":"#ff8a00","opacity":0.25},"path":"M0,0 L256,0 L256,256 L0,256 Z","scale":1,"shadow":{"blur":4,"show":false,"type":"outer","angle":90,"color":{"color":"#000000","opacity":0.25},"behind":true,"offset":4},"stroke":{"color":{"color":"#000000","opacity":1},"style":"solid","width":0,"radius":0},"version":1746536685986},"visible":true,"category":"shape","position":{"x":33.050000000000004,"y":6.43},"rotation":0}},"projectId":"","background":{"color":"#FFFFFF","locked":false}}},"orders":["68352ae3uBxHL5Uo3BfCJdAkDySQF6"]}}}