{"code":0,"msg":"ok","data":{"id":"cmbqc3xto002n3c3eb7kb2oj3","title":"蓝色科技简洁工作安排单页","width":960,"height":540,"priceStrategy":"paid","snapshot":"https://cdn.aitubiao.com/cover/cmb55yumr05mkh0o6a3f242jh_1749435813094.png","createdAt":"2025-06-10T09:44:08.062Z","updatedAt":"2025-06-11T09:05:51.122Z","dimension":"PPT","tags":[{"id":"cmbrq5yxz000tcj3e3re6fqkd","name":"项目汇报","dimensionId":9,"dimension":{"scopes":["ppt"]}},{"id":"cmbrq5yxz000qcj3eg2ked8a2","name":"市场营销","dimensionId":9,"dimension":{"scopes":["ppt"]}},{"id":"cmbrq5yy0000vcj3eg5f2axr5","name":"单图表","dimensionId":10,"dimension":{"scopes":["ppt"]}}],"author":{"id":"clzb5ewqk0003j5yc55w8zbuk","name":"coveabc","avatar":null,"tier":{"id":"ckxtg2o0j00019zue6g8t68kc","name":"会员用户"}},"data":{"pages":{"cmb55yumr05mlh0o679g3gldj":{"id":"cmb55yumr05mlh0o679g3gldj","name":"First Page","size":{"width":960,"height":540},"theme":{"colors":[]},"locked":false,"orders":["6834761f8JT1QDkadZDCaZmGz1zYye","6834761ftBPMzL9QwaejsVmg5y8Abp","6834761fbN9h6dsrL7APuFfwp6CVuy","6834761fgiP7yKiHoq8bZNLTA8ZaoM","6834761fkQdoznP7wwVHPoSNjryiTM","6834761fnmwTguC3RqESDh2PfqVBi3","6834761fh9LJma3t8RPmZDYDqMxEkU","6834761fbM4SGswKd7qJ5jpidaAM87","6834761fmj6pLLq4cHYW6cuHjAkYH6","6834761fgzGZW8fecK61AnBAnucZ5V","6834761foTzsoCakwKnmw6UnXJR3KT","6834761f8x6g2mXx6f2ByTz7ptjCyx","6834761fukQj9FHZr9JGY7zUdap1yT","6834761fgGhGpA2uSsD83Xk6LSA1Hz","6834761fcPY1RFrAk2mkzkeshtSUkW","6834761ffbTrAmcqN3zAZSXzMSjLFN","6834761fjHKzkox1P1k7XJSbHHN4xP","6834761fd7qHsesVSeJWnyH2p1yJFj","6834761fudGSh9FWZjn7MjLsfxp87S","6834761f9wv5M9MCjxJbtgXCSaP9i4"],"visible":true,"elements":{"6834761f153ULpebhGc4AzvsWyQJNF":{"id":"6834761f153ULpebhGc4AzvsWyQJNF","size":{"width":128.01,"height":22.4},"scale":1,"locked":false,"parent":"6834761foTzsoCakwKnmw6UnXJR3KT","setting":{"scale":1,"version":1747237621297,"autoSize":true,"direction":"horizontal-tb","paragraphs":[{"chars":[{"text":"单击此处添加内容","color":{"color":"#000000","opacity":1},"fontSize":16,"fontStyle":"normal","fontFamily":"Misans 中等","fontWeight":"normal","textStroke":false,"letterSpacing":0,"textDecoration":[],"textStrokeColor":{"color":"#44e296","opacity":1},"textStrokeWidth":10}],"textAlign":"start","lineHeight":1.4}],"textShadow":false,"defaultText":true,"textShadowBlur":10,"textShadowAngle":45,"textShadowColor":{"color":"#000000","opacity":0.4},"textShadowOffset":10},"visible":true,"category":"text","position":{"x":0,"y":0},"rotation":0},"6834761f1GsZd5cAiLZuHyYJ9F7mgr":{"id":"6834761f1GsZd5cAiLZuHyYJ9F7mgr","size":{"width":266.03,"height":170},"scale":1,"locked":false,"parent":"6834761fgiP7yKiHoq8bZNLTA8ZaoM","setting":{"blur":0,"fill":{"color":"#ffffff","opacity":1},"path":"M64,32 L192,32 L256,96 L0,96 Z","scale":1.251010020616602,"shadow":{"blur":4,"show":false,"type":"outer","angle":90,"color":{"color":"#000000","opacity":0.25},"behind":true,"offset":4},"stroke":{"color":{"color":"#000000","opacity":1},"style":"solid","width":0,"radius":0},"version":1747281338966},"visible":true,"category":"shape","position":{"x":136.12,"y":48.01999999999998},"rotation":-90},"6834761f53VtX9GtRZapcnAaTvdVpC":{"id":"6834761f53VtX9GtRZapcnAaTvdVpC","size":{"width":392.53,"height":39.19},"scale":1,"locked":false,"parent":"6834761f9wv5M9MCjxJbtgXCSaP9i4","setting":{"scale":1,"version":1747065413595,"autoSize":false,"direction":"horizontal-tb","paragraphs":[{"chars":[{"text":"﻿双击此处输入正文内容，内容要求简单明了扼要说明，不必过于繁琐，保证阅读清晰度。﻿","color":{"color":"#616161","opacity":1},"fontSize":14,"fontStyle":"normal","fontFamily":"Misans 中等","fontWeight":"normal","textStroke":false,"letterSpacing":0,"textDecoration":[],"textStrokeColor":{"color":"#44e296","opacity":1},"textStrokeWidth":10}],"textAlign":"start","lineHeight":1.4}],"textShadow":false,"defaultText":true,"textShadowBlur":10,"textShadowAngle":45,"textShadowColor":{"color":"#000000","opacity":0.4},"textShadowOffset":10},"visible":true,"category":"text","position":{"x":103.57000000000005,"y":0},"rotation":0},"6834761f5nKv2TLhx7yqTxMEEYCJa4":{"id":"6834761f5nKv2TLhx7yqTxMEEYCJa4","size":{"width":34.13172055346784,"height":34.13172055346784},"scale":1,"locked":false,"parent":"6834761fnmwTguC3RqESDh2PfqVBi3","setting":{"alt":"图片","fit":"fill","src":"https://cdn.aitubiao.com/resource/vector/icon/office/2-circle-fill.svg","fill":{"colors":[{"color":"#009fff","opacity":1}]},"flip":"none","size":{"width":34.63537765131067,"height":34.63537765131067},"scale":0.985458305004976,"stroke":{"show":false,"color":{"color":"#000000","opacity":1},"style":"solid","width":0.5,"radius":0},"opacity":1,"version":1747281494232,"transform":{"scale":1,"translate":{"x":0,"y":0}},"adjustment":{"src":"","color":{"hue":0,"blur":0,"noise":0,"enable":false,"contrast":0,"pixelate":1,"vibrance":0,"brightness":0,"saturation":0,"temperature":0},"filter":{"sepia":false,"emboss":false,"enable":false,"invert":false,"brownie":false,"sharpen":false,"vintage":false,"polaroid":false,"grayscale":false,"blackwhite":false,"kodachrome":false,"technicolor":false},"shadow":{"blur":10,"show":false,"angle":45,"color":{"color":"#000000","opacity":0.5},"offset":10},"version":""}},"visible":true,"category":"image","position":{"x":0.003050215991265759,"y":0.0018686471014746076},"rotation":0},"6834761f7FR8c9pEgbDWQGohJJNK3H":{"id":"6834761f7FR8c9pEgbDWQGohJJNK3H","size":{"width":34.13172055346784,"height":34.13172055346784},"scale":1,"locked":false,"parent":"6834761fmj6pLLq4cHYW6cuHjAkYH6","setting":{"alt":"图片","fit":"fill","src":"https://cdn.aitubiao.com/resource/vector/icon/office/2-circle-fill.svg","fill":{"colors":[{"color":"#009fff","opacity":1}]},"flip":"none","size":{"width":34.63537765131067,"height":34.63537765131067},"scale":0.985458305004976,"stroke":{"show":false,"color":{"color":"#000000","opacity":1},"style":"solid","width":0.5,"radius":0},"opacity":1,"version":1747281494232,"transform":{"scale":1,"translate":{"x":0,"y":0}},"adjustment":{"src":"","color":{"hue":0,"blur":0,"noise":0,"enable":false,"contrast":0,"pixelate":1,"vibrance":0,"brightness":0,"saturation":0,"temperature":0},"filter":{"sepia":false,"emboss":false,"enable":false,"invert":false,"brownie":false,"sharpen":false,"vintage":false,"polaroid":false,"grayscale":false,"blackwhite":false,"kodachrome":false,"technicolor":false},"shadow":{"blur":10,"show":false,"angle":45,"color":{"color":"#000000","opacity":0.5},"offset":10},"version":""}},"visible":true,"category":"image","position":{"x":-0.0007307933735489769,"y":0.0018686471014746076},"rotation":0},"6834761f87pkJayoqYAP13YsAdoqVj":{"id":"6834761f87pkJayoqYAP13YsAdoqVj","size":{"width":34.13172055346784,"height":34.13172055346784},"scale":1,"locked":false,"parent":"6834761fkQdoznP7wwVHPoSNjryiTM","setting":{"alt":"图片","fit":"fill","src":"https://cdn.aitubiao.com/resource/vector/icon/office/1-circle-fill.svg","fill":{"colors":[{"color":"#0077ff","opacity":1}]},"flip":"none","size":{"width":34.63537765131067,"height":34.63537765131067},"scale":0.985458305004976,"stroke":{"show":false,"color":{"color":"#000000","opacity":1},"style":"solid","width":0.5,"radius":0},"opacity":1,"version":1748232982883,"transform":{"scale":1,"translate":{"x":0,"y":0}},"adjustment":{"src":"","color":{"hue":0,"blur":0,"noise":0,"enable":false,"contrast":0,"pixelate":1,"vibrance":0,"brightness":0,"saturation":0,"temperature":0},"filter":{"sepia":false,"emboss":false,"enable":false,"invert":false,"brownie":false,"sharpen":false,"vintage":false,"polaroid":false,"grayscale":false,"blackwhite":false,"kodachrome":false,"technicolor":false},"shadow":{"blur":10,"show":false,"angle":45,"color":{"color":"#000000","opacity":0.5},"offset":10},"version":""}},"visible":true,"category":"image","position":{"x":-0.0018770755337982337,"y":-0.0038333212195595934},"rotation":0},"6834761f899majMgHeBKQinmD9sksq":{"id":"6834761f899majMgHeBKQinmD9sksq","size":{"width":4.38,"height":20.48},"scale":1,"locked":false,"parent":"6834761f9wv5M9MCjxJbtgXCSaP9i4","setting":{"blur":0,"fill":{"color":"#0077ff","opacity":1},"path":"M0,0 L256,0 L256,256 L0,256 Z","scale":0.8180921546465053,"shadow":{"blur":4,"show":false,"type":"outer","angle":90,"color":{"color":"#000000","opacity":0.25},"behind":true,"offset":4},"stroke":{"color":{"color":"#ff8a00","opacity":1},"style":"solid","width":0,"radius":24},"version":1747282379010},"visible":true,"category":"shape","position":{"x":0,"y":9.34499999999997},"rotation":0},"6834761f8JT1QDkadZDCaZmGz1zYye":{"id":"6834761f8JT1QDkadZDCaZmGz1zYye","size":{"width":270.49,"height":44.8},"scale":1,"locked":false,"setting":{"scale":1,"version":1747226984340,"children":["6834761ffbEWcMTkED48CjnqCNZGV4","6834761fmWo6kKAV2kq9qTWR3Jspin","6834761fn587jcujrSHnrnkyDpXhqB"]},"visible":true,"category":"group","position":{"x":50.2,"y":42.96},"rotation":0},"6834761f8jf9QKB9pcCLpdpizYJpZu":{"id":"6834761f8jf9QKB9pcCLpdpizYJpZu","size":{"width":266.0244694360933,"height":162.95538531562283},"scale":1,"locked":false,"parent":"6834761fgiP7yKiHoq8bZNLTA8ZaoM","setting":{"blur":0,"fill":{"color":{"type":"linear","angle":0,"colorStops":[{"color":"#0077ff","offset":0,"opacity":1},{"color":"#009fff","offset":1,"opacity":0}]},"opacity":0.39},"path":"M64,32 L192,32 L256,96 L0,96 Z","scale":1.251010020616602,"shadow":{"blur":4,"show":false,"type":"outer","angle":90,"color":{"color":"#000000","opacity":0.25},"behind":true,"offset":4},"stroke":{"color":{"color":{"type":"linear","angle":0,"colorStops":[{"color":"#0077ff","offset":0.13301541548813584,"opacity":1},{"color":"#ffffff","offset":1,"opacity":0}]},"opacity":1},"style":"solid","width":1,"radius":4},"version":1747282504738},"visible":true,"category":"shape","position":{"x":132.60472414033944,"y":51.53862500065205},"rotation":-90},"6834761f8x6g2mXx6f2ByTz7ptjCyx":{"id":"6834761f8x6g2mXx6f2ByTz7ptjCyx","size":{"width":193.29764652672606,"height":62.49776570341558},"scale":1,"locked":false,"setting":{"scale":0.985458305004976,"version":1747281338966,"children":["6834761fhvp2YyQxTi7Bn3Um7JtU9V","6834761fmHajEiENbFhvL6R97geXdc"]},"visible":true,"category":"group","position":{"x":716.132353473274,"y":234.26679593862644},"rotation":0},"6834761f9wv5M9MCjxJbtgXCSaP9i4":{"id":"6834761f9wv5M9MCjxJbtgXCSaP9i4","size":{"width":496.1,"height":39.19},"scale":1,"locked":false,"setting":{"scale":1,"version":1747065496479,"children":["6834761f53VtX9GtRZapcnAaTvdVpC","6834761frKUHGJBx49axYip3mXbGq7","6834761f899majMgHeBKQinmD9sksq"]},"visible":true,"category":"group","position":{"x":244.11,"y":436.24499999999995},"rotation":0},"6834761fbDoyUVm3FsR42X3fWt6BK6":{"id":"6834761fbDoyUVm3FsR42X3fWt6BK6","size":{"width":128.01,"height":22.4},"scale":1,"locked":false,"parent":"6834761fukQj9FHZr9JGY7zUdap1yT","setting":{"scale":1,"version":1747237621297,"autoSize":true,"direction":"horizontal-tb","paragraphs":[{"chars":[{"text":"单击此处添加内容","color":{"color":"#000000","opacity":1},"fontSize":16,"fontStyle":"normal","fontFamily":"Misans 中等","fontWeight":"normal","textStroke":false,"letterSpacing":0,"textDecoration":[],"textStrokeColor":{"color":"#44e296","opacity":1},"textStrokeWidth":10}],"textAlign":"start","lineHeight":1.4}],"textShadow":false,"defaultText":true,"textShadowBlur":10,"textShadowAngle":45,"textShadowColor":{"color":"#000000","opacity":0.4},"textShadowOffset":10},"visible":true,"category":"text","position":{"x":0,"y":0},"rotation":0},"6834761fbM4SGswKd7qJ5jpidaAM87":{"id":"6834761fbM4SGswKd7qJ5jpidaAM87","size":{"width":34.13,"height":93.67},"scale":1,"locked":false,"setting":{"scale":1,"version":1747281518832,"children":["6834761fe2b3o5eZ1A9TygWsiBjFSR","6834761foaJeuQzHTDvADBvPE7CHyB"]},"visible":true,"category":"group","position":{"x":254.73,"y":136.05},"rotation":0},"6834761fbN9h6dsrL7APuFfwp6CVuy":{"id":"6834761fbN9h6dsrL7APuFfwp6CVuy","size":{"width":390.92,"height":321.16},"scale":1,"locked":false,"setting":{"blur":0,"fill":{"color":{"type":"linear","angle":270,"colorStops":[{"color":"#ffffff","offset":0,"opacity":0},{"color":"#acd3ff","offset":1,"opacity":0.48}]},"opacity":1},"path":"M64,32 L192,32 L256,96 L0,96 Z","scale":1,"shadow":{"blur":4,"show":false,"type":"outer","angle":90,"color":{"color":"#000000","opacity":0.25},"behind":true,"offset":4},"stroke":{"color":{"color":"#000000","opacity":1},"style":"solid","width":0,"radius":0},"version":1747280917299},"visible":true,"category":"shape","position":{"x":-11.46999999999997,"y":98.84000000000003},"rotation":90},"6834761fbZFsQmt2dQ4qKzEjj59ZDM":{"id":"6834761fbZFsQmt2dQ4qKzEjj59ZDM","size":{"width":126.13866304063693,"height":22.07426603211146},"scale":1,"locked":false,"parent":"6834761fgGhGpA2uSsD83Xk6LSA1Hz","setting":{"scale":0.985458305004976,"version":1747281338966,"autoSize":true,"direction":"horizontal-tb","paragraphs":[{"chars":[{"text":"单击此处添加内容","color":{"color":"#000000","opacity":1},"fontSize":16,"fontStyle":"normal","fontFamily":"Misans 中等","fontWeight":"normal","textStroke":false,"letterSpacing":0,"textDecoration":[],"textStrokeColor":{"color":"#44e296","opacity":1},"textStrokeWidth":10}],"textAlign":"start","lineHeight":1.4}],"textShadow":false,"defaultText":true,"textShadowBlur":10,"textShadowAngle":45,"textShadowColor":{"color":"#000000","opacity":0.4},"textShadowOffset":10},"visible":true,"category":"text","position":{"x":67.16060616598963,"y":0.0022342965845041363},"rotation":0},"6834761fcPY1RFrAk2mkzkeshtSUkW":{"id":"6834761fcPY1RFrAk2mkzkeshtSUkW","size":{"width":193.3,"height":62.5},"scale":1,"locked":false,"setting":{"scale":1,"version":1747281363966,"children":["6834761fqHYTq6LEsDUiKJgD7Etmgh","6834761fxpyt3sSZHDc7oskd5xRW16"]},"visible":true,"category":"group","position":{"x":50.48000000000002,"y":234.27000000000004},"rotation":0},"6834761fcdxTKK2sDCYs2CECEF2Mny":{"id":"6834761fcdxTKK2sDCYs2CECEF2Mny","size":{"width":59.52168162230055,"height":1.970916610009952},"scale":1,"locked":false,"parent":"6834761fmj6pLLq4cHYW6cuHjAkYH6","setting":{"end":"none","type":"line","scale":0.985458305004976,"start":"triangle","points":[[0,0],[60.400436824284604,0]],"shadow":{"blur":4,"show":false,"angle":90,"color":{"color":"#000000","opacity":0.25},"behind":true,"offset":4},"stroke":{"cap":"round","color":{"color":{"type":"linear","angle":90,"colorStops":[{"color":"#6ed9ea","offset":0,"opacity":1},{"color":"#247bff","offset":1,"opacity":1}]},"opacity":1},"style":"dotted","width":2,"radius":0},"version":1747281494232,"category":"straight"},"visible":true,"category":"line","position":{"x":-12.683579178787596,"y":62.440506852216714},"rotation":-90},"6834761fd7qHsesVSeJWnyH2p1yJFj":{"id":"6834761fd7qHsesVSeJWnyH2p1yJFj","size":{"width":80,"height":27.99},"scale":1,"locked":false,"setting":{"scale":1,"version":1747281809597,"autoSize":true,"direction":"horizontal-tb","paragraphs":[{"chars":[{"text":"实践执行﻿","color":{"color":"#000000","opacity":1},"fontSize":20,"fontStyle":"normal","fontFamily":"Misans 中等","fontWeight":"normal","textStroke":false,"letterSpacing":0,"textDecoration":[],"textStrokeColor":{"color":"#44e296","opacity":1},"textStrokeWidth":10}],"textAlign":"start","lineHeight":1.4}],"textShadow":false,"defaultText":true,"textShadowBlur":10,"textShadowAngle":45,"textShadowColor":{"color":"#000000","opacity":0.4},"textShadowOffset":10},"visible":true,"category":"text","position":{"x":527.7550000000001,"y":245.18},"rotation":0},"6834761fe2b3o5eZ1A9TygWsiBjFSR":{"id":"6834761fe2b3o5eZ1A9TygWsiBjFSR","size":{"width":34.13172055346784,"height":34.13172055346784},"scale":1,"locked":false,"parent":"6834761fbM4SGswKd7qJ5jpidaAM87","setting":{"alt":"图片","fit":"fill","src":"https://cdn.aitubiao.com/resource/vector/icon/office/1-circle-fill.svg","fill":{"colors":[{"color":"#0077ff","opacity":1}]},"flip":"none","size":{"width":34.63537765131067,"height":34.63537765131067},"scale":0.985458305004976,"stroke":{"show":false,"color":{"color":"#000000","opacity":1},"style":"solid","width":0.5,"radius":0},"opacity":1,"version":1748232978615,"transform":{"scale":1,"translate":{"x":0,"y":0}},"adjustment":{"src":"","color":{"hue":0,"blur":0,"noise":0,"enable":false,"contrast":0,"pixelate":1,"vibrance":0,"brightness":0,"saturation":0,"temperature":0},"filter":{"sepia":false,"emboss":false,"enable":false,"invert":false,"brownie":false,"sharpen":false,"vintage":false,"polaroid":false,"grayscale":false,"blackwhite":false,"kodachrome":false,"technicolor":false},"shadow":{"blur":10,"show":false,"angle":45,"color":{"color":"#000000","opacity":0.5},"offset":10},"version":""}},"visible":true,"category":"image","position":{"x":0.004341915101463201,"y":-0.0038333212195595934},"rotation":0},"6834761ffbEWcMTkED48CjnqCNZGV4":{"id":"6834761ffbEWcMTkED48CjnqCNZGV4","size":{"width":26.391121468769732,"height":26.391121468769732},"scale":1,"locked":false,"parent":"6834761f8JT1QDkadZDCaZmGz1zYye","setting":{"blur":0,"fill":{"color":"#ffffff","opacity":0},"path":"M0,0 L256,0 L256,256 L0,256 Z","scale":0.16290815721462795,"shadow":{"blur":4,"show":false,"type":"outer","angle":90,"color":{"color":"#000000","opacity":0.25},"behind":true,"offset":4},"stroke":{"color":{"color":"#1278ed","opacity":1},"style":"solid","width":1,"radius":4},"version":1747226984340},"visible":true,"category":"shape","position":{"x":0,"y":7.229999999999997},"rotation":0},"6834761ffbTrAmcqN3zAZSXzMSjLFN":{"id":"6834761ffbTrAmcqN3zAZSXzMSjLFN","size":{"width":193.3,"height":62.5},"scale":1,"locked":false,"setting":{"scale":1,"version":1747281363966,"children":["6834761frV1YLe5sqiVPajehsVvs4i","6834761fxxHGqKuqjXSnQjmQBwrobh"]},"visible":true,"category":"group","position":{"x":50.48000000000002,"y":136.05},"rotation":0},"6834761ffdduTh2moW6TZBiPq4RmTE":{"id":"6834761ffdduTh2moW6TZBiPq4RmTE","size":{"width":59.52168162230055,"height":1.970916610009952},"scale":1,"locked":false,"parent":"6834761fkQdoznP7wwVHPoSNjryiTM","setting":{"end":"none","type":"line","scale":0.985458305004976,"start":"triangle","points":[[0,0],[60.400436824284604,0]],"shadow":{"blur":4,"show":false,"angle":90,"color":{"color":"#000000","opacity":0.25},"behind":true,"offset":4},"stroke":{"cap":"round","color":{"color":{"type":"linear","angle":0,"colorStops":[{"color":"#599bff","offset":0,"opacity":1},{"color":"#1f30cf","offset":1,"opacity":1}]},"opacity":1},"style":"dotted","width":2,"radius":0},"version":1747281494232,"category":"straight"},"visible":true,"category":"line","position":{"x":-12.69458004399769,"y":62.91767945334817},"rotation":-90},"6834761fgGhGpA2uSsD83Xk6LSA1Hz":{"id":"6834761fgGhGpA2uSsD83Xk6LSA1Hz","size":{"width":193.3,"height":62.5},"scale":1,"locked":false,"setting":{"scale":1,"version":1747281363966,"children":["6834761fiX64tbFEvwcXw5B6z9bnB4","6834761fbZFsQmt2dQ4qKzEjj59ZDM"]},"visible":true,"category":"group","position":{"x":47.99000000000001,"y":331.98},"rotation":0},"6834761fgiP7yKiHoq8bZNLTA8ZaoM":{"id":"6834761fgiP7yKiHoq8bZNLTA8ZaoM","size":{"width":354.13,"height":266.03},"scale":1,"locked":false,"setting":{"scale":1,"version":1747281441892,"children":["6834761fnwNN8fo6LGePUpg78Lz6Nw","6834761f1GsZd5cAiLZuHyYJ9F7mgr","6834761foNW76ugwnBQja1MYxDeA5Q","6834761f8jf9QKB9pcCLpdpizYJpZu"]},"visible":true,"category":"group","position":{"x":303.21500000000003,"y":128.39000000000004},"rotation":0},"6834761fgzGZW8fecK61AnBAnucZ5V":{"id":"6834761fgzGZW8fecK61AnBAnucZ5V","size":{"width":34.13172055346784,"height":34.13172055346784},"scale":1,"locked":false,"setting":{"alt":"图片","fit":"fill","src":"https://cdn.aitubiao.com/resource/vector/icon/office/3-circle-fill.svg","fill":{"colors":[{"color":"#41dcfc","opacity":1}]},"flip":"none","size":{"width":34.13172055346784,"height":34.13172055346784},"scale":1,"stroke":{"show":false,"color":{"color":"#000000","opacity":1},"style":"solid","width":0.5,"radius":0},"opacity":1,"version":1747281538545,"transform":{"scale":1,"translate":{"x":0,"y":0}},"adjustment":{"src":"","color":{"hue":0,"blur":0,"noise":0,"enable":false,"contrast":0,"pixelate":1,"vibrance":0,"brightness":0,"saturation":0,"temperature":0},"filter":{"sepia":false,"emboss":false,"enable":false,"invert":false,"brownie":false,"sharpen":false,"vintage":false,"polaroid":false,"grayscale":false,"blackwhite":false,"kodachrome":false,"technicolor":false},"shadow":{"blur":10,"show":false,"angle":45,"color":{"color":"#000000","opacity":0.5},"offset":10},"version":""}},"visible":true,"category":"image","position":{"x":254.73926920662646,"y":331.98484146291986},"rotation":0},"6834761fh9LJma3t8RPmZDYDqMxEkU":{"id":"6834761fh9LJma3t8RPmZDYDqMxEkU","size":{"width":34.13172055346784,"height":34.13172055346784},"scale":1,"locked":false,"setting":{"alt":"图片","fit":"fill","src":"https://cdn.aitubiao.com/resource/vector/icon/office/3-circle-fill.svg","fill":{"colors":[{"color":"#41dcfc","opacity":1}]},"flip":"none","size":{"width":34.13172055346784,"height":34.13172055346784},"scale":1,"stroke":{"show":false,"color":{"color":"#000000","opacity":1},"style":"solid","width":0.5,"radius":0},"opacity":1,"version":1747281538542,"transform":{"scale":1,"translate":{"x":0,"y":0}},"adjustment":{"src":"","color":{"hue":0,"blur":0,"noise":0,"enable":false,"contrast":0,"pixelate":1,"vibrance":0,"brightness":0,"saturation":0,"temperature":0},"filter":{"sepia":false,"emboss":false,"enable":false,"invert":false,"brownie":false,"sharpen":false,"vintage":false,"polaroid":false,"grayscale":false,"blackwhite":false,"kodachrome":false,"technicolor":false},"shadow":{"blur":10,"show":false,"angle":45,"color":{"color":"#000000","opacity":0.5},"offset":10},"version":""}},"visible":true,"category":"image","position":{"x":671.7030502159912,"y":331.98484146291986},"rotation":0},"6834761fhvp2YyQxTi7Bn3Um7JtU9V":{"id":"6834761fhvp2YyQxTi7Bn3Um7JtU9V","size":{"width":196.15,"height":39.19},"scale":1,"locked":false,"parent":"6834761f8x6g2mXx6f2ByTz7ptjCyx","setting":{"scale":1,"version":1747281141743,"autoSize":false,"direction":"horizontal-tb","paragraphs":[{"chars":[{"text":"双击此处输入正文内容，内容要简单说明，保证阅读清晰度。","color":{"color":"#616161","opacity":1},"fontSize":14,"fontStyle":"normal","fontFamily":"Misans 常规","fontWeight":"normal","textStroke":false,"letterSpacing":0,"textDecoration":[],"textStrokeColor":{"color":"#44e296","opacity":1},"textStrokeWidth":10}],"textAlign":"start","lineHeight":1.4}],"textShadow":false,"defaultText":true,"textShadowBlur":10,"textShadowAngle":45,"textShadowColor":{"color":"#000000","opacity":0.4},"textShadowOffset":10},"visible":true,"category":"text","position":{"x":1.1368683772161603e-13,"y":24.230000000000018},"rotation":0},"6834761fiX64tbFEvwcXw5B6z9bnB4":{"id":"6834761fiX64tbFEvwcXw5B6z9bnB4","size":{"width":193.29764652672606,"height":38.62011097314501},"scale":1,"locked":false,"parent":"6834761fgGhGpA2uSsD83Xk6LSA1Hz","setting":{"scale":0.985458305004976,"version":1747281338966,"autoSize":false,"direction":"horizontal-tb","paragraphs":[{"chars":[{"text":"双击此处输入正文内容，内容要简单说明，保证阅读清晰度。","color":{"color":"#616161","opacity":1},"fontSize":14,"fontStyle":"normal","fontFamily":"Misans 常规","fontWeight":"normal","textStroke":false,"letterSpacing":0,"textDecoration":[],"textStrokeColor":{"color":"#44e296","opacity":1},"textStrokeWidth":10}],"textAlign":"end","lineHeight":1.4}],"textShadow":false,"defaultText":true,"textShadowBlur":10,"textShadowAngle":45,"textShadowColor":{"color":"#000000","opacity":0.4},"textShadowOffset":10},"visible":true,"category":"text","position":{"x":0.0016226799004144254,"y":23.879889026855096},"rotation":0},"6834761fjHKzkox1P1k7XJSbHHN4xP":{"id":"6834761fjHKzkox1P1k7XJSbHHN4xP","size":{"width":80,"height":27.99},"scale":1,"locked":false,"setting":{"scale":1,"version":1747281791622,"autoSize":true,"direction":"horizontal-tb","paragraphs":[{"chars":[{"text":"工作计划","color":{"color":"#000000","opacity":1},"fontSize":20,"fontStyle":"normal","fontFamily":"Misans 中等","fontWeight":"normal","textStroke":false,"letterSpacing":0,"textDecoration":[],"textStrokeColor":{"color":"#44e296","opacity":1},"textStrokeWidth":10}],"textAlign":"start","lineHeight":1.4}],"textShadow":false,"defaultText":true,"textShadowBlur":10,"textShadowAngle":45,"textShadowColor":{"color":"#000000","opacity":0.4},"textShadowOffset":10},"visible":true,"category":"text","position":{"x":352.84499999999997,"y":245.18},"rotation":0},"6834761fkQdoznP7wwVHPoSNjryiTM":{"id":"6834761fkQdoznP7wwVHPoSNjryiTM","size":{"width":34.13,"height":93.67},"scale":1,"locked":false,"setting":{"scale":1,"version":1747281523500,"children":["6834761f87pkJayoqYAP13YsAdoqVj","6834761ffdduTh2moW6TZBiPq4RmTE"]},"visible":true,"category":"group","position":{"x":671.7,"y":136.05},"rotation":0},"6834761fmHajEiENbFhvL6R97geXdc":{"id":"6834761fmHajEiENbFhvL6R97geXdc","size":{"width":128,"height":22.4},"scale":1,"locked":false,"parent":"6834761f8x6g2mXx6f2ByTz7ptjCyx","setting":{"scale":1,"version":1747237621297,"autoSize":true,"direction":"horizontal-tb","paragraphs":[{"chars":[{"text":"单击此处添加内容","color":{"color":"#000000","opacity":1},"fontSize":16,"fontStyle":"normal","fontFamily":"Misans 中等","fontWeight":"normal","textStroke":false,"letterSpacing":0,"textDecoration":[],"textStrokeColor":{"color":"#44e296","opacity":1},"textStrokeWidth":10}],"textAlign":"start","lineHeight":1.4}],"textShadow":false,"defaultText":true,"textShadowBlur":10,"textShadowAngle":45,"textShadowColor":{"color":"#000000","opacity":0.4},"textShadowOffset":10},"visible":true,"category":"text","position":{"x":2.2737367544323206e-13,"y":0},"rotation":0},"6834761fmWo6kKAV2kq9qTWR3Jspin":{"id":"6834761fmWo6kKAV2kq9qTWR3Jspin","size":{"width":21.01498121856883,"height":21.01498121856883},"scale":1,"locked":false,"parent":"6834761f8JT1QDkadZDCaZmGz1zYye","setting":{"blur":0,"fill":{"color":"#0077ff","opacity":1},"path":"M0,0 L256,0 L256,256 L0,256 Z","scale":0.12972210628746192,"shadow":{"blur":4,"show":false,"type":"outer","angle":90,"color":{"color":"#000000","opacity":0.25},"behind":true,"offset":4},"stroke":{"color":{"color":"#2b5afd","opacity":1},"style":"solid","width":0,"radius":4},"version":1748232990692},"visible":true,"category":"shape","position":{"x":7.9625994771016835,"y":16.550490571224593},"rotation":0},"6834761fmj6pLLq4cHYW6cuHjAkYH6":{"id":"6834761fmj6pLLq4cHYW6cuHjAkYH6","size":{"width":34.13,"height":93.18},"scale":1,"locked":false,"setting":{"scale":1,"version":1747281516241,"children":["6834761f7FR8c9pEgbDWQGohJJNK3H","6834761fcdxTKK2sDCYs2CECEF2Mny"]},"visible":true,"category":"group","position":{"x":254.74,"y":234.26},"rotation":0},"6834761fn587jcujrSHnrnkyDpXhqB":{"id":"6834761fn587jcujrSHnrnkyDpXhqB","size":{"width":215.62,"height":44.8},"scale":1,"locked":false,"parent":"6834761f8JT1QDkadZDCaZmGz1zYye","setting":{"scale":1,"version":1747223525328,"autoSize":false,"direction":"horizontal-tb","paragraphs":[{"chars":[{"text":"请输入标题","color":{"color":"#000000","opacity":1},"fontSize":32,"fontStyle":"normal","fontFamily":"Misans 加粗","fontWeight":"normal","textStroke":false,"letterSpacing":0,"textDecoration":[],"textStrokeColor":{"color":"#44e296","opacity":1},"textStrokeWidth":10}],"textAlign":"start","lineHeight":1.4}],"textShadow":false,"defaultText":true,"textShadowBlur":10,"textShadowAngle":45,"textShadowColor":{"color":"#000000","opacity":0.4},"textShadowOffset":10},"visible":true,"category":"text","position":{"x":54.86999999999999,"y":0},"rotation":0},"6834761fnmwTguC3RqESDh2PfqVBi3":{"id":"6834761fnmwTguC3RqESDh2PfqVBi3","size":{"width":34.13,"height":93.18},"scale":1,"locked":false,"setting":{"scale":1,"version":1747281521433,"children":["6834761f5nKv2TLhx7yqTxMEEYCJa4","6834761foPZ26bX8L8B27HHwQJqiWS"]},"visible":true,"category":"group","position":{"x":671.7,"y":234.26},"rotation":0},"6834761fnwNN8fo6LGePUpg78Lz6Nw":{"id":"6834761fnwNN8fo6LGePUpg78Lz6Nw","size":{"width":266.03,"height":170.11},"scale":1,"locked":false,"parent":"6834761fgiP7yKiHoq8bZNLTA8ZaoM","setting":{"blur":0,"fill":{"color":"#ffffff","opacity":1},"path":"M64,32 L192,32 L256,96 L0,96 Z","scale":1.251010020616602,"shadow":{"blur":4,"show":false,"type":"outer","angle":90,"color":{"color":"#000000","opacity":0.25},"behind":true,"offset":4},"stroke":{"color":{"color":"#000000","opacity":1},"style":"solid","width":0,"radius":0},"version":1747281338966},"visible":true,"category":"shape","position":{"x":-47.95999999999998,"y":47.95999999999998},"rotation":90},"6834761foNW76ugwnBQja1MYxDeA5Q":{"id":"6834761foNW76ugwnBQja1MYxDeA5Q","size":{"width":266.0244694360933,"height":162.60062032582104},"scale":1,"locked":false,"parent":"6834761fgiP7yKiHoq8bZNLTA8ZaoM","setting":{"blur":0,"fill":{"color":{"type":"linear","angle":0,"colorStops":[{"color":"#0077ff","offset":0,"opacity":0.45},{"color":"#009fff","offset":1,"opacity":0}]},"opacity":1},"path":"M64,32 L192,32 L256,96 L0,96 Z","scale":1.251010020616602,"shadow":{"blur":4,"show":false,"type":"outer","angle":90,"color":{"color":"#000000","opacity":0.25},"behind":true,"offset":4},"stroke":{"color":{"color":{"type":"linear","angle":0,"colorStops":[{"color":"#0077ff","offset":0.13301541548813584,"opacity":1},{"color":"#ffffff","offset":1,"opacity":0}]},"opacity":1},"style":"solid","width":1,"radius":4},"version":1747282478908},"visible":true,"category":"shape","position":{"x":-44.20620494365332,"y":51.71600749555296},"rotation":90},"6834761foPZ26bX8L8B27HHwQJqiWS":{"id":"6834761foPZ26bX8L8B27HHwQJqiWS","size":{"width":59.52168162230055,"height":1.970916610009952},"scale":1,"locked":false,"parent":"6834761fnmwTguC3RqESDh2PfqVBi3","setting":{"end":"none","type":"line","scale":0.985458305004976,"start":"triangle","points":[[0,0],[60.400436824284604,0]],"shadow":{"blur":4,"show":false,"angle":90,"color":{"color":"#000000","opacity":0.25},"behind":true,"offset":4},"stroke":{"cap":"round","color":{"color":{"type":"linear","angle":90,"colorStops":[{"color":"#6ed9ea","offset":0,"opacity":1},{"color":"#247bff","offset":1,"opacity":1}]},"opacity":1},"style":"dotted","width":2,"radius":0},"version":1747281494232,"category":"straight"},"visible":true,"category":"line","position":{"x":-12.679798169422725,"y":62.440506852216714},"rotation":-90},"6834761foTzsoCakwKnmw6UnXJR3KT":{"id":"6834761foTzsoCakwKnmw6UnXJR3KT","size":{"width":193.3,"height":62.5},"scale":1,"locked":false,"setting":{"scale":0.985458305004976,"version":1747281338966,"children":["6834761fsMabqcFNKH8wjJBDgnsgFY","6834761f153ULpebhGc4AzvsWyQJNF"]},"visible":true,"category":"group","position":{"x":716.1300000000001,"y":331.98},"rotation":0},"6834761foaJeuQzHTDvADBvPE7CHyB":{"id":"6834761foaJeuQzHTDvADBvPE7CHyB","size":{"width":59.52168162230055,"height":1.970916610009952},"scale":1,"locked":false,"parent":"6834761fbM4SGswKd7qJ5jpidaAM87","setting":{"end":"none","type":"line","scale":0.985458305004976,"start":"triangle","points":[[0,0],[60.400436824284604,0]],"shadow":{"blur":4,"show":false,"angle":90,"color":{"color":"#000000","opacity":0.25},"behind":true,"offset":4},"stroke":{"cap":"round","color":{"color":{"type":"linear","angle":0,"colorStops":[{"color":"#599bff","offset":0,"opacity":1},{"color":"#1f30cf","offset":1,"opacity":1}]},"opacity":1},"style":"dotted","width":2,"radius":0},"version":1747281494232,"category":"straight"},"visible":true,"category":"line","position":{"x":-12.688361053362627,"y":62.91767945334817},"rotation":-90},"6834761fpqh1S7UrAoCd9KGaMNYudM":{"id":"6834761fpqh1S7UrAoCd9KGaMNYudM","size":{"width":196.15,"height":39.19},"scale":1,"locked":false,"parent":"6834761fukQj9FHZr9JGY7zUdap1yT","setting":{"scale":1,"version":1747281141743,"autoSize":false,"direction":"horizontal-tb","paragraphs":[{"chars":[{"text":"双击此处输入正文内容，内容要简单说明，保证阅读清晰度。","color":{"color":"#616161","opacity":1},"fontSize":14,"fontStyle":"normal","fontFamily":"Misans 常规","fontWeight":"normal","textStroke":false,"letterSpacing":0,"textDecoration":[],"textStrokeColor":{"color":"#44e296","opacity":1},"textStrokeWidth":10}],"textAlign":"start","lineHeight":1.4}],"textShadow":false,"defaultText":true,"textShadowBlur":10,"textShadowAngle":45,"textShadowColor":{"color":"#000000","opacity":0.4},"textShadowOffset":10},"visible":true,"category":"text","position":{"x":0,"y":24.23},"rotation":0},"6834761fqHYTq6LEsDUiKJgD7Etmgh":{"id":"6834761fqHYTq6LEsDUiKJgD7Etmgh","size":{"width":193.29764652672606,"height":38.62011097314501},"scale":1,"locked":false,"parent":"6834761fcPY1RFrAk2mkzkeshtSUkW","setting":{"scale":0.985458305004976,"version":1747281338966,"autoSize":false,"direction":"horizontal-tb","paragraphs":[{"chars":[{"text":"双击此处输入正文内容，内容要简单说明，保证阅读清晰度。","color":{"color":"#616161","opacity":1},"fontSize":14,"fontStyle":"normal","fontFamily":"Misans 常规","fontWeight":"normal","textStroke":false,"letterSpacing":0,"textDecoration":[],"textStrokeColor":{"color":"#44e296","opacity":1},"textStrokeWidth":10}],"textAlign":"end","lineHeight":1.4}],"textShadow":false,"defaultText":true,"textShadowBlur":10,"textShadowAngle":45,"textShadowColor":{"color":"#000000","opacity":0.4},"textShadowOffset":10},"visible":true,"category":"text","position":{"x":0.0016226799004144254,"y":23.879889026855096},"rotation":0},"6834761frKUHGJBx49axYip3mXbGq7":{"id":"6834761frKUHGJBx49axYip3mXbGq7","size":{"width":40,"height":28},"scale":1,"locked":false,"parent":"6834761f9wv5M9MCjxJbtgXCSaP9i4","setting":{"scale":1,"version":1746884840363,"autoSize":true,"direction":"horizontal-tb","paragraphs":[{"chars":[{"text":"总结","color":{"color":"#000000","opacity":1},"fontSize":20,"fontStyle":"normal","fontFamily":"Misans 中等","fontWeight":"normal","textStroke":false,"letterSpacing":0,"textDecoration":[],"textStrokeColor":{"color":"#44e296","opacity":1},"textStrokeWidth":10}],"textAlign":"start","lineHeight":1.4}],"textShadow":false,"defaultText":true,"textShadowBlur":10,"textShadowAngle":45,"textShadowColor":{"color":"#000000","opacity":0.4},"textShadowOffset":10},"visible":true,"category":"text","position":{"x":16.02000000000004,"y":5.579999999999984},"rotation":0},"6834761frV1YLe5sqiVPajehsVvs4i":{"id":"6834761frV1YLe5sqiVPajehsVvs4i","size":{"width":193.29764652672606,"height":38.62011097314501},"scale":1,"locked":false,"parent":"6834761ffbTrAmcqN3zAZSXzMSjLFN","setting":{"scale":0.985458305004976,"version":1747281338966,"autoSize":false,"direction":"horizontal-tb","paragraphs":[{"chars":[{"text":"双击此处输入正文内容，内容要简单说明，保证阅读清晰度。","color":{"color":"#616161","opacity":1},"fontSize":14,"fontStyle":"normal","fontFamily":"Misans 常规","fontWeight":"normal","textStroke":false,"letterSpacing":0,"textDecoration":[],"textStrokeColor":{"color":"#44e296","opacity":1},"textStrokeWidth":10}],"textAlign":"end","lineHeight":1.4}],"textShadow":false,"defaultText":true,"textShadowBlur":10,"textShadowAngle":45,"textShadowColor":{"color":"#000000","opacity":0.4},"textShadowOffset":10},"visible":true,"category":"text","position":{"x":0.0016226799004144254,"y":23.879889026855096},"rotation":0},"6834761fsMabqcFNKH8wjJBDgnsgFY":{"id":"6834761fsMabqcFNKH8wjJBDgnsgFY","size":{"width":196.15,"height":39.19},"scale":1,"locked":false,"parent":"6834761foTzsoCakwKnmw6UnXJR3KT","setting":{"scale":1,"version":1747281141743,"autoSize":false,"direction":"horizontal-tb","paragraphs":[{"chars":[{"text":"双击此处输入正文内容，内容要简单说明，保证阅读清晰度。","color":{"color":"#616161","opacity":1},"fontSize":14,"fontStyle":"normal","fontFamily":"Misans 常规","fontWeight":"normal","textStroke":false,"letterSpacing":0,"textDecoration":[],"textStrokeColor":{"color":"#44e296","opacity":1},"textStrokeWidth":10}],"textAlign":"start","lineHeight":1.4}],"textShadow":false,"defaultText":true,"textShadowBlur":10,"textShadowAngle":45,"textShadowColor":{"color":"#000000","opacity":0.4},"textShadowOffset":10},"visible":true,"category":"text","position":{"x":0,"y":24.23},"rotation":0},"6834761ftBPMzL9QwaejsVmg5y8Abp":{"id":"6834761ftBPMzL9QwaejsVmg5y8Abp","size":{"width":390.92,"height":325.68},"scale":1,"locked":false,"setting":{"blur":0,"fill":{"color":{"type":"linear","angle":270,"colorStops":[{"color":"#ffffff","offset":0,"opacity":0},{"color":"#acd3ff","offset":1,"opacity":0.48}]},"opacity":1},"path":"M64,32 L192,32 L256,96 L0,96 Z","scale":1,"shadow":{"blur":4,"show":false,"type":"outer","angle":90,"color":{"color":"#000000","opacity":0.25},"behind":true,"offset":4},"stroke":{"color":{"color":"#000000","opacity":1},"style":"solid","width":0,"radius":0},"version":1747280917299},"visible":true,"category":"shape","position":{"x":577.3900000000001,"y":96.33000000000001},"rotation":-90.43},"6834761fudGSh9FWZjn7MjLsfxp87S":{"id":"6834761fudGSh9FWZjn7MjLsfxp87S","size":{"width":527.45,"height":66.62},"scale":1,"locked":false,"setting":{"blur":0,"fill":{"color":"#fffefe","opacity":1},"path":"M0,0 L256,0 L256,256 L0,256 Z","scale":1,"shadow":{"blur":7,"show":true,"type":"outer","angle":89,"color":{"color":"#000000","opacity":0.08},"behind":true,"offset":4},"stroke":{"color":{"color":"#0077ff","opacity":1},"style":"solid","width":0,"radius":24},"version":1747388849160},"visible":true,"category":"shape","position":{"x":222.8,"y":422.53},"rotation":0},"6834761fukQj9FHZr9JGY7zUdap1yT":{"id":"6834761fukQj9FHZr9JGY7zUdap1yT","size":{"width":193.3,"height":62.5},"scale":1,"locked":false,"setting":{"scale":0.985458305004976,"version":1747281338966,"children":["6834761fpqh1S7UrAoCd9KGaMNYudM","6834761fbDoyUVm3FsR42X3fWt6BK6"]},"visible":true,"category":"group","position":{"x":716.1300000000001,"y":136.05},"rotation":0},"6834761fxpyt3sSZHDc7oskd5xRW16":{"id":"6834761fxpyt3sSZHDc7oskd5xRW16","size":{"width":126.13866304063693,"height":22.07426603211146},"scale":1,"locked":false,"parent":"6834761fcPY1RFrAk2mkzkeshtSUkW","setting":{"scale":0.985458305004976,"version":1747281338966,"autoSize":true,"direction":"horizontal-tb","paragraphs":[{"chars":[{"text":"单击此处添加内容","color":{"color":"#000000","opacity":1},"fontSize":16,"fontStyle":"normal","fontFamily":"Misans 中等","fontWeight":"normal","textStroke":false,"letterSpacing":0,"textDecoration":[],"textStrokeColor":{"color":"#44e296","opacity":1},"textStrokeWidth":10}],"textAlign":"start","lineHeight":1.4}],"textShadow":false,"defaultText":true,"textShadowBlur":10,"textShadowAngle":45,"textShadowColor":{"color":"#000000","opacity":0.4},"textShadowOffset":10},"visible":true,"category":"text","position":{"x":67.16060616598963,"y":0.0022342965845041363},"rotation":0},"6834761fxxHGqKuqjXSnQjmQBwrobh":{"id":"6834761fxxHGqKuqjXSnQjmQBwrobh","size":{"width":126.13866304063693,"height":22.07426603211146},"scale":1,"locked":false,"parent":"6834761ffbTrAmcqN3zAZSXzMSjLFN","setting":{"scale":0.985458305004976,"version":1747281338966,"autoSize":true,"direction":"horizontal-tb","paragraphs":[{"chars":[{"text":"单击此处添加内容","color":{"color":"#000000","opacity":1},"fontSize":16,"fontStyle":"normal","fontFamily":"Misans 中等","fontWeight":"normal","textStroke":false,"letterSpacing":0,"textDecoration":[],"textStrokeColor":{"color":"#44e296","opacity":1},"textStrokeWidth":10}],"textAlign":"start","lineHeight":1.4}],"textShadow":false,"defaultText":true,"textShadowBlur":10,"textShadowAngle":45,"textShadowColor":{"color":"#000000","opacity":0.4},"textShadowOffset":10},"visible":true,"category":"text","position":{"x":67.16060616598963,"y":0.0022342965845041363},"rotation":0}},"background":{"locked":false}}},"orders":["cmb55yumr05mlh0o679g3gldj"]}}}