{"code":0,"msg":"ok","data":{"id":"cmbqc52ib003g3c3e755ld7m1","title":"绿色科技工作汇报单页","width":960,"height":540,"priceStrategy":"free","snapshot":"https://cdn.aitubiao.com/cover/cmb5vol9d062xh0o679yvh2pv_1749434968126.png","createdAt":"2025-06-10T09:44:08.062Z","updatedAt":"2025-06-11T09:05:51.122Z","dimension":"PPT","tags":[{"id":"cmbrq5yxz000pcj3e5cvx26ud","name":"工作总结","dimensionId":9,"dimension":{"scopes":["ppt"]}},{"id":"cmbrq5yxz000qcj3eg2ked8a2","name":"市场营销","dimensionId":9,"dimension":{"scopes":["ppt"]}},{"id":"cmbrq5yxz000tcj3e3re6fqkd","name":"项目汇报","dimensionId":9,"dimension":{"scopes":["ppt"]}},{"id":"cmbrq5yy0000vcj3eg5f2axr5","name":"单图表","dimensionId":10,"dimension":{"scopes":["ppt"]}}],"author":{"id":"clzb5ewqk0003j5yc55w8zbuk","name":"coveabc","avatar":null,"tier":{"id":"ckxtg2o0j00019zue6g8t68kc","name":"会员用户"}},"data":{"pages":{"cmb5vol9d062yh0o6hwyn9ksz":{"id":"cmb5vol9d062yh0o6hwyn9ksz","name":"First Page","size":{"width":960,"height":540},"theme":{"colors":[]},"locked":false,"orders":["68351ede2tVtGW1qq7ZJtFSMm31FFf","68351edesk7yeQ1T2Gg5hiccE7ptG8","68351edepVpd4wjSaN54y9omH7EytB","68351edencBXn3jCjZMCBYDJDym1pE","68351ede8urS1kN7pLkArtV8ZyL6Dp","68351edeiBZviAbcKzPSXNTdwMSFXU","68351edefgehCNZGKKjsCsRMqgz8MC","68351edeg9QZxn42UAz6Fb28SdiVJ8","68351edewcGkfVGCAg8Nn1hgPH3C3W","68351edeir6iho2XPHHk7spLdhzb2T","68351edeiuWSv1eXugtoMvCDgNNvdP","68351ede1oG77Kayya77xcM9cDcnyH","68351edekYJ73QNxQzgbAHraKtVcd7","68351edepH9eBq6PrVCwYUktLvb5Sx","68351ede39RN1UN9fxTW61ReSwGGVD","68351edejg5biP7hHMhMe1Be8vLxHS","68351edeg68NGicThLVS62gZix1cYi","68351ede5FmgMZprziv837nAeSJZzc","68351ede3vw29FzGDaH2cCKdesBSkM","68351edeuEQ6a2qbThzMXxUQcjSPsn","68351eder1NqkzFyfM9aHx7RALQ5kq","68351ederAVLEPnd6DBiDK4xSQ8BvP","68351ede5rDYPwJFpoqmfVsng5GMb7","68351ededALTPFwkeDHhAQNNwif647","68351edeib8YQ6cU1Z54zqtMPYa2Eo","68351edewEdkTdznoby5PXDfz1oeXg","68351ede1LuEzko48Fb2adMXYNTPgv","68351eded1FG15BpiRp5DjpdEfPbTf","68351ededx4dLVUpBBHfU8f2SCcs1g","68351eded92gk23mJCB5zVvg7g44rk","68351edear3eCitzBkcjjgCaEgXTGM","68351ede5qcHJck3c3jStQJF1HXbi7","68351ede4Y4EgNE7SwT3KDU5hpaAF9","68351edesX3sKb4WzBBBK3SPTrp8Fw","68351edecGZPtBDuPod89G6orMikcK"],"visible":true,"elements":{"68351ede15rYVjGtknBQDTFEtq3JFW":{"id":"68351ede15rYVjGtknBQDTFEtq3JFW","size":{"width":160,"height":44.8},"scale":1,"locked":false,"parent":"68351edecGZPtBDuPod89G6orMikcK","setting":{"scale":1,"version":1748226388642,"autoSize":true,"direction":"horizontal-tb","paragraphs":[{"chars":[{"text":"请输入标题","color":{"color":"#000000","opacity":1},"fontSize":32,"fontStyle":"normal","fontFamily":"Misans 加粗","fontWeight":"normal","textStroke":false,"letterSpacing":0,"textDecoration":[],"textStrokeColor":{"color":"#44e296","opacity":1},"textStrokeWidth":10}],"textAlign":"start","lineHeight":1.4}],"textShadow":false,"defaultText":true,"textShadowBlur":10,"textShadowAngle":45,"textShadowColor":{"color":"#000000","opacity":0.4},"textShadowOffset":10},"visible":true,"category":"text","position":{"x":26.009999999999998,"y":0},"rotation":0},"68351ede1LuEzko48Fb2adMXYNTPgv":{"id":"68351ede1LuEzko48Fb2adMXYNTPgv","size":{"width":10,"height":10},"scale":1,"locked":false,"setting":{"blur":0,"fill":{"color":"#c8c8c8","opacity":1},"path":"M128,0 L256,256 L0,256 Z","scale":0.050123456790123436,"shadow":{"blur":4,"show":false,"type":"outer","angle":90,"color":{"color":"#000000","opacity":0.25},"behind":true,"offset":4},"stroke":{"color":{"color":"#000000","opacity":1},"style":"solid","width":0,"radius":0},"version":1746773483344},"visible":true,"category":"shape","position":{"x":552.032163690182,"y":326.13223735412475},"rotation":180.11},"68351ede1oG77Kayya77xcM9cDcnyH":{"id":"68351ede1oG77Kayya77xcM9cDcnyH","size":{"width":46.55,"height":28},"scale":1,"locked":false,"setting":{"scale":0.5717991199956544,"version":1746773197587,"autoSize":true,"direction":"horizontal-tb","paragraphs":[{"chars":[{"text":"2022","color":{"color":"#444444","opacity":1},"fontSize":34.9773186082413,"fontStyle":"normal","fontFamily":"Misans 中等","fontWeight":"normal","textStroke":false,"letterSpacing":0,"textDecoration":[],"textStrokeColor":{"color":"#44e296","opacity":1},"textStrokeWidth":10}],"textAlign":"start","lineHeight":1.4}],"textShadow":false,"defaultText":true,"textShadowBlur":10,"textShadowAngle":45,"textShadowColor":{"color":"#000000","opacity":0.4},"textShadowOffset":10},"visible":true,"category":"text","position":{"x":576.44,"y":287.125},"rotation":0},"68351ede2tVtGW1qq7ZJtFSMm31FFf":{"id":"68351ede2tVtGW1qq7ZJtFSMm31FFf","size":{"width":119.5,"height":50.01},"scale":1,"locked":false,"setting":{"blur":0,"fill":{"color":"#02a882","opacity":1},"path":"M0,0 L256,0 L256,256 L0,256 Z","scale":1,"shadow":{"blur":4,"show":false,"type":"outer","angle":90,"color":{"color":"#000000","opacity":0.25},"behind":true,"offset":4},"stroke":{"color":{"color":"#000000","opacity":1},"style":"solid","width":0,"radius":0},"version":1746773573033},"visible":true,"category":"shape","position":{"x":54.45999999999999,"y":276.115},"rotation":0},"68351ede39RN1UN9fxTW61ReSwGGVD":{"id":"68351ede39RN1UN9fxTW61ReSwGGVD","size":{"width":10,"height":10},"scale":1,"locked":false,"setting":{"blur":0,"fill":{"color":"#c8c8c8","opacity":1},"path":"M128,0 L256,256 L0,256 Z","scale":0.050123456790123436,"shadow":{"blur":4,"show":false,"type":"outer","angle":90,"color":{"color":"#000000","opacity":0.25},"behind":true,"offset":4},"stroke":{"color":{"color":"#000000","opacity":1},"style":"solid","width":0,"radius":0},"version":1746773412665},"visible":true,"category":"shape","position":{"x":64.84999999999997,"y":266.12},"rotation":0},"68351ede3vw29FzGDaH2cCKdesBSkM":{"id":"68351ede3vw29FzGDaH2cCKdesBSkM","size":{"width":10,"height":10},"scale":1,"locked":false,"setting":{"blur":0,"fill":{"color":"#c8c8c8","opacity":1},"path":"M128,0 L256,256 L0,256 Z","scale":0.050123456790123436,"shadow":{"blur":4,"show":false,"type":"outer","angle":90,"color":{"color":"#000000","opacity":0.25},"behind":true,"offset":4},"stroke":{"color":{"color":"#000000","opacity":1},"style":"solid","width":0,"radius":0},"version":1746773483344},"visible":true,"category":"shape","position":{"x":187.21216369018185,"y":326.13223735412475},"rotation":180.11},"68351ede4Y4EgNE7SwT3KDU5hpaAF9":{"id":"68351ede4Y4EgNE7SwT3KDU5hpaAF9","size":{"width":108,"height":25.2},"scale":1,"locked":false,"setting":{"scale":1,"version":1748226965585,"autoSize":true,"direction":"horizontal-tb","paragraphs":[{"chars":[{"text":"双击添加标题","color":{"color":"#000000","opacity":1},"fontSize":18,"fontStyle":"normal","fontFamily":"Misans 加粗","fontWeight":"normal","textStroke":false,"letterSpacing":0,"textDecoration":[],"textStrokeColor":{"color":"#44e296","opacity":1},"textStrokeWidth":10}],"textAlign":"start","lineHeight":1.4}],"textShadow":false,"defaultText":true,"textShadowBlur":10,"textShadowAngle":45,"textShadowColor":{"color":"#000000","opacity":0.4},"textShadowOffset":10},"visible":true,"category":"text","position":{"x":693.57,"y":121.55},"rotation":0},"68351ede5FmgMZprziv837nAeSJZzc":{"id":"68351ede5FmgMZprziv837nAeSJZzc","size":{"width":153.49,"height":50.39},"scale":1,"locked":false,"setting":{"scale":0.7729029172470115,"version":1748239239009,"autoSize":false,"direction":"horizontal-tb","paragraphs":[{"chars":[{"text":"双击此处输入正文内容,内容要求简单明了扼要说明,不必过于繁琐,保证阅读清晰度。","color":{"color":"#616161","opacity":1},"fontSize":15.525882659031193,"fontStyle":"normal","fontFamily":"Misans 常规","fontWeight":"normal","textStroke":false,"letterSpacing":0,"textDecoration":[],"textStrokeColor":{"color":"#44e296","opacity":1},"textStrokeWidth":10}],"textAlign":"start","lineHeight":1.4}],"textShadow":false,"defaultText":true,"textShadowBlur":10,"textShadowAngle":45,"textShadowColor":{"color":"#000000","opacity":0.4},"textShadowOffset":10},"visible":true,"category":"text","position":{"x":83.83999999999997,"y":155.85000000000002},"rotation":0},"68351ede5qcHJck3c3jStQJF1HXbi7":{"id":"68351ede5qcHJck3c3jStQJF1HXbi7","size":{"width":149.56,"height":2},"scale":1,"locked":false,"setting":{"end":"none","type":"line","scale":1,"start":"none","points":[[0,0],[149.56073849777556,0]],"shadow":{"blur":4,"show":false,"angle":90,"color":{"color":"#000000","opacity":0.25},"behind":true,"offset":4},"stroke":{"cap":"butt","color":{"color":"#c8c8c8","opacity":1},"style":"dotted","width":2,"radius":0},"version":1746773412665,"category":"straight"},"visible":true,"category":"line","position":{"x":604.4899999999999,"y":195.34},"rotation":89.82},"68351ede5rDYPwJFpoqmfVsng5GMb7":{"id":"68351ede5rDYPwJFpoqmfVsng5GMb7","size":{"width":10,"height":10},"scale":1,"locked":false,"setting":{"blur":0,"fill":{"color":"#c8c8c8","opacity":1},"path":"M128,0 L256,256 L0,256 Z","scale":0.050123456790123436,"shadow":{"blur":4,"show":false,"type":"outer","angle":90,"color":{"color":"#000000","opacity":0.25},"behind":true,"offset":4},"stroke":{"color":{"color":"#000000","opacity":1},"style":"solid","width":0,"radius":0},"version":1746773412665},"visible":true,"category":"shape","position":{"x":431.78,"y":266.12},"rotation":0},"68351ede8urS1kN7pLkArtV8ZyL6Dp":{"id":"68351ede8urS1kN7pLkArtV8ZyL6Dp","size":{"width":119.5,"height":50.01},"scale":1,"locked":false,"setting":{"blur":0,"fill":{"color":"#C1EADA","opacity":1},"path":"M0,0 L256,0 L256,256 L0,256 Z","scale":1,"shadow":{"blur":4,"show":false,"type":"outer","angle":90,"color":{"color":"#000000","opacity":0.25},"behind":true,"offset":4},"stroke":{"color":{"color":"#000000","opacity":1},"style":"solid","width":0,"radius":0},"version":1748227516187},"visible":true,"category":"shape","position":{"x":541.3233333333332,"y":276.115},"rotation":0},"68351edear3eCitzBkcjjgCaEgXTGM":{"id":"68351edear3eCitzBkcjjgCaEgXTGM","size":{"width":10,"height":10},"scale":1,"locked":false,"setting":{"blur":0,"fill":{"color":"#c8c8c8","opacity":1},"path":"M128,0 L256,256 L0,256 Z","scale":0.050123456790123436,"shadow":{"blur":4,"show":false,"type":"outer","angle":90,"color":{"color":"#000000","opacity":0.25},"behind":true,"offset":4},"stroke":{"color":{"color":"#000000","opacity":1},"style":"solid","width":0,"radius":0},"version":1746773412665},"visible":true,"category":"shape","position":{"x":674.5799999999999,"y":266.12},"rotation":0},"68351edecGZPtBDuPod89G6orMikcK":{"id":"68351edecGZPtBDuPod89G6orMikcK","size":{"width":186.01,"height":44.8},"scale":1,"locked":false,"setting":{"scale":1,"version":1748226428898,"children":["68351ede15rYVjGtknBQDTFEtq3JFW","68351edemojr18PC4ABgjorJ8e6s5F"]},"visible":true,"category":"group","position":{"x":13.81,"y":9.89},"rotation":0},"68351eded1FG15BpiRp5DjpdEfPbTf":{"id":"68351eded1FG15BpiRp5DjpdEfPbTf","size":{"width":149.56,"height":2},"scale":1,"locked":false,"setting":{"end":"none","type":"line","scale":1,"start":"none","points":[[0,0],[149.56073849777556,0]],"shadow":{"blur":4,"show":false,"angle":90,"color":{"color":"#000000","opacity":0.25},"behind":true,"offset":4},"stroke":{"cap":"butt","color":{"color":"#c8c8c8","opacity":1},"style":"dotted","width":2,"radius":0},"version":1746773483344,"category":"straight"},"visible":true,"category":"line","position":{"x":482.4185959134566,"y":404.91269469636796},"rotation":269.93},"68351eded92gk23mJCB5zVvg7g44rk":{"id":"68351eded92gk23mJCB5zVvg7g44rk","size":{"width":153.49,"height":50.39},"scale":1,"locked":false,"setting":{"scale":0.7729029172470115,"version":1748226722291,"autoSize":false,"direction":"horizontal-tb","paragraphs":[{"chars":[{"text":"双击此处输入正文内容,内容要求简单明了扼要说明,不必过于繁琐,保证阅读清晰度。","color":{"color":"#000000","opacity":1},"fontSize":15.525882659031195,"fontStyle":"normal","fontFamily":"Misans 常规","fontWeight":"normal","textStroke":false,"letterSpacing":0,"textDecoration":[],"textStrokeColor":{"color":"#44e296","opacity":1},"textStrokeWidth":10}],"textAlign":"start","lineHeight":1.4}],"textShadow":false,"defaultText":true,"textShadowBlur":10,"textShadowAngle":45,"textShadowColor":{"color":"#000000","opacity":0.4},"textShadowOffset":10},"visible":true,"category":"text","position":{"x":576.4438967052764,"y":430.2999319160899},"rotation":0},"68351ededALTPFwkeDHhAQNNwif647":{"id":"68351ededALTPFwkeDHhAQNNwif647","size":{"width":149.56,"height":2},"scale":1,"locked":false,"setting":{"end":"none","type":"line","scale":1,"start":"none","points":[[0,0],[149.56073849777556,0]],"shadow":{"blur":4,"show":false,"angle":90,"color":{"color":"#000000","opacity":0.25},"behind":true,"offset":4},"stroke":{"cap":"butt","color":{"color":"#c8c8c8","opacity":1},"style":"dotted","width":2,"radius":0},"version":1746773412665,"category":"straight"},"visible":true,"category":"line","position":{"x":361.68999999999994,"y":195.34},"rotation":89.82},"68351ededx4dLVUpBBHfU8f2SCcs1g":{"id":"68351ededx4dLVUpBBHfU8f2SCcs1g","size":{"width":108,"height":25.2},"scale":1,"locked":false,"setting":{"scale":1,"version":1748226970854,"autoSize":true,"direction":"horizontal-tb","paragraphs":[{"chars":[{"text":"双击添加标题","color":{"color":"#000000","opacity":1},"fontSize":18,"fontStyle":"normal","fontFamily":"Misans 加粗","fontWeight":"normal","textStroke":false,"letterSpacing":0,"textDecoration":[],"textStrokeColor":{"color":"#44e296","opacity":1},"textStrokeWidth":10}],"textAlign":"start","lineHeight":1.4}],"textShadow":false,"defaultText":true,"textShadowBlur":10,"textShadowAngle":45,"textShadowColor":{"color":"#000000","opacity":0.4},"textShadowOffset":10},"visible":true,"category":"text","position":{"x":576.44,"y":396},"rotation":0},"68351edefgehCNZGKKjsCsRMqgz8MC":{"id":"68351edefgehCNZGKKjsCsRMqgz8MC","size":{"width":119.5,"height":50.01},"scale":1,"locked":false,"setting":{"blur":0,"fill":{"color":"#02a882","opacity":1},"path":"M0,0 L256,0 L256,256 L0,256 Z","scale":1,"shadow":{"blur":4,"show":false,"type":"outer","angle":90,"color":{"color":"#000000","opacity":0.25},"behind":true,"offset":4},"stroke":{"color":{"color":"#000000","opacity":1},"style":"solid","width":0,"radius":0},"version":1746773592327},"visible":true,"category":"shape","position":{"x":784.76,"y":276.115},"rotation":0},"68351edeg68NGicThLVS62gZix1cYi":{"id":"68351edeg68NGicThLVS62gZix1cYi","size":{"width":108,"height":25.2},"scale":1,"locked":false,"setting":{"scale":1,"version":1748226959737,"autoSize":true,"direction":"horizontal-tb","paragraphs":[{"chars":[{"text":"双击添加标题","color":{"color":"#000000","opacity":1},"fontSize":18,"fontStyle":"normal","fontFamily":"Misans 加粗","fontWeight":"normal","textStroke":false,"letterSpacing":0,"textDecoration":[],"textStrokeColor":{"color":"#44e296","opacity":1},"textStrokeWidth":10}],"textAlign":"start","lineHeight":1.4}],"textShadow":false,"defaultText":true,"textShadowBlur":10,"textShadowAngle":45,"textShadowColor":{"color":"#000000","opacity":0.4},"textShadowOffset":10},"visible":true,"category":"text","position":{"x":83.84,"y":121.55},"rotation":0},"68351edeg9QZxn42UAz6Fb28SdiVJ8":{"id":"68351edeg9QZxn42UAz6Fb28SdiVJ8","size":{"width":45.2,"height":28},"scale":1,"locked":false,"setting":{"scale":0.5717991199956544,"version":1746773172698,"autoSize":true,"direction":"horizontal-tb","paragraphs":[{"chars":[{"text":"2018","color":{"color":"#ffffff","opacity":1},"fontSize":34.9773186082413,"fontStyle":"normal","fontFamily":"Misans 中等","fontWeight":"normal","textStroke":false,"letterSpacing":0,"textDecoration":[],"textStrokeColor":{"color":"#44e296","opacity":1},"textStrokeWidth":10}],"textAlign":"start","lineHeight":1.4}],"textShadow":false,"defaultText":true,"textShadowBlur":10,"textShadowAngle":45,"textShadowColor":{"color":"#000000","opacity":0.4},"textShadowOffset":10},"visible":true,"category":"text","position":{"x":90.42999999999998,"y":287.125},"rotation":0},"68351edeiBZviAbcKzPSXNTdwMSFXU":{"id":"68351edeiBZviAbcKzPSXNTdwMSFXU","size":{"width":119.5,"height":50.01},"scale":1,"locked":false,"setting":{"blur":0,"fill":{"color":"#C1EADA","opacity":1},"path":"M0,0 L256,0 L256,256 L0,256 Z","scale":1,"shadow":{"blur":4,"show":false,"type":"outer","angle":90,"color":{"color":"#000000","opacity":0.25},"behind":true,"offset":4},"stroke":{"color":{"color":"#000000","opacity":1},"style":"solid","width":0,"radius":0},"version":1748227520460},"visible":true,"category":"shape","position":{"x":663.0466666666666,"y":276.115},"rotation":0},"68351edeib8YQ6cU1Z54zqtMPYa2Eo":{"id":"68351edeib8YQ6cU1Z54zqtMPYa2Eo","size":{"width":108,"height":25.2},"scale":1,"locked":false,"setting":{"scale":1,"version":1748226963060,"autoSize":true,"direction":"horizontal-tb","paragraphs":[{"chars":[{"text":"双击添加标题","color":{"color":"#000000","opacity":1},"fontSize":18,"fontStyle":"normal","fontFamily":"Misans 加粗","fontWeight":"normal","textStroke":false,"letterSpacing":0,"textDecoration":[],"textStrokeColor":{"color":"#44e296","opacity":1},"textStrokeWidth":10}],"textAlign":"start","lineHeight":1.4}],"textShadow":false,"defaultText":true,"textShadowBlur":10,"textShadowAngle":45,"textShadowColor":{"color":"#000000","opacity":0.4},"textShadowOffset":10},"visible":true,"category":"text","position":{"x":450.77,"y":121.55},"rotation":0},"68351edeir6iho2XPHHk7spLdhzb2T":{"id":"68351edeir6iho2XPHHk7spLdhzb2T","size":{"width":47.55,"height":28},"scale":1,"locked":false,"setting":{"scale":0.5717991199956544,"version":1746773189805,"autoSize":true,"direction":"horizontal-tb","paragraphs":[{"chars":[{"text":"2020","color":{"color":"#444444","opacity":1},"fontSize":34.9773186082413,"fontStyle":"normal","fontFamily":"Misans 中等","fontWeight":"normal","textStroke":false,"letterSpacing":0,"textDecoration":[],"textStrokeColor":{"color":"#44e296","opacity":1},"textStrokeWidth":10}],"textAlign":"start","lineHeight":1.4}],"textShadow":false,"defaultText":true,"textShadowBlur":10,"textShadowAngle":45,"textShadowColor":{"color":"#000000","opacity":0.4},"textShadowOffset":10},"visible":true,"category":"text","position":{"x":333.43999999999994,"y":287.125},"rotation":0},"68351edeiuWSv1eXugtoMvCDgNNvdP":{"id":"68351edeiuWSv1eXugtoMvCDgNNvdP","size":{"width":43.42,"height":28},"scale":1,"locked":false,"setting":{"scale":0.5717991199956544,"version":1746773192745,"autoSize":true,"direction":"horizontal-tb","paragraphs":[{"chars":[{"text":"2021","color":{"color":"#444444","opacity":1},"fontSize":34.9773186082413,"fontStyle":"normal","fontFamily":"Misans 中等","fontWeight":"normal","textStroke":false,"letterSpacing":0,"textDecoration":[],"textStrokeColor":{"color":"#44e296","opacity":1},"textStrokeWidth":10}],"textAlign":"start","lineHeight":1.4}],"textShadow":false,"defaultText":true,"textShadowBlur":10,"textShadowAngle":45,"textShadowColor":{"color":"#000000","opacity":0.4},"textShadowOffset":10},"visible":true,"category":"text","position":{"x":454.93999999999994,"y":287.125},"rotation":0},"68351edejg5biP7hHMhMe1Be8vLxHS":{"id":"68351edejg5biP7hHMhMe1Be8vLxHS","size":{"width":149.56,"height":2},"scale":1,"locked":false,"setting":{"end":"none","type":"line","scale":1,"start":"none","points":[[0,0],[149.56073849777556,0]],"shadow":{"blur":4,"show":false,"angle":90,"color":{"color":"#000000","opacity":0.25},"behind":true,"offset":4},"stroke":{"cap":"butt","color":{"color":"#c8c8c8","opacity":1},"style":"dotted","width":2,"radius":0},"version":1746773412665,"category":"straight"},"visible":true,"category":"line","position":{"x":-5.2400000000000375,"y":195.34},"rotation":89.82},"68351edekYJ73QNxQzgbAHraKtVcd7":{"id":"68351edekYJ73QNxQzgbAHraKtVcd7","size":{"width":46.5,"height":28},"scale":1,"locked":false,"setting":{"scale":0.5717991199956544,"version":1746773202625,"autoSize":true,"direction":"horizontal-tb","paragraphs":[{"chars":[{"text":"2023","color":{"color":"#444444","opacity":1},"fontSize":34.9773186082413,"fontStyle":"normal","fontFamily":"Misans 中等","fontWeight":"normal","textStroke":false,"letterSpacing":0,"textDecoration":[],"textStrokeColor":{"color":"#44e296","opacity":1},"textStrokeWidth":10}],"textAlign":"start","lineHeight":1.4}],"textShadow":false,"defaultText":true,"textShadowBlur":10,"textShadowAngle":45,"textShadowColor":{"color":"#000000","opacity":0.4},"textShadowOffset":10},"visible":true,"category":"text","position":{"x":698.24,"y":287.125},"rotation":0},"68351edemojr18PC4ABgjorJ8e6s5F":{"id":"68351edemojr18PC4ABgjorJ8e6s5F","size":{"width":18.26603088739766,"height":14.980400393207734},"scale":1,"locked":false,"parent":"68351edecGZPtBDuPod89G6orMikcK","setting":{"blur":0,"fill":{"color":"#67d498","opacity":1},"path":"M128,0 L256,256 L0,256 Z","scale":0.1127532770827016,"shadow":{"blur":4,"show":false,"type":"outer","angle":90,"color":{"color":"#000000","opacity":0.25},"behind":true,"offset":4},"stroke":{"color":{"color":"#000000","opacity":1},"style":"solid","width":0,"radius":2},"version":1748226381143},"visible":true,"category":"shape","position":{"x":-1.640000000000013,"y":14.909999999999997},"rotation":90},"68351edencBXn3jCjZMCBYDJDym1pE":{"id":"68351edencBXn3jCjZMCBYDJDym1pE","size":{"width":119.5,"height":50.01},"scale":1,"locked":false,"setting":{"blur":0,"fill":{"color":"#C1EADA","opacity":1},"path":"M0,0 L256,0 L256,256 L0,256 Z","scale":1,"shadow":{"blur":4,"show":false,"type":"outer","angle":90,"color":{"color":"#000000","opacity":0.25},"behind":true,"offset":4},"stroke":{"color":{"color":"#000000","opacity":1},"style":"solid","width":0,"radius":0},"version":1748227511853},"visible":true,"category":"shape","position":{"x":419.60999999999984,"y":276.115},"rotation":0},"68351edepH9eBq6PrVCwYUktLvb5Sx":{"id":"68351edepH9eBq6PrVCwYUktLvb5Sx","size":{"width":46.45,"height":28},"scale":1,"locked":false,"setting":{"scale":0.5717991199956544,"version":1746773215301,"autoSize":true,"direction":"horizontal-tb","paragraphs":[{"chars":[{"text":"2024","color":{"color":"#ffffff","opacity":1},"fontSize":34.9773186082413,"fontStyle":"normal","fontFamily":"Misans 中等","fontWeight":"normal","textStroke":false,"letterSpacing":0,"textDecoration":[],"textStrokeColor":{"color":"#44e296","opacity":1},"textStrokeWidth":10}],"textAlign":"start","lineHeight":1.4}],"textShadow":false,"defaultText":true,"textShadowBlur":10,"textShadowAngle":45,"textShadowColor":{"color":"#000000","opacity":0.4},"textShadowOffset":10},"visible":true,"category":"text","position":{"x":824.47,"y":287.125},"rotation":0},"68351edepVpd4wjSaN54y9omH7EytB":{"id":"68351edepVpd4wjSaN54y9omH7EytB","size":{"width":119.5,"height":50.01},"scale":1,"locked":false,"setting":{"blur":0,"fill":{"color":"#C1EADA","opacity":1},"path":"M0,0 L256,0 L256,256 L0,256 Z","scale":1,"shadow":{"blur":4,"show":false,"type":"outer","angle":90,"color":{"color":"#000000","opacity":0.25},"behind":true,"offset":4},"stroke":{"color":{"color":"#000000","opacity":1},"style":"solid","width":0,"radius":0},"version":1748227505152},"visible":true,"category":"shape","position":{"x":297.89666666666665,"y":276.115},"rotation":0},"68351eder1NqkzFyfM9aHx7RALQ5kq":{"id":"68351eder1NqkzFyfM9aHx7RALQ5kq","size":{"width":108,"height":25.2},"scale":1,"locked":false,"setting":{"scale":1,"version":1748226968273,"autoSize":true,"direction":"horizontal-tb","paragraphs":[{"chars":[{"text":"双击添加标题","color":{"color":"#000000","opacity":1},"fontSize":18,"fontStyle":"normal","fontFamily":"Misans 加粗","fontWeight":"normal","textStroke":false,"letterSpacing":0,"textDecoration":[],"textStrokeColor":{"color":"#44e296","opacity":1},"textStrokeWidth":10}],"textAlign":"start","lineHeight":1.4}],"textShadow":false,"defaultText":true,"textShadowBlur":10,"textShadowAngle":45,"textShadowColor":{"color":"#000000","opacity":0.4},"textShadowOffset":10},"visible":true,"category":"text","position":{"x":211.94,"y":396},"rotation":0},"68351ederAVLEPnd6DBiDK4xSQ8BvP":{"id":"68351ederAVLEPnd6DBiDK4xSQ8BvP","size":{"width":153.49,"height":50.39},"scale":1,"locked":false,"setting":{"scale":0.7729029172470115,"version":1748226719408,"autoSize":false,"direction":"horizontal-tb","paragraphs":[{"chars":[{"text":"双击此处输入正文内容,内容要求简单明了扼要说明,不必过于繁琐,保证阅读清晰度。","color":{"color":"#000000","opacity":1},"fontSize":15.525882659031195,"fontStyle":"normal","fontFamily":"Misans 常规","fontWeight":"normal","textStroke":false,"letterSpacing":0,"textDecoration":[],"textStrokeColor":{"color":"#44e296","opacity":1},"textStrokeWidth":10}],"textAlign":"start","lineHeight":1.4}],"textShadow":false,"defaultText":true,"textShadowBlur":10,"textShadowAngle":45,"textShadowColor":{"color":"#000000","opacity":0.4},"textShadowOffset":10},"visible":true,"category":"text","position":{"x":211.9438967052763,"y":430.2999319160899},"rotation":0},"68351edesX3sKb4WzBBBK3SPTrp8Fw":{"id":"68351edesX3sKb4WzBBBK3SPTrp8Fw","size":{"width":153.49,"height":50.39},"scale":1,"locked":false,"setting":{"scale":0.7729029172470115,"version":1748226983263,"autoSize":false,"direction":"horizontal-tb","paragraphs":[{"chars":[{"text":"双击此处输入正文内容,内容要求简单明了扼要说明,不必过于繁琐,保证阅读清晰度。","color":{"color":"#000000","opacity":1},"fontSize":15.525882659031193,"fontStyle":"normal","fontFamily":"Misans 常规","fontWeight":"normal","textStroke":false,"letterSpacing":0,"textDecoration":[],"textStrokeColor":{"color":"#44e296","opacity":1},"textStrokeWidth":10}],"textAlign":"start","lineHeight":1.4}],"textShadow":false,"defaultText":true,"textShadowBlur":10,"textShadowAngle":45,"textShadowColor":{"color":"#000000","opacity":0.4},"textShadowOffset":10},"visible":true,"category":"text","position":{"x":693.5699999999999,"y":155.85000000000002},"rotation":0},"68351edesk7yeQ1T2Gg5hiccE7ptG8":{"id":"68351edesk7yeQ1T2Gg5hiccE7ptG8","size":{"width":119.5,"height":50.01},"scale":1,"locked":false,"setting":{"blur":0,"fill":{"color":"#c1eada","opacity":1},"path":"M0,0 L256,0 L256,256 L0,256 Z","scale":1,"shadow":{"blur":4,"show":false,"type":"outer","angle":90,"color":{"color":"#000000","opacity":0.25},"behind":true,"offset":4},"stroke":{"color":{"color":"#000000","opacity":1},"style":"solid","width":0,"radius":0},"version":1748227497965},"visible":true,"category":"shape","position":{"x":176.17333333333335,"y":276.115},"rotation":0},"68351edeuEQ6a2qbThzMXxUQcjSPsn":{"id":"68351edeuEQ6a2qbThzMXxUQcjSPsn","size":{"width":149.56,"height":2},"scale":1,"locked":false,"setting":{"end":"none","type":"line","scale":1,"start":"none","points":[[0,0],[149.56073849777556,0]],"shadow":{"blur":4,"show":false,"angle":90,"color":{"color":"#000000","opacity":0.25},"behind":true,"offset":4},"stroke":{"cap":"butt","color":{"color":"#c8c8c8","opacity":1},"style":"dotted","width":2,"radius":0},"version":1746773483344,"category":"straight"},"visible":true,"category":"line","position":{"x":117.59859591345656,"y":404.91269469636796},"rotation":269.93},"68351edewEdkTdznoby5PXDfz1oeXg":{"id":"68351edewEdkTdznoby5PXDfz1oeXg","size":{"width":153.49,"height":50.39},"scale":1,"locked":false,"setting":{"scale":0.7729029172470115,"version":1748239243034,"autoSize":false,"direction":"horizontal-tb","paragraphs":[{"chars":[{"text":"双击此处输入正文内容,内容要求简单明了扼要说明,不必过于繁琐,保证阅读清晰度。","color":{"color":"#000000","opacity":1},"fontSize":15.525882659031193,"fontStyle":"normal","fontFamily":"Misans 常规","fontWeight":"normal","textStroke":false,"letterSpacing":0,"textDecoration":[],"textStrokeColor":{"color":"#44e296","opacity":1},"textStrokeWidth":10}],"textAlign":"start","lineHeight":1.4}],"textShadow":false,"defaultText":true,"textShadowBlur":10,"textShadowAngle":45,"textShadowColor":{"color":"#000000","opacity":0.4},"textShadowOffset":10},"visible":true,"category":"text","position":{"x":450.77,"y":155.85000000000002},"rotation":0},"68351edewcGkfVGCAg8Nn1hgPH3C3W":{"id":"68351edewcGkfVGCAg8Nn1hgPH3C3W","size":{"width":44.64,"height":28},"scale":1,"locked":false,"setting":{"scale":0.5717991199956544,"version":1746773181322,"autoSize":true,"direction":"horizontal-tb","paragraphs":[{"chars":[{"text":"2019","color":{"color":"#444444","opacity":1},"fontSize":34.9773186082413,"fontStyle":"normal","fontFamily":"Misans 中等","fontWeight":"normal","textStroke":false,"letterSpacing":0,"textDecoration":[],"textStrokeColor":{"color":"#44e296","opacity":1},"textStrokeWidth":10}],"textAlign":"start","lineHeight":1.4}],"textShadow":false,"defaultText":true,"textShadowBlur":10,"textShadowAngle":45,"textShadowColor":{"color":"#000000","opacity":0.4},"textShadowOffset":10},"visible":true,"category":"text","position":{"x":211.94,"y":287.125},"rotation":0}},"background":{"locked":false}}},"orders":["cmb5vol9d062yh0o6hwyn9ksz"]}}}