{"code":0,"msg":"ok","data":{"id":"cmbqc79va00503c3e92dhhxxr","title":"蓝橙现代课程创新点研究报告","width":960,"height":540,"priceStrategy":"paid","snapshot":"https://cdn.aitubiao.com/cover/cmb60mcur06ehh0o6d4ft2ndj_1749434357973.png","createdAt":"2025-06-10T09:44:08.062Z","updatedAt":"2025-06-11T09:05:51.122Z","dimension":"PPT","tags":[{"id":"cmbrq5yxx000lcj3e27o22pkk","name":"柱状图","dimensionId":8,"dimension":{"scopes":["ppt"]}},{"id":"cmbrq5yxx000jcj3egz0z8cwd","name":"饼图","dimensionId":8,"dimension":{"scopes":["ppt"]}},{"id":"cmbrq5yxz000scj3e81hp8l69","name":"教育培训","dimensionId":9,"dimension":{"scopes":["ppt"]}},{"id":"cmbrq5yxz000rcj3eaxcte4m4","name":"研究报告","dimensionId":9,"dimension":{"scopes":["ppt"]}},{"id":"cmbrq5yy0000vcj3eg5f2axr5","name":"单图表","dimensionId":10,"dimension":{"scopes":["ppt"]}}],"author":{"id":"clzb5ewqk0003j5yc55w8zbuk","name":"coveabc","avatar":null,"tier":{"id":"ckxtg2o0j00019zue6g8t68kc","name":"会员用户"}},"data":{"pages":{"68353f3bjdEM9Jb6NSvPVBjBPgTWZh":{"id":"68353f3bjdEM9Jb6NSvPVBjBPgTWZh","name":"","next":null,"prev":null,"size":{"width":960,"height":540},"theme":{"colors":[]},"locked":false,"orders":["68353f3b75hcFV3WCFu9d1QvZZWjjp","68353f3b5X72a6YZndXGJvySpqabk3","68353f3bpwvavCFJujVw9jUgfNZeYn","68353f3b7BQwE1Ztf7ztbzQBAWjS4L","68353f3brzahsEVpUErx75JsURvNPA","68353f3bdTh3NezYNsztnuFT9VKFKE","68353f3biogZckdfmE2nnA3v5hhnQj","68353f3b4hpAc4AWk5mBjx62Kt9xBQ","68353f3b3wj7X42pxVQkWtRHmQxYyk"],"visible":true,"elements":{"68353f3b3wj7X42pxVQkWtRHmQxYyk":{"id":"68353f3b3wj7X42pxVQkWtRHmQxYyk","size":{"width":219.25,"height":44.8},"scale":1,"locked":false,"pageId":"68353f3bjdEM9Jb6NSvPVBjBPgTWZh","setting":{"scale":1,"version":1745898940995,"children":["68353f3bfSggDERrXnhKpvGr4v21Nr","68353f3bcrSeCNh5sngm78FdZvuRX3"]},"visible":true,"category":"group","position":{"x":23.95,"y":17.36},"rotation":0},"68353f3b4hpAc4AWk5mBjx62Kt9xBQ":{"id":"68353f3b4hpAc4AWk5mBjx62Kt9xBQ","size":{"width":540.65,"height":432},"scale":1,"locked":false,"pageId":"68353f3bjdEM9Jb6NSvPVBjBPgTWZh","setting":{"data":[[["季度","线下课时占比","线上课时占比","完课率"],["Q1","70%","30%","85%"],["Q2","55%","45%","80%"],["Q3","40%","60%","75%"],["Q4","35%","65%","72%"]]],"pipe":"cross","props":{"map":[{"name":"X轴对象","type":"","index":0,"function":"objCol","isLegend":false,"xAxisIndex":0,"configurable":true},{"name":"数值列","type":"bar","index":1,"function":"vCol","isLegend":false,"yAxisIndex":0,"configurable":true},{"name":"数值列","type":"bar","index":2,"function":"vCol","isLegend":false,"yAxisIndex":0,"configurable":true},{"name":"数值列","type":"line","index":3,"function":"vCol","isLegend":false,"yAxisIndex":1,"configurable":true}],"axis":{"show":true,"xAxis":[{"grid":{"show":false,"type":"solid","color":{"color":"#D9D9D9","opacity":1},"width":1},"line":{"show":false,"color":{"color":"#4D4D4D","opacity":1},"width":1},"type":"category","label":{"show":true,"angle":0,"color":{"color":"#000000","opacity":1},"fontSize":13.074074074074074,"direction":"auto","fontFamily":"Misans 中等"},"position":"bottom"}],"yAxis":[{"grid":{"show":true,"type":"dotted","color":{"color":"#cccccc","opacity":1},"width":1},"line":{"show":true,"color":{"color":"#bababa","opacity":1},"width":1},"type":"value","label":{"show":true,"angle":0,"color":{"color":"#000000","opacity":1},"suffix":"","fontSize":12.925925925925926,"fontFamily":"Misans 常规"},"range":[null,null],"position":"left","stepOfLabel":"auto"},{"grid":{"show":false,"type":"solid","color":{"color":"#D9D9D9","opacity":1},"width":1},"line":{"show":true,"color":{"color":"#bababa","opacity":1},"width":1},"type":"value","label":{"show":true,"angle":0,"color":{"color":"#000000","opacity":1},"suffix":"%","fontSize":13.074074074074074,"fontFamily":"Misans 常规"},"range":[null,null],"position":"right","stepOfLabel":"auto"}]},"fill":{"props":[{"color":{"color":"#0f7cff","opacity":1},"border":{"type":"solid","color":null,"width":0},"shadow":{"blur":3,"show":false,"type":"inner","angle":0,"color":{"color":"#5956F4","opacity":0.4},"radius":0},"symbol":{"url":""},"texture":{"url":""}},{"color":{"color":"#6ae5b0","opacity":1},"border":{"type":"solid","color":null,"width":0},"shadow":{"blur":3,"show":false,"type":"inner","angle":0,"color":{"color":"#5956F4","opacity":0.4},"radius":0},"symbol":{"url":""},"texture":{"url":""}},{"color":{"color":"#fba23a","opacity":1},"border":{"type":"solid","color":null,"width":0},"shadow":{"blur":3,"show":false,"type":"inner","angle":0,"color":{"color":"#5956F4","opacity":0.4},"radius":0},"symbol":{"url":""},"texture":{"url":""}}],"controlType":"multiple"},"type":"mixed-line-stacked-column","label":{"show":false,"overlap":false,"barLabel":{"show":false,"color":{"color":"#ffffff","opacity":1},"suffix":"","fontSize":14,"fontFamily":"Misans","positionChoice":"center"},"highlight":false,"lineLabel":{"show":false,"color":{"color":"#333333","opacity":1},"suffix":"","fontSize":14,"fontFamily":"Misans","positionChoice":"top"}},"title":{"show":false,"subTitle":{"show":false,"text":"副标题","color":{"color":"#333333","opacity":1},"fontSize":16,"fontFamily":"Misans"},"mainTitle":{"show":true,"text":"主标题","color":{"color":"#333333","opacity":1},"fontSize":24,"position":{"x":"left","y":"top"},"fontFamily":"Misans"}},"legend":{"show":true,"color":{"color":"#333333","opacity":1},"display":"horizontal","fontSize":12,"position":{"x":"center","y":"top"},"fontFamily":"Misans 常规"},"display":{"bar":{"border":{"type":"solid","color":null,"width":0,"radius":[4,4,4,4]},"widthPercent":0.5},"line":{"type":"straight","width":5,"endPoint":{"fill":{"color":"#ffffff","opacity":1},"color":null,"width":2,"radius":4}}},"padding":{"top":20,"left":24,"right":24,"bottom":23},"tooltip":true,"animation":{"loop":false,"show":false,"duration":2,"endPause":1,"moveStyle":null,"startDelay":0,"transition":false},"background":{"blur":0,"show":false,"color":{"color":"#ffffff","opacity":1},"border":{"radius":0},"texture":""},"numberFormat":{"decimalPlaces":null,"separatorType":"1000.00"}},"scale":1.08,"version":1745896280187},"visible":true,"category":"chart","position":{"x":427.82,"y":62.16},"rotation":0},"68353f3b5X72a6YZndXGJvySpqabk3":{"id":"68353f3b5X72a6YZndXGJvySpqabk3","size":{"width":168.0448335980452,"height":187.40078301771533},"scale":1,"locked":false,"pageId":"68353f3bjdEM9Jb6NSvPVBjBPgTWZh","setting":{"data":[[["名称","进度"],["直播答疑使用率","90"]]],"pipe":"key_value","props":{"map":[{"name":"名称","type":"","index":0,"function":"objCol","isLegend":true,"xAxisIndex":0,"configurable":true},{"name":"值","type":"pie","index":1,"function":"vCol","isLegend":false,"yAxisIndex":0,"configurable":true}],"fill":{"props":[{"color":{"color":{"type":"linear","angle":312,"colorStops":[{"color":"#00d373","offset":0.013392857142857142,"opacity":1},{"color":"#c4ff9e","offset":0.9955357142857143,"opacity":1}]},"opacity":1},"border":{"type":"solid","color":{"color":"#598c3f","opacity":1},"width":0},"shadow":{"blur":4,"show":false,"type":"outer","angle":77,"color":{"color":"#0300a9","opacity":0.5},"radius":4},"texture":{"url":""}}],"controlType":"single"},"type":"donut-progress","label":{"show":true,"overlap":false,"highlight":false,"textLabel":{"show":true,"color":{"color":"#000000","opacity":1},"fontSize":29.651934255510728,"fontFamily":"Misans 中等"},"numberLabel":{"show":true,"color":{"color":"#000000","opacity":1},"fontSize":58.35497260646281,"fontFamily":"Misans 加粗"}},"title":{"show":true,"subTitle":{"show":false,"text":"副标题","color":{"color":"#333333","opacity":1},"fontSize":16,"fontFamily":"Misans"},"mainTitle":{"show":false,"text":"圆环进度图","color":{"color":"#333333","opacity":1},"fontSize":24,"position":{"x":"center","y":"top"},"fontFamily":"Misans"}},"legend":{"show":false,"color":{"color":"#333333","opacity":1},"display":"horizontal","fontSize":14,"position":{"x":"center","y":"bottom"},"fontFamily":"Misans"},"display":{"pie":{"border":{"type":"solid","color":null,"width":0,"radius":0},"startAngle":0,"gapPercentage":10,"backgroundColor":{"color":"#f0f0f0","opacity":1},"rotateDirection":"clockwise","innerRadiusRatio":0.75}},"padding":{"top":20,"left":24,"right":24,"bottom":23},"tooltip":true,"animation":{"loop":false,"show":false,"duration":2,"endPause":1,"moveStyle":null,"startDelay":0,"transition":false},"background":{"blur":0,"show":false,"color":{"color":"#ffffff","opacity":1},"border":{"radius":0},"texture":""},"numberFormat":{"decimalPlaces":null,"separatorType":"1000.00"}},"scale":0.4046953529775155,"version":1745895452231},"visible":true,"category":"chart","position":{"x":23.950000000000003,"y":97.76500000000003},"rotation":0},"68353f3b75hcFV3WCFu9d1QvZZWjjp":{"id":"68353f3b75hcFV3WCFu9d1QvZZWjjp","size":{"width":423.62,"height":198.8},"scale":1,"locked":false,"pageId":"68353f3bjdEM9Jb6NSvPVBjBPgTWZh","setting":{"blur":0,"fill":{"color":"#ffffff","opacity":1},"path":"M0,0 L256,0 L256,256 L0,256 Z","scale":0.5590807169763661,"shadow":{"blur":14,"show":true,"type":"outer","angle":50,"color":{"color":"#cbecd2","opacity":0.5},"behind":true,"offset":10},"stroke":{"color":{"color":"#000000","opacity":1},"style":"solid","width":0,"radius":8},"version":1745896594159},"visible":true,"category":"shape","position":{"x":20.46,"y":92.06500000000003},"rotation":0},"68353f3b7BQwE1Ztf7ztbzQBAWjS4L":{"id":"68353f3b7BQwE1Ztf7ztbzQBAWjS4L","size":{"width":228.94,"height":69.12},"scale":1,"locked":false,"pageId":"68353f3bjdEM9Jb6NSvPVBjBPgTWZh","setting":{"scale":0.7729029172470115,"version":1746785229006,"autoSize":false,"direction":"horizontal-tb","paragraphs":[{"chars":[{"text":"定期开展在线直播答疑，打破时空限制，增强互动，及时解疑，提高学习效果与满意度。","color":{"color":"#616161","opacity":1},"fontSize":21.29306479671442,"fontStyle":"normal","fontFamily":"Misans 中等","fontWeight":"normal","textStroke":false,"letterSpacing":0,"textDecoration":[],"textStrokeColor":{"color":"#44e296","opacity":1},"textStrokeWidth":10}],"textAlign":"start","lineHeight":1.4}],"textShadow":false,"defaultText":false,"textShadowBlur":10,"textShadowAngle":45,"textShadowColor":{"color":"#000000","opacity":0.4},"textShadowOffset":10},"visible":true,"category":"text","position":{"x":211.65,"y":195.71},"rotation":0},"68353f3bcrSeCNh5sngm78FdZvuRX3":{"id":"68353f3bcrSeCNh5sngm78FdZvuRX3","size":{"width":10,"height":30.8},"scale":1,"locked":false,"pageId":"68353f3bjdEM9Jb6NSvPVBjBPgTWZh","parent":"68353f3b3wj7X42pxVQkWtRHmQxYyk","setting":{"blur":0,"fill":{"color":"#0f7cff","opacity":1},"path":"M0,0 L256,0 L256,256 L0,256 Z","scale":0.11153699026754178,"shadow":{"blur":4,"show":false,"type":"outer","angle":90,"color":{"color":"#000000","opacity":0.25},"behind":true,"offset":4},"stroke":{"color":{"color":"#000000","opacity":1},"style":"solid","width":0,"radius":12},"version":1745804403957},"visible":true,"category":"shape","position":{"x":0,"y":7},"rotation":0},"68353f3bdTh3NezYNsztnuFT9VKFKE":{"id":"68353f3bdTh3NezYNsztnuFT9VKFKE","size":{"width":210.6,"height":54.98},"scale":1,"locked":false,"pageId":"68353f3bjdEM9Jb6NSvPVBjBPgTWZh","setting":{"scale":0.7729029172470115,"version":1746695167268,"autoSize":false,"direction":"horizontal-tb","paragraphs":[{"chars":[{"text":"引入AI批改作业，优化教学反馈","color":{"color":"#000000","opacity":1},"fontSize":25.412352890161465,"fontStyle":"normal","fontFamily":"Misans 加粗","fontWeight":"normal","textStroke":false,"letterSpacing":0,"textDecoration":[],"textStrokeColor":{"color":"#44e296","opacity":1},"textStrokeWidth":10}],"textAlign":"start","lineHeight":1.4}],"textShadow":false,"defaultText":false,"textShadowBlur":10,"textShadowAngle":45,"textShadowColor":{"color":"#000000","opacity":0.4},"textShadowOffset":10},"visible":true,"category":"text","position":{"x":211.65,"y":335.97},"rotation":0},"68353f3bfSggDERrXnhKpvGr4v21Nr":{"id":"68353f3bfSggDERrXnhKpvGr4v21Nr","size":{"width":192,"height":44.8},"scale":1,"locked":false,"pageId":"68353f3bjdEM9Jb6NSvPVBjBPgTWZh","parent":"68353f3b3wj7X42pxVQkWtRHmQxYyk","setting":{"scale":1,"version":1745908419122,"autoSize":true,"direction":"horizontal-tb","paragraphs":[{"chars":[{"text":"课程创新亮点","color":{"color":"#000000","opacity":1},"fontSize":32,"fontStyle":"normal","fontFamily":"Misans 加粗","fontWeight":"normal","textStroke":false,"letterSpacing":0,"textDecoration":[],"textStrokeColor":{"color":"#44e296","opacity":1},"textStrokeWidth":10}],"textAlign":"start","lineHeight":1.4}],"textShadow":false,"defaultText":false,"textShadowBlur":10,"textShadowAngle":45,"textShadowColor":{"color":"#000000","opacity":0.4},"textShadowOffset":10},"visible":true,"category":"text","position":{"x":27.25,"y":0},"rotation":0},"68353f3biogZckdfmE2nnA3v5hhnQj":{"id":"68353f3biogZckdfmE2nnA3v5hhnQj","size":{"width":223.37,"height":69.12},"scale":1,"locked":false,"pageId":"68353f3bjdEM9Jb6NSvPVBjBPgTWZh","setting":{"scale":0.7729029172470115,"version":1746785232494,"autoSize":false,"direction":"horizontal-tb","paragraphs":[{"chars":[{"text":"借助人工智能技术实现作业智能批改与分析，减轻教师负担，提升学生学习效果。","color":{"color":"#616161","opacity":1},"fontSize":21.29306479671442,"fontStyle":"normal","fontFamily":"Misans 中等","fontWeight":"normal","textStroke":false,"letterSpacing":0,"textDecoration":[],"textStrokeColor":{"color":"#44e296","opacity":1},"textStrokeWidth":10}],"textAlign":"start","lineHeight":1.4}],"textShadow":false,"defaultText":false,"textShadowBlur":10,"textShadowAngle":45,"textShadowColor":{"color":"#000000","opacity":0.4},"textShadowOffset":10},"visible":true,"category":"text","position":{"x":211.65,"y":405.57},"rotation":0},"68353f3bpwvavCFJujVw9jUgfNZeYn":{"id":"68353f3bpwvavCFJujVw9jUgfNZeYn","size":{"width":193.62,"height":54.98},"scale":1,"locked":false,"pageId":"68353f3bjdEM9Jb6NSvPVBjBPgTWZh","setting":{"scale":0.7729029172470115,"version":1746695116132,"autoSize":false,"direction":"horizontal-tb","paragraphs":[{"chars":[{"text":"实施直播答疑，提升互动效率","color":{"color":"#000000","opacity":1},"fontSize":25.412352890161465,"fontStyle":"normal","fontFamily":"Misans 加粗","fontWeight":"normal","textStroke":false,"letterSpacing":0,"textDecoration":[],"textStrokeColor":{"color":"#44e296","opacity":1},"textStrokeWidth":10}],"textAlign":"start","lineHeight":1.4}],"textShadow":false,"defaultText":false,"textShadowBlur":10,"textShadowAngle":45,"textShadowColor":{"color":"#000000","opacity":0.4},"textShadowOffset":10},"visible":true,"category":"text","position":{"x":211.65,"y":127.31},"rotation":0},"68353f3brzahsEVpUErx75JsURvNPA":{"id":"68353f3brzahsEVpUErx75JsURvNPA","size":{"width":168,"height":187.06},"scale":1,"locked":false,"pageId":"68353f3bjdEM9Jb6NSvPVBjBPgTWZh","setting":{"data":[[["名称","进度"],["Ai批改准确率","92"]]],"pipe":"key_value","props":{"map":[{"name":"名称","type":"","index":0,"function":"objCol","isLegend":true,"xAxisIndex":0,"configurable":true},{"name":"值","type":"pie","index":1,"function":"vCol","isLegend":false,"yAxisIndex":0,"configurable":true}],"fill":{"props":[{"color":{"color":"#0f7cff","opacity":1},"border":{"type":"solid","color":null,"width":0},"shadow":{"blur":4,"show":false,"type":"inner","angle":77,"color":{"color":"#0300a9","opacity":0.5},"radius":4},"texture":{"url":""}}],"controlType":"single"},"type":"donut-progress","label":{"show":true,"overlap":false,"highlight":false,"textLabel":{"show":true,"color":{"color":"#333333","opacity":1},"fontSize":22.882216983123556,"fontFamily":"Misans"},"numberLabel":{"show":true,"color":{"color":"#333333","opacity":1},"fontSize":46,"fontFamily":"Misans 特粗"}},"title":{"show":false,"subTitle":{"show":false,"text":"副标题","color":{"color":"#333333","opacity":1},"fontSize":16,"fontFamily":"Misans"},"mainTitle":{"show":true,"text":"圆环进度图","color":{"color":"#333333","opacity":1},"fontSize":24,"position":{"x":"center","y":"top"},"fontFamily":"Misans"}},"legend":{"show":false,"color":{"color":"#333333","opacity":1},"display":"horizontal","fontSize":14,"position":{"x":"center","y":"bottom"},"fontFamily":"Misans"},"display":{"pie":{"border":{"type":"solid","color":null,"width":0,"radius":0},"startAngle":0,"gapPercentage":0,"backgroundColor":null,"rotateDirection":"clockwise","innerRadiusRatio":0.75}},"padding":{"top":20,"left":24,"right":24,"bottom":23},"tooltip":true,"animation":{"loop":false,"show":false,"duration":2,"endPause":1,"moveStyle":null,"startDelay":0,"transition":false},"background":{"blur":0,"show":false,"color":{"color":"#ffffff","opacity":1},"border":{"radius":0},"texture":""},"numberFormat":{"decimalPlaces":null,"separatorType":"1000.00"}},"scale":0.5312883737455665,"version":1745895457227},"visible":true,"category":"chart","position":{"x":23.95,"y":307.1},"rotation":0}},"projectId":"","background":{"color":"#ffffff","locked":false}}},"orders":["68353f3bjdEM9Jb6NSvPVBjBPgTWZh"]}}}